Workbook
Name conflict_and_fragility_1: Conflict!$J$7:$AA$225
Name food_security_1: Food!$J$7:$V$225
Name Health: Conflict!#REF!
Name Health: Food!#REF!
Name Health: Macro!#REF!
Name Health: 'Natural Hazard'!#REF!
Name Health: Socioeconomic!#REF!
Name health_1: Health!$J$7:$R$225
Name indicators_list: 'Data Dictionary'!$B$7:$R$35
Name macro_fiscal_1: Macro!$J$7:$P$225
Name natural_hazard_1: 'Natural Hazard'!$J$7:$X$225
Name reliabilitysheet: 'Compound Alert'!#REF!
Name reliabilitysheet_1: 'Data Reliability'!$E$5:$T$223
Name socioeconomic_vulnerability_1: Socioeconomic!$J$7:$T$225

Sheet Landing

Sheet Dashboard
B2: COMPOUND RISK MONITOR: Methodology Options
B4: Click on the rectangles, and then the appearing arrow, to see and select options. If display does not refresh you may need to enable automatic calculations (scroll to right for instructions).
B6: Snapshot | J6: Dimensions → Overall Dimensions
B7: Overall Alert is a synthesis of underlying vulnerability and emerging threat | J7: How to calculate overall alert dimensions from underlying vulnerability and emerging threat dimensions? (Will only effect Overall Alert snapshot)
B8: Overall Alert | G8: Select one | J8: AGGREGATE: Geometric Mean | O8: Select one
B10: Indicators → Dimensions | J10: Count medium values as half flags
B11: How to calculate underlying and emerging dimensions from indicators | J11: For overall alert, high values are >7 and medium values are >5. For underlying and emerging, high is 10, and medium is >7.
B12: Max value (default) Select the maximum value across the suite of grouped indicators. | G12: Select one | J12: Yes (default) | O12: Select one
B15: =CONCATENATE("— ",UPPER(B8)," — ") -> — OVERALL ALERT —
A40: Blank1 | B40: Country Name | C40: Country Code | D40: Region | E40: Lending Group | F40: Blank2 | G40: =CONCATENATE(B8, " Flags") -> Overall Alert Flags | I40: Blank3 | J40: Health | K40: Food Security | L40: Macro Fiscal | M40: Socioecon. Vulnerability | N40: Natural Hazards | O40: Conflict Fragility
A41: Blank1 | B41: Country Name | C41: Country Code | D41: Region | E41: Lending Group | F41: Blank2 | G41: Flags | H41: B1 | I41: Blank3 | J41: Health | K41: Food Security | L41: Macro Fiscal | M41: Socioecon Vulnerability | N41: Natural Hazards | O41: Conflict Fragility | P41: Blank4
A42: 1 | B42: ='Compound Alert'!B194 -> Chad | C42: ='Compound Alert'!C194 -> TCD | D42: ='Compound Alert'!D194 -> SSF Sub-Saharan Africa | E42: ='Compound Alert'!E194 -> IDA | F42: ='Compound Alert'!F194 -> 189 | G42: =IF($B$8="Overall Alert",'Compound Alert'!G194,IF($B$8="Underlying Vulnerability",'Compound Alert'!J194,IF($B$8="Emerging Threat",'Compound Alert'!M194))) -> 3.5 | H42: =IF($B$8="Overall Alert",'Compound Alert'!H194,IF($B$8="Underlying Vulnerability",'Compound Alert'!K194,IF($B$8="Emerging Threat",'Compound Alert'!N194))) -> 3.5 | I42: =ROUNDDOWN(G42,0) -> 3 | J42: =IF( $B$8="Overall Alert",IF( 'Compound Alert'!R194 >= 7, "HIGH",IF( 'Compound Alert'!R194 >= 5, "MED","LOW")), IF( $B$8="Underlying Vulnerability", IF( 'Compound Alert'!Y194 >= 10, "HIGH",IF( 'Compound Alert'!Y194 >= 7, "MED","LOW")),IF( $B$8="Emerging Threat", IF( 'Compound Alert'!AF194 >= 10, "HIGH",IF( 'Compound Alert'!AF194 >= 7, "MED","LOW"))))) -> HIGH | K42: =IF( $B$8="Overall Alert",IF( 'Compound Alert'!S194 >= 7, "HIGH",IF( 'Compound Alert'!S194 >= 5, "MED","LOW")), IF( $B$8="Underlying Vulnerability", IF( 'Compound Alert'!Z194 >= 10, "HIGH",IF( 'Compound Alert'!Z194 >= 7, "MED","LOW")),IF( $B$8="Emerging Threat", IF( 'Compound Alert'!AG194 >= 10, "HIGH",IF( 'Compound Alert'!AG194 >= 7, "MED","LOW"))))) -> HIGH | L42: =IF( $B$8="Overall Alert",IF( 'Compound Alert'!T194 >= 7, "HIGH",IF( 'Compound Alert'!T194 >= 5, "MED","LOW")), IF( $B$8="Underlying Vulnerability", IF( 'Compound Alert'!AA194 >= 10, "HIGH",IF( 'Compound Alert'!AA194 >= 7, "MED","LOW")),IF( $B$8="Emerging Threat", IF( 'Compound Alert'!AH194 >= 10, "HIGH",IF( 'Compound Alert'!AH194 >= 7, "MED","LOW"))))) -> MED | M42: =IF( $B$8="Overall Alert",IF( 'Compound Alert'!U194 >= 7, "HIGH",IF( 'Compound Alert'!U194 >= 5, "MED","LOW")), IF( $B$8="Underlying Vulnerability", IF( 'Compound Alert'!AB194 >= 10, "HIGH",IF( 'Compound Alert'!AB194 >= 7, "MED","LOW")),IF( $B$8="Emerging Threat", IF( 'Compound Alert'!AI194 >= 10, "HIGH",IF( 'Compound Alert'!AI194 >= 7, "MED","LOW"))))) -> LOW | N42: =IF( $B$8="Overall Alert",IF( 'Compound Alert'!V194 >= 7, "HIGH",IF( 'Compound Alert'!V194 >= 5, "MED","LOW")), IF( $B$8="Underlying Vulnerability", IF( 'Compound Alert'!AC194 >= 10, "HIGH",IF( 'Compound Alert'!AC194 >= 7, "MED","LOW")),IF( $B$8="Emerging Threat", IF( 'Compound Alert'!AJ194 >= 10, "HIGH",IF( 'Compound Alert'!AJ194 >= 7, "MED","LOW"))))) -> HIGH | O42: =IF( $B$8="Overall Alert",IF( 'Compound Alert'!W194 >= 7, "HIGH",IF( 'Compound Alert'!W194 >= 5, "MED","LOW")), IF( $B$8="Underlying Vulnerability", IF( 'Compound Alert'!AD194 >= 10, "HIGH",IF( 'Compound Alert'!AD194 >= 7, "MED","LOW")),IF( $B$8="Emerging Threat", IF( 'Compound Alert'!AK194 >= 10, "HIGH",IF( 'Compound Alert'!AK194 >= 7, "MED","LOW"))))) -> LOW
A43: 2 | B43: ='Compound Alert'!B181 -> Somalia | C43: ='Compound Alert'!C181 -> SOM | D43: ='Compound Alert'!D181 -> SSF Sub-Saharan Africa | E43: ='Compound Alert'!E181 -> IDA | F43: ='Compound Alert'!F181 -> 176 | G43: =IF($B$8="Overall Alert",'Compound Alert'!G181,IF($B$8="Underlying Vulnerability",'Compound Alert'!J181,IF($B$8="Emerging Threat",'Compound Alert'!M181))) -> 2.5 | H43: =IF($B$8="Overall Alert",'Compound Alert'!H181,IF($B$8="Underlying Vulnerability",'Compound Alert'!K181,IF($B$8="Emerging Threat",'Compound Alert'!N181))) -> 2.5 | I43: =ROUNDDOWN(G43,0) -> 2 | J43: =IF( $B$8="Overall Alert",IF( 'Compound Alert'!R181 >= 7, "HIGH",IF( 'Compound Alert'!R181 >= 5, "MED","LOW")), IF( $B$8="Underlying Vulnerability", IF( 'Compound Alert'!Y181 >= 10, "HIGH",IF( 'Compound Alert'!Y181 >= 7, "MED","LOW")),IF( $B$8="Emerging Threat", IF( 'Compound Alert'!AF181 >= 10, "HIGH",IF( 'Compound Alert'!AF181 >= 7, "MED","LOW"))))) -> LOW | K43: =IF( $B$8="Overall Alert",IF( 'Compound Alert'!S181 >= 7, "HIGH",IF( 'Compound Alert'!S181 >= 5, "MED","LOW")), IF( $B$8="Underlying Vulnerability", IF( 'Compound Alert'!Z181 >= 10, "HIGH",IF( 'Compound Alert'!Z181 >= 7, "MED","LOW")),IF( $B$8="Emerging Threat", IF( 'Compound Alert'!AG181 >= 10, "HIGH",IF( 'Compound Alert'!AG181 >= 7, "MED","LOW"))))) -> HIGH | L43: =IF( $B$8="Overall Alert",IF( 'Compound Alert'!T181 >= 7, "HIGH",IF( 'Compound Alert'!T181 >= 5, "MED","LOW")), IF( $B$8="Underlying Vulnerability", IF( 'Compound Alert'!AA181 >= 10, "HIGH",IF( 'Compound Alert'!AA181 >= 7, "MED","LOW")),IF( $B$8="Emerging Threat", IF( 'Compound Alert'!AH181 >= 10, "HIGH",IF( 'Compound Alert'!AH181 >= 7, "MED","LOW"))))) -> MED | M43: =IF( $B$8="Overall Alert",IF( 'Compound Alert'!U181 >= 7, "HIGH",IF( 'Compound Alert'!U181 >= 5, "MED","LOW")), IF( $B$8="Underlying Vulnerability", IF( 'Compound Alert'!AB181 >= 10, "HIGH",IF( 'Compound Alert'!AB181 >= 7, "MED","LOW")),IF( $B$8="Emerging Threat", IF( 'Compound Alert'!AI181 >= 10, "HIGH",IF( 'Compound Alert'!AI181 >= 7, "MED","LOW"))))) -> LOW | N43: =IF( $B$8="Overall Alert",IF( 'Compound Alert'!V181 >= 7, "HIGH",IF( 'Compound Alert'!V181 >= 5, "MED","LOW")), IF( $B$8="Underlying Vulnerability", IF( 'Compound Alert'!AC181 >= 10, "HIGH",IF( 'Compound Alert'!AC181 >= 7, "MED","LOW")),IF( $B$8="Emerging Threat", IF( 'Compound Alert'!AJ181 >= 10, "HIGH",IF( 'Compound Alert'!AJ181 >= 7, "MED","LOW"))))) -> HIGH | O43: =IF( $B$8="Overall Alert",IF( 'Compound Alert'!W181 >= 7, "HIGH",IF( 'Compound Alert'!W181 >= 5, "MED","LOW")), IF( $B$8="Underlying Vulnerability", IF( 'Compound Alert'!AD181 >= 10, "HIGH",IF( 'Compound Alert'!AD181 >= 7, "MED","LOW")),IF( $B$8="Emerging Threat", IF( 'Compound Alert'!AK181 >= 10, "HIGH",IF( 'Compound Alert'!AK181 >= 7, "MED","LOW"))))) -> LOW
A44: 3 | B44: ='Compound Alert'!B174 -> Sudan | C44: ='Compound Alert'!C174 -> SDN | D44: ='Compound Alert'!D174 -> SSF Sub-Saharan Africa | E44: ='Compound Alert'!E174 -> IDA | F44: ='Compound Alert'!F174 -> 169 | G44: =IF($B$8="Overall Alert",'Compound Alert'!G174,IF($B$8="Underlying Vulnerability",'Compound Alert'!J174,IF($B$8="Emerging Threat",'Compound Alert'!M174))) -> 1.5 | H44: =IF($B$8="Overall Alert",'Compound Alert'!H174,IF($B$8="Underlying Vulnerability",'Compound Alert'!K174,IF($B$8="Emerging Threat",'Compound Alert'!N174))) -> 1.5 | I44: =ROUNDDOWN(G44,0) -> 1 | J44: =IF( $B$8="Overall Alert",IF( 'Compound Alert'!R174 >= 7, "HIGH",IF( 'Compound Alert'!R174 >= 5, "MED","LOW")), IF( $B$8="Underlying Vulnerability", IF( 'Compound Alert'!Y174 >= 10, "HIGH",IF( 'Compound Alert'!Y174 >= 7, "MED","LOW")),IF( $B$8="Emerging Threat", IF( 'Compound Alert'!AF174 >= 10, "HIGH",IF( 'Compound Alert'!AF174 >= 7, "MED","LOW"))))) -> LOW | K44: =IF( $B$8="Overall Alert",IF( 'Compound Alert'!S174 >= 7, "HIGH",IF( 'Compound Alert'!S174 >= 5, "MED","LOW")), IF( $B$8="Underlying Vulnerability", IF( 'Compound Alert'!Z174 >= 10, "HIGH",IF( 'Compound Alert'!Z174 >= 7, "MED","LOW")),IF( $B$8="Emerging Threat", IF( 'Compound Alert'!AG174 >= 10, "HIGH",IF( 'Compound Alert'!AG174 >= 7, "MED","LOW"))))) -> HIGH | L44: =IF( $B$8="Overall Alert",IF( 'Compound Alert'!T174 >= 7, "HIGH",IF( 'Compound Alert'!T174 >= 5, "MED","LOW")), IF( $B$8="Underlying Vulnerability", IF( 'Compound Alert'!AA174 >= 10, "HIGH",IF( 'Compound Alert'!AA174 >= 7, "MED","LOW")),IF( $B$8="Emerging Threat", IF( 'Compound Alert'!AH174 >= 10, "HIGH",IF( 'Compound Alert'!AH174 >= 7, "MED","LOW"))))) -> MED | M44: =IF( $B$8="Overall Alert",IF( 'Compound Alert'!U174 >= 7, "HIGH",IF( 'Compound Alert'!U174 >= 5, "MED","LOW")), IF( $B$8="Underlying Vulnerability", IF( 'Compound Alert'!AB174 >= 10, "HIGH",IF( 'Compound Alert'!AB174 >= 7, "MED","LOW")),IF( $B$8="Emerging Threat", IF( 'Compound Alert'!AI174 >= 10, "HIGH",IF( 'Compound Alert'!AI174 >= 7, "MED","LOW"))))) -> LOW | N44: =IF( $B$8="Overall Alert",IF( 'Compound Alert'!V174 >= 7, "HIGH",IF( 'Compound Alert'!V174 >= 5, "MED","LOW")), IF( $B$8="Underlying Vulnerability", IF( 'Compound Alert'!AC174 >= 10, "HIGH",IF( 'Compound Alert'!AC174 >= 7, "MED","LOW")),IF( $B$8="Emerging Threat", IF( 'Compound Alert'!AJ174 >= 10, "HIGH",IF( 'Compound Alert'!AJ174 >= 7, "MED","LOW"))))) -> LOW | O44: =IF( $B$8="Overall Alert",IF( 'Compound Alert'!W174 >= 7, "HIGH",IF( 'Compound Alert'!W174 >= 5, "MED","LOW")), IF( $B$8="Underlying Vulnerability", IF( 'Compound Alert'!AD174 >= 10, "HIGH",IF( 'Compound Alert'!AD174 >= 7, "MED","LOW")),IF( $B$8="Emerging Threat", IF( 'Compound Alert'!AK174 >= 10, "HIGH",IF( 'Compound Alert'!AK174 >= 7, "MED","LOW"))))) -> LOW
A45: 4 | B45: ='Compound Alert'!B136 -> Myanmar | C45: ='Compound Alert'!C136 -> MMR | D45: ='Compound Alert'!D136 -> EAS East Asia & Pacific | E45: ='Compound Alert'!E136 -> IDA | F45: ='Compound Alert'!F136 -> 131 | G45: =IF($B$8="Overall Alert",'Compound Alert'!G136,IF($B$8="Underlying Vulnerability",'Compound Alert'!J136,IF($B$8="Emerging Threat",'Compound Alert'!M136))) -> 2.5 | H45: =IF($B$8="Overall Alert",'Compound Alert'!H136,IF($B$8="Underlying Vulnerability",'Compound Alert'!K136,IF($B$8="Emerging Threat",'Compound Alert'!N136))) -> 2.5 | I45: =ROUNDDOWN(G45,0) -> 2 | J45: =IF( $B$8="Overall Alert",IF( 'Compound Alert'!R136 >= 7, "HIGH",IF( 'Compound Alert'!R136 >= 5, "MED","LOW")), IF( $B$8="Underlying Vulnerability", IF( 'Compound Alert'!Y136 >= 10, "HIGH",IF( 'Compound Alert'!Y136 >= 7, "MED","LOW")),IF( $B$8="Emerging Threat", IF( 'Compound Alert'!AF136 >= 10, "HIGH",IF( 'Compound Alert'!AF136 >= 7, "MED","LOW"))))) -> LOW | K45: =IF( $B$8="Overall Alert",IF( 'Compound Alert'!S136 >= 7, "HIGH",IF( 'Compound Alert'!S136 >= 5, "MED","LOW")), IF( $B$8="Underlying Vulnerability", IF( 'Compound Alert'!Z136 >= 10, "HIGH",IF( 'Compound Alert'!Z136 >= 7, "MED","LOW")),IF( $B$8="Emerging Threat", IF( 'Compound Alert'!AG136 >= 10, "HIGH",IF( 'Compound Alert'!AG136 >= 7, "MED","LOW"))))) -> LOW | L45: =IF( $B$8="Overall Alert",IF( 'Compound Alert'!T136 >= 7, "HIGH",IF( 'Compound Alert'!T136 >= 5, "MED","LOW")), IF( $B$8="Underlying Vulnerability", IF( 'Compound Alert'!AA136 >= 10, "HIGH",IF( 'Compound Alert'!AA136 >= 7, "MED","LOW")),IF( $B$8="Emerging Threat", IF( 'Compound Alert'!AH136 >= 10, "HIGH",IF( 'Compound Alert'!AH136 >= 7, "MED","LOW"))))) -> MED | M45: =IF( $B$8="Overall Alert",IF( 'Compound Alert'!U136 >= 7, "HIGH",IF( 'Compound Alert'!U136 >= 5, "MED","LOW")), IF( $B$8="Underlying Vulnerability", IF( 'Compound Alert'!AB136 >= 10, "HIGH",IF( 'Compound Alert'!AB136 >= 7, "MED","LOW")),IF( $B$8="Emerging Threat", IF( 'Compound Alert'!AI136 >= 10, "HIGH",IF( 'Compound Alert'!AI136 >= 7, "MED","LOW"))))) -> HIGH | N45: =IF( $B$8="Overall Alert",IF( 'Compound Alert'!V136 >= 7, "HIGH",IF( 'Compound Alert'!V136 >= 5, "MED","LOW")), IF( $B$8="Underlying Vulnerability", IF( 'Compound Alert'!AC136 >= 10, "HIGH",IF( 'Compound Alert'!AC136 >= 7, "MED","LOW")),IF( $B$8="Emerging Threat", IF( 'Compound Alert'!AJ136 >= 10, "HIGH",IF( 'Compound Alert'!AJ136 >= 7, "MED","LOW"))))) -> HIGH | O45: =IF( $B$8="Overall Alert",IF( 'Compound Alert'!W136 >= 7, "HIGH",IF( 'Compound Alert'!W136 >= 5, "MED","LOW")), IF( $B$8="Underlying Vulnerability", IF( 'Compound Alert'!AD136 >= 10, "HIGH",IF( 'Compound Alert'!AD136 >= 7, "MED","LOW")),IF( $B$8="Emerging Threat", IF( 'Compound Alert'!AK136 >= 10, "HIGH",IF( 'Compound Alert'!AK136 >= 7, "MED","LOW"))))) -> LOW
A46: 5 | B46: ='Compound Alert'!B148 -> Nigeria | C46: ='Compound Alert'!C148 -> NGA | D46: ='Compound Alert'!D148 -> SSF Sub-Saharan Africa | E46: ='Compound Alert'!E148 -> Blend | F46: ='Compound Alert'!F148 -> 143 | G46: =IF($B$8="Overall Alert",'Compound Alert'!G148,IF($B$8="Underlying Vulnerability",'Compound Alert'!J148,IF($B$8="Emerging Threat",'Compound Alert'!M148))) -> 2 | H46: =IF($B$8="Overall Alert",'Compound Alert'!H148,IF($B$8="Underlying Vulnerability",'Compound Alert'!K148,IF($B$8="Emerging Threat",'Compound Alert'!N148))) -> 2 | I46: =ROUNDDOWN(G46,0) -> 2 | J46: =IF( $B$8="Overall Alert",IF( 'Compound Alert'!R148 >= 7, "HIGH",IF( 'Compound Alert'!R148 >= 5, "MED","LOW")), IF( $B$8="Underlying Vulnerability", IF( 'Compound Alert'!Y148 >= 10, "HIGH",IF( 'Compound Alert'!Y148 >= 7, "MED","LOW")),IF( $B$8="Emerging Threat", IF( 'Compound Alert'!AF148 >= 10, "HIGH",IF( 'Compound Alert'!AF148 >= 7, "MED","LOW"))))) -> LOW | K46: =IF( $B$8="Overall Alert",IF( 'Compound Alert'!S148 >= 7, "HIGH",IF( 'Compound Alert'!S148 >= 5, "MED","LOW")), IF( $B$8="Underlying Vulnerability", IF( 'Compound Alert'!Z148 >= 10, "HIGH",IF( 'Compound Alert'!Z148 >= 7, "MED","LOW")),IF( $B$8="Emerging Threat", IF( 'Compound Alert'!AG148 >= 10, "HIGH",IF( 'Compound Alert'!AG148 >= 7, "MED","LOW"))))) -> HIGH | L46: =IF( $B$8="Overall Alert",IF( 'Compound Alert'!T148 >= 7, "HIGH",IF( 'Compound Alert'!T148 >= 5, "MED","LOW")), IF( $B$8="Underlying Vulnerability", IF( 'Compound Alert'!AA148 >= 10, "HIGH",IF( 'Compound Alert'!AA148 >= 7, "MED","LOW")),IF( $B$8="Emerging Threat", IF( 'Compound Alert'!AH148 >= 10, "HIGH",IF( 'Compound Alert'!AH148 >= 7, "MED","LOW"))))) -> LOW | M46: =IF( $B$8="Overall Alert",IF( 'Compound Alert'!U148 >= 7, "HIGH",IF( 'Compound Alert'!U148 >= 5, "MED","LOW")), IF( $B$8="Underlying Vulnerability", IF( 'Compound Alert'!AB148 >= 10, "HIGH",IF( 'Compound Alert'!AB148 >= 7, "MED","LOW")),IF( $B$8="Emerging Threat", IF( 'Compound Alert'!AI148 >= 10, "HIGH",IF( 'Compound Alert'!AI148 >= 7, "MED","LOW"))))) -> LOW | N46: =IF( $B$8="Overall Alert",IF( 'Compound Alert'!V148 >= 7, "HIGH",IF( 'Compound Alert'!V148 >= 5, "MED","LOW")), IF( $B$8="Underlying Vulnerability", IF( 'Compound Alert'!AC148 >= 10, "HIGH",IF( 'Compound Alert'!AC148 >= 7, "MED","LOW")),IF( $B$8="Emerging Threat", IF( 'Compound Alert'!AJ148 >= 10, "HIGH",IF( 'Compound Alert'!AJ148 >= 7, "MED","LOW"))))) -> LOW | O46: =IF( $B$8="Overall Alert",IF( 'Compound Alert'!W148 >= 7, "HIGH",IF( 'Compound Alert'!W148 >= 5, "MED","LOW")), IF( $B$8="Underlying Vulnerability", IF( 'Compound Alert'!AD148 >= 10, "HIGH",IF( 'Compound Alert'!AD148 >= 7, "MED","LOW")),IF( $B$8="Emerging Threat", IF( 'Compound Alert'!AK148 >= 10, "HIGH",IF( 'Compound Alert'!AK148 >= 7, "MED","LOW"))))) -> HIGH
A47: 6 | B47: ='Compound Alert'!B134 -> Mali | C47: ='Compound Alert'!C134 -> MLI | D47: ='Compound Alert'!D134 -> SSF Sub-Saharan Africa | E47: ='Compound Alert'!E134 -> IDA | F47: ='Compound Alert'!F134 -> 129 | G47: =IF($B$8="Overall Alert",'Compound Alert'!G134,IF($B$8="Underlying Vulnerability",'Compound Alert'!J134,IF($B$8="Emerging Threat",'Compound Alert'!M134))) -> 3 | H47: =IF($B$8="Overall Alert",'Compound Alert'!H134,IF($B$8="Underlying Vulnerability",'Compound Alert'!K134,IF($B$8="Emerging Threat",'Compound Alert'!N134))) -> 3 | I47: =ROUNDDOWN(G47,0) -> 3 | J47: =IF( $B$8="Overall Alert",IF( 'Compound Alert'!R134 >= 7, "HIGH",IF( 'Compound Alert'!R134 >= 5, "MED","LOW")), IF( $B$8="Underlying Vulnerability", IF( 'Compound Alert'!Y134 >= 10, "HIGH",IF( 'Compound Alert'!Y134 >= 7, "MED","LOW")),IF( $B$8="Emerging Threat", IF( 'Compound Alert'!AF134 >= 10, "HIGH",IF( 'Compound Alert'!AF134 >= 7, "MED","LOW"))))) -> LOW | K47: =IF( $B$8="Overall Alert",IF( 'Compound Alert'!S134 >= 7, "HIGH",IF( 'Compound Alert'!S134 >= 5, "MED","LOW")), IF( $B$8="Underlying Vulnerability", IF( 'Compound Alert'!Z134 >= 10, "HIGH",IF( 'Compound Alert'!Z134 >= 7, "MED","LOW")),IF( $B$8="Emerging Threat", IF( 'Compound Alert'!AG134 >= 10, "HIGH",IF( 'Compound Alert'!AG134 >= 7, "MED","LOW"))))) -> HIGH | L47: =IF( $B$8="Overall Alert",IF( 'Compound Alert'!T134 >= 7, "HIGH",IF( 'Compound Alert'!T134 >= 5, "MED","LOW")), IF( $B$8="Underlying Vulnerability", IF( 'Compound Alert'!AA134 >= 10, "HIGH",IF( 'Compound Alert'!AA134 >= 7, "MED","LOW")),IF( $B$8="Emerging Threat", IF( 'Compound Alert'!AH134 >= 10, "HIGH",IF( 'Compound Alert'!AH134 >= 7, "MED","LOW"))))) -> LOW | M47: =IF( $B$8="Overall Alert",IF( 'Compound Alert'!U134 >= 7, "HIGH",IF( 'Compound Alert'!U134 >= 5, "MED","LOW")), IF( $B$8="Underlying Vulnerability", IF( 'Compound Alert'!AB134 >= 10, "HIGH",IF( 'Compound Alert'!AB134 >= 7, "MED","LOW")),IF( $B$8="Emerging Threat", IF( 'Compound Alert'!AI134 >= 10, "HIGH",IF( 'Compound Alert'!AI134 >= 7, "MED","LOW"))))) -> LOW | N47: =IF( $B$8="Overall Alert",IF( 'Compound Alert'!V134 >= 7, "HIGH",IF( 'Compound Alert'!V134 >= 5, "MED","LOW")), IF( $B$8="Underlying Vulnerability", IF( 'Compound Alert'!AC134 >= 10, "HIGH",IF( 'Compound Alert'!AC134 >= 7, "MED","LOW")),IF( $B$8="Emerging Threat", IF( 'Compound Alert'!AJ134 >= 10, "HIGH",IF( 'Compound Alert'!AJ134 >= 7, "MED","LOW"))))) -> HIGH | O47: =IF( $B$8="Overall Alert",IF( 'Compound Alert'!W134 >= 7, "HIGH",IF( 'Compound Alert'!W134 >= 5, "MED","LOW")), IF( $B$8="Underlying Vulnerability", IF( 'Compound Alert'!AD134 >= 10, "HIGH",IF( 'Compound Alert'!AD134 >= 7, "MED","LOW")),IF( $B$8="Emerging Threat", IF( 'Compound Alert'!AK134 >= 10, "HIGH",IF( 'Compound Alert'!AK134 >= 7, "MED","LOW"))))) -> HIGH
A48: 7 | B48: ='Compound Alert'!B147 -> Niger | C48: ='Compound Alert'!C147 -> NER | D48: ='Compound Alert'!D147 -> SSF Sub-Saharan Africa | E48: ='Compound Alert'!E147 -> IDA | F48: ='Compound Alert'!F147 -> 142 | G48: =IF($B$8="Overall Alert",'Compound Alert'!G147,IF($B$8="Underlying Vulnerability",'Compound Alert'!J147,IF($B$8="Emerging Threat",'Compound Alert'!M147))) -> 2.5 | H48: =IF($B$8="Overall Alert",'Compound Alert'!H147,IF($B$8="Underlying Vulnerability",'Compound Alert'!K147,IF($B$8="Emerging Threat",'Compound Alert'!N147))) -> 2.5 | I48: =ROUNDDOWN(G48,0) -> 2 | J48: =IF( $B$8="Overall Alert",IF( 'Compound Alert'!R147 >= 7, "HIGH",IF( 'Compound Alert'!R147 >= 5, "MED","LOW")), IF( $B$8="Underlying Vulnerability", IF( 'Compound Alert'!Y147 >= 10, "HIGH",IF( 'Compound Alert'!Y147 >= 7, "MED","LOW")),IF( $B$8="Emerging Threat", IF( 'Compound Alert'!AF147 >= 10, "HIGH",IF( 'Compound Alert'!AF147 >= 7, "MED","LOW"))))) -> LOW | K48: =IF( $B$8="Overall Alert",IF( 'Compound Alert'!S147 >= 7, "HIGH",IF( 'Compound Alert'!S147 >= 5, "MED","LOW")), IF( $B$8="Underlying Vulnerability", IF( 'Compound Alert'!Z147 >= 10, "HIGH",IF( 'Compound Alert'!Z147 >= 7, "MED","LOW")),IF( $B$8="Emerging Threat", IF( 'Compound Alert'!AG147 >= 10, "HIGH",IF( 'Compound Alert'!AG147 >= 7, "MED","LOW"))))) -> HIGH | L48: =IF( $B$8="Overall Alert",IF( 'Compound Alert'!T147 >= 7, "HIGH",IF( 'Compound Alert'!T147 >= 5, "MED","LOW")), IF( $B$8="Underlying Vulnerability", IF( 'Compound Alert'!AA147 >= 10, "HIGH",IF( 'Compound Alert'!AA147 >= 7, "MED","LOW")),IF( $B$8="Emerging Threat", IF( 'Compound Alert'!AH147 >= 10, "HIGH",IF( 'Compound Alert'!AH147 >= 7, "MED","LOW"))))) -> LOW | M48: =IF( $B$8="Overall Alert",IF( 'Compound Alert'!U147 >= 7, "HIGH",IF( 'Compound Alert'!U147 >= 5, "MED","LOW")), IF( $B$8="Underlying Vulnerability", IF( 'Compound Alert'!AB147 >= 10, "HIGH",IF( 'Compound Alert'!AB147 >= 7, "MED","LOW")),IF( $B$8="Emerging Threat", IF( 'Compound Alert'!AI147 >= 10, "HIGH",IF( 'Compound Alert'!AI147 >= 7, "MED","LOW"))))) -> LOW | N48: =IF( $B$8="Overall Alert",IF( 'Compound Alert'!V147 >= 7, "HIGH",IF( 'Compound Alert'!V147 >= 5, "MED","LOW")), IF( $B$8="Underlying Vulnerability", IF( 'Compound Alert'!AC147 >= 10, "HIGH",IF( 'Compound Alert'!AC147 >= 7, "MED","LOW")),IF( $B$8="Emerging Threat", IF( 'Compound Alert'!AJ147 >= 10, "HIGH",IF( 'Compound Alert'!AJ147 >= 7, "MED","LOW"))))) -> MED | O48: =IF( $B$8="Overall Alert",IF( 'Compound Alert'!W147 >= 7, "HIGH",IF( 'Compound Alert'!W147 >= 5, "MED","LOW")), IF( $B$8="Underlying Vulnerability", IF( 'Compound Alert'!AD147 >= 10, "HIGH",IF( 'Compound Alert'!AD147 >= 7, "MED","LOW")),IF( $B$8="Emerging Threat", IF( 'Compound Alert'!AK147 >= 10, "HIGH",IF( 'Compound Alert'!AK147 >= 7, "MED","LOW"))))) -> HIGH
A49: 8 | B49: ='Compound Alert'!B156 -> Pakistan | C49: ='Compound Alert'!C156 -> PAK | D49: ='Compound Alert'!D156 -> SAS South Asia | E49: ='Compound Alert'!E156 -> Blend | F49: ='Compound Alert'!F156 -> 151 | G49: =IF($B$8="Overall Alert",'Compound Alert'!G156,IF($B$8="Underlying Vulnerability",'Compound Alert'!J156,IF($B$8="Emerging Threat",'Compound Alert'!M156))) -> 4 | H49: =IF($B$8="Overall Alert",'Compound Alert'!H156,IF($B$8="Underlying Vulnerability",'Compound Alert'!K156,IF($B$8="Emerging Threat",'Compound Alert'!N156))) -> 4 | I49: =ROUNDDOWN(G49,0) -> 4 | J49: =IF( $B$8="Overall Alert",IF( 'Compound Alert'!R156 >= 7, "HIGH",IF( 'Compound Alert'!R156 >= 5, "MED","LOW")), IF( $B$8="Underlying Vulnerability", IF( 'Compound Alert'!Y156 >= 10, "HIGH",IF( 'Compound Alert'!Y156 >= 7, "MED","LOW")),IF( $B$8="Emerging Threat", IF( 'Compound Alert'!AF156 >= 10, "HIGH",IF( 'Compound Alert'!AF156 >= 7, "MED","LOW"))))) -> LOW | K49: =IF( $B$8="Overall Alert",IF( 'Compound Alert'!S156 >= 7, "HIGH",IF( 'Compound Alert'!S156 >= 5, "MED","LOW")), IF( $B$8="Underlying Vulnerability", IF( 'Compound Alert'!Z156 >= 10, "HIGH",IF( 'Compound Alert'!Z156 >= 7, "MED","LOW")),IF( $B$8="Emerging Threat", IF( 'Compound Alert'!AG156 >= 10, "HIGH",IF( 'Compound Alert'!AG156 >= 7, "MED","LOW"))))) -> HIGH | L49: =IF( $B$8="Overall Alert",IF( 'Compound Alert'!T156 >= 7, "HIGH",IF( 'Compound Alert'!T156 >= 5, "MED","LOW")), IF( $B$8="Underlying Vulnerability", IF( 'Compound Alert'!AA156 >= 10, "HIGH",IF( 'Compound Alert'!AA156 >= 7, "MED","LOW")),IF( $B$8="Emerging Threat", IF( 'Compound Alert'!AH156 >= 10, "HIGH",IF( 'Compound Alert'!AH156 >= 7, "MED","LOW"))))) -> LOW | M49: =IF( $B$8="Overall Alert",IF( 'Compound Alert'!U156 >= 7, "HIGH",IF( 'Compound Alert'!U156 >= 5, "MED","LOW")), IF( $B$8="Underlying Vulnerability", IF( 'Compound Alert'!AB156 >= 10, "HIGH",IF( 'Compound Alert'!AB156 >= 7, "MED","LOW")),IF( $B$8="Emerging Threat", IF( 'Compound Alert'!AI156 >= 10, "HIGH",IF( 'Compound Alert'!AI156 >= 7, "MED","LOW"))))) -> HIGH | N49: =IF( $B$8="Overall Alert",IF( 'Compound Alert'!V156 >= 7, "HIGH",IF( 'Compound Alert'!V156 >= 5, "MED","LOW")), IF( $B$8="Underlying Vulnerability", IF( 'Compound Alert'!AC156 >= 10, "HIGH",IF( 'Compound Alert'!AC156 >= 7, "MED","LOW")),IF( $B$8="Emerging Threat", IF( 'Compound Alert'!AJ156 >= 10, "HIGH",IF( 'Compound Alert'!AJ156 >= 7, "MED","LOW"))))) -> HIGH | O49: =IF( $B$8="Overall Alert",IF( 'Compound Alert'!W156 >= 7, "HIGH",IF( 'Compound Alert'!W156 >= 5, "MED","LOW")), IF( $B$8="Underlying Vulnerability", IF( 'Compound Alert'!AD156 >= 10, "HIGH",IF( 'Compound Alert'!AD156 >= 7, "MED","LOW")),IF( $B$8="Emerging Threat", IF( 'Compound Alert'!AK156 >= 10, "HIGH",IF( 'Compound Alert'!AK156 >= 7, "MED","LOW"))))) -> HIGH
A50: 9 | B50: ='Compound Alert'!B192 -> Syrian Arab Republic | C50: ='Compound Alert'!C192 -> SYR | D50: ='Compound Alert'!D192 -> MEA Middle East & North Africa | E50: ='Compound Alert'!E192 -> IDA | F50: ='Compound Alert'!F192 -> 187 | G50: =IF($B$8="Overall Alert",'Compound Alert'!G192,IF($B$8="Underlying Vulnerability",'Compound Alert'!J192,IF($B$8="Emerging Threat",'Compound Alert'!M192))) -> 3 | H50: =IF($B$8="Overall Alert",'Compound Alert'!H192,IF($B$8="Underlying Vulnerability",'Compound Alert'!K192,IF($B$8="Emerging Threat",'Compound Alert'!N192))) -> 3 | I50: =ROUNDDOWN(G50,0) -> 3 | J50: =IF( $B$8="Overall Alert",IF( 'Compound Alert'!R192 >= 7, "HIGH",IF( 'Compound Alert'!R192 >= 5, "MED","LOW")), IF( $B$8="Underlying Vulnerability", IF( 'Compound Alert'!Y192 >= 10, "HIGH",IF( 'Compound Alert'!Y192 >= 7, "MED","LOW")),IF( $B$8="Emerging Threat", IF( 'Compound Alert'!AF192 >= 10, "HIGH",IF( 'Compound Alert'!AF192 >= 7, "MED","LOW"))))) -> LOW | K50: =IF( $B$8="Overall Alert",IF( 'Compound Alert'!S192 >= 7, "HIGH",IF( 'Compound Alert'!S192 >= 5, "MED","LOW")), IF( $B$8="Underlying Vulnerability", IF( 'Compound Alert'!Z192 >= 10, "HIGH",IF( 'Compound Alert'!Z192 >= 7, "MED","LOW")),IF( $B$8="Emerging Threat", IF( 'Compound Alert'!AG192 >= 10, "HIGH",IF( 'Compound Alert'!AG192 >= 7, "MED","LOW"))))) -> HIGH | L50: =IF( $B$8="Overall Alert",IF( 'Compound Alert'!T192 >= 7, "HIGH",IF( 'Compound Alert'!T192 >= 5, "MED","LOW")), IF( $B$8="Underlying Vulnerability", IF( 'Compound Alert'!AA192 >= 10, "HIGH",IF( 'Compound Alert'!AA192 >= 7, "MED","LOW")),IF( $B$8="Emerging Threat", IF( 'Compound Alert'!AH192 >= 10, "HIGH",IF( 'Compound Alert'!AH192 >= 7, "MED","LOW"))))) -> LOW | M50: =IF( $B$8="Overall Alert",IF( 'Compound Alert'!U192 >= 7, "HIGH",IF( 'Compound Alert'!U192 >= 5, "MED","LOW")), IF( $B$8="Underlying Vulnerability", IF( 'Compound Alert'!AB192 >= 10, "HIGH",IF( 'Compound Alert'!AB192 >= 7, "MED","LOW")),IF( $B$8="Emerging Threat", IF( 'Compound Alert'!AI192 >= 10, "HIGH",IF( 'Compound Alert'!AI192 >= 7, "MED","LOW"))))) -> HIGH | N50: =IF( $B$8="Overall Alert",IF( 'Compound Alert'!V192 >= 7, "HIGH",IF( 'Compound Alert'!V192 >= 5, "MED","LOW")), IF( $B$8="Underlying Vulnerability", IF( 'Compound Alert'!AC192 >= 10, "HIGH",IF( 'Compound Alert'!AC192 >= 7, "MED","LOW")),IF( $B$8="Emerging Threat", IF( 'Compound Alert'!AJ192 >= 10, "HIGH",IF( 'Compound Alert'!AJ192 >= 7, "MED","LOW"))))) -> HIGH | O50: =IF( $B$8="Overall Alert",IF( 'Compound Alert'!W192 >= 7, "HIGH",IF( 'Compound Alert'!W192 >= 5, "MED","LOW")), IF( $B$8="Underlying Vulnerability", IF( 'Compound Alert'!AD192 >= 10, "HIGH",IF( 'Compound Alert'!AD192 >= 7, "MED","LOW")),IF( $B$8="Emerging Threat", IF( 'Compound Alert'!AK192 >= 10, "HIGH",IF( 'Compound Alert'!AK192 >= 7, "MED","LOW"))))) -> LOW
A51: 10 | B51: ='Compound Alert'!B8 -> Angola | C51: ='Compound Alert'!C8 -> AGO | D51: ='Compound Alert'!D8 -> SSF Sub-Saharan Africa | E51: ='Compound Alert'!E8 -> IBRD | F51: ='Compound Alert'!F8 -> 3 | G51: =IF($B$8="Overall Alert",'Compound Alert'!G8,IF($B$8="Underlying Vulnerability",'Compound Alert'!J8,IF($B$8="Emerging Threat",'Compound Alert'!M8))) -> 2 | H51: =IF($B$8="Overall Alert",'Compound Alert'!H8,IF($B$8="Underlying Vulnerability",'Compound Alert'!K8,IF($B$8="Emerging Threat",'Compound Alert'!N8))) -> 2 | I51: =ROUNDDOWN(G51,0) -> 2 | J51: =IF( $B$8="Overall Alert",IF( 'Compound Alert'!R8 >= 7, "HIGH",IF( 'Compound Alert'!R8 >= 5, "MED","LOW")), IF( $B$8="Underlying Vulnerability", IF( 'Compound Alert'!Y8 >= 10, "HIGH",IF( 'Compound Alert'!Y8 >= 7, "MED","LOW")),IF( $B$8="Emerging Threat", IF( 'Compound Alert'!AF8 >= 10, "HIGH",IF( 'Compound Alert'!AF8 >= 7, "MED","LOW"))))) -> LOW | K51: =IF( $B$8="Overall Alert",IF( 'Compound Alert'!S8 >= 7, "HIGH",IF( 'Compound Alert'!S8 >= 5, "MED","LOW")), IF( $B$8="Underlying Vulnerability", IF( 'Compound Alert'!Z8 >= 10, "HIGH",IF( 'Compound Alert'!Z8 >= 7, "MED","LOW")),IF( $B$8="Emerging Threat", IF( 'Compound Alert'!AG8 >= 10, "HIGH",IF( 'Compound Alert'!AG8 >= 7, "MED","LOW"))))) -> LOW | L51: =IF( $B$8="Overall Alert",IF( 'Compound Alert'!T8 >= 7, "HIGH",IF( 'Compound Alert'!T8 >= 5, "MED","LOW")), IF( $B$8="Underlying Vulnerability", IF( 'Compound Alert'!AA8 >= 10, "HIGH",IF( 'Compound Alert'!AA8 >= 7, "MED","LOW")),IF( $B$8="Emerging Threat", IF( 'Compound Alert'!AH8 >= 10, "HIGH",IF( 'Compound Alert'!AH8 >= 7, "MED","LOW"))))) -> MED | M51: =IF( $B$8="Overall Alert",IF( 'Compound Alert'!U8 >= 7, "HIGH",IF( 'Compound Alert'!U8 >= 5, "MED","LOW")), IF( $B$8="Underlying Vulnerability", IF( 'Compound Alert'!AB8 >= 10, "HIGH",IF( 'Compound Alert'!AB8 >= 7, "MED","LOW")),IF( $B$8="Emerging Threat", IF( 'Compound Alert'!AI8 >= 10, "HIGH",IF( 'Compound Alert'!AI8 >= 7, "MED","LOW"))))) -> HIGH | N51: =IF( $B$8="Overall Alert",IF( 'Compound Alert'!V8 >= 7, "HIGH",IF( 'Compound Alert'!V8 >= 5, "MED","LOW")), IF( $B$8="Underlying Vulnerability", IF( 'Compound Alert'!AC8 >= 10, "HIGH",IF( 'Compound Alert'!AC8 >= 7, "MED","LOW")),IF( $B$8="Emerging Threat", IF( 'Compound Alert'!AJ8 >= 10, "HIGH",IF( 'Compound Alert'!AJ8 >= 7, "MED","LOW"))))) -> MED | O51: =IF( $B$8="Overall Alert",IF( 'Compound Alert'!W8 >= 7, "HIGH",IF( 'Compound Alert'!W8 >= 5, "MED","LOW")), IF( $B$8="Underlying Vulnerability", IF( 'Compound Alert'!AD8 >= 10, "HIGH",IF( 'Compound Alert'!AD8 >= 7, "MED","LOW")),IF( $B$8="Emerging Threat", IF( 'Compound Alert'!AK8 >= 10, "HIGH",IF( 'Compound Alert'!AK8 >= 7, "MED","LOW"))))) -> LOW
A52: 11 | B52: ='Compound Alert'!B91 -> Haiti | C52: ='Compound Alert'!C91 -> HTI | D52: ='Compound Alert'!D91 -> LCN Latin America & Caribbean | E52: ='Compound Alert'!E91 -> IDA | F52: ='Compound Alert'!F91 -> 86 | G52: =IF($B$8="Overall Alert",'Compound Alert'!G91,IF($B$8="Underlying Vulnerability",'Compound Alert'!J91,IF($B$8="Emerging Threat",'Compound Alert'!M91))) -> 3.5 | H52: =IF($B$8="Overall Alert",'Compound Alert'!H91,IF($B$8="Underlying Vulnerability",'Compound Alert'!K91,IF($B$8="Emerging Threat",'Compound Alert'!N91))) -> 3.5 | I52: =ROUNDDOWN(G52,0) -> 3 | J52: =IF( $B$8="Overall Alert",IF( 'Compound Alert'!R91 >= 7, "HIGH",IF( 'Compound Alert'!R91 >= 5, "MED","LOW")), IF( $B$8="Underlying Vulnerability", IF( 'Compound Alert'!Y91 >= 10, "HIGH",IF( 'Compound Alert'!Y91 >= 7, "MED","LOW")),IF( $B$8="Emerging Threat", IF( 'Compound Alert'!AF91 >= 10, "HIGH",IF( 'Compound Alert'!AF91 >= 7, "MED","LOW"))))) -> LOW | K52: =IF( $B$8="Overall Alert",IF( 'Compound Alert'!S91 >= 7, "HIGH",IF( 'Compound Alert'!S91 >= 5, "MED","LOW")), IF( $B$8="Underlying Vulnerability", IF( 'Compound Alert'!Z91 >= 10, "HIGH",IF( 'Compound Alert'!Z91 >= 7, "MED","LOW")),IF( $B$8="Emerging Threat", IF( 'Compound Alert'!AG91 >= 10, "HIGH",IF( 'Compound Alert'!AG91 >= 7, "MED","LOW"))))) -> HIGH | L52: =IF( $B$8="Overall Alert",IF( 'Compound Alert'!T91 >= 7, "HIGH",IF( 'Compound Alert'!T91 >= 5, "MED","LOW")), IF( $B$8="Underlying Vulnerability", IF( 'Compound Alert'!AA91 >= 10, "HIGH",IF( 'Compound Alert'!AA91 >= 7, "MED","LOW")),IF( $B$8="Emerging Threat", IF( 'Compound Alert'!AH91 >= 10, "HIGH",IF( 'Compound Alert'!AH91 >= 7, "MED","LOW"))))) -> MED | M52: =IF( $B$8="Overall Alert",IF( 'Compound Alert'!U91 >= 7, "HIGH",IF( 'Compound Alert'!U91 >= 5, "MED","LOW")), IF( $B$8="Underlying Vulnerability", IF( 'Compound Alert'!AB91 >= 10, "HIGH",IF( 'Compound Alert'!AB91 >= 7, "MED","LOW")),IF( $B$8="Emerging Threat", IF( 'Compound Alert'!AI91 >= 10, "HIGH",IF( 'Compound Alert'!AI91 >= 7, "MED","LOW"))))) -> HIGH | N52: =IF( $B$8="Overall Alert",IF( 'Compound Alert'!V91 >= 7, "HIGH",IF( 'Compound Alert'!V91 >= 5, "MED","LOW")), IF( $B$8="Underlying Vulnerability", IF( 'Compound Alert'!AC91 >= 10, "HIGH",IF( 'Compound Alert'!AC91 >= 7, "MED","LOW")),IF( $B$8="Emerging Threat", IF( 'Compound Alert'!AJ91 >= 10, "HIGH",IF( 'Compound Alert'!AJ91 >= 7, "MED","LOW"))))) -> HIGH | O52: =IF( $B$8="Overall Alert",IF( 'Compound Alert'!W91 >= 7, "HIGH",IF( 'Compound Alert'!W91 >= 5, "MED","LOW")), IF( $B$8="Underlying Vulnerability", IF( 'Compound Alert'!AD91 >= 10, "HIGH",IF( 'Compound Alert'!AD91 >= 7, "MED","LOW")),IF( $B$8="Emerging Threat", IF( 'Compound Alert'!AK91 >= 10, "HIGH",IF( 'Compound Alert'!AK91 >= 7, "MED","LOW"))))) -> LOW
A53: 12 | B53: ='Compound Alert'!B22 -> Burkina Faso | C53: ='Compound Alert'!C22 -> BFA | D53: ='Compound Alert'!D22 -> SSF Sub-Saharan Africa | E53: ='Compound Alert'!E22 -> IDA | F53: ='Compound Alert'!F22 -> 17 | G53: =IF($B$8="Overall Alert",'Compound Alert'!G22,IF($B$8="Underlying Vulnerability",'Compound Alert'!J22,IF($B$8="Emerging Threat",'Compound Alert'!M22))) -> 2.5 | H53: =IF($B$8="Overall Alert",'Compound Alert'!H22,IF($B$8="Underlying Vulnerability",'Compound Alert'!K22,IF($B$8="Emerging Threat",'Compound Alert'!N22))) -> 2.5 | I53: =ROUNDDOWN(G53,0) -> 2 | J53: =IF( $B$8="Overall Alert",IF( 'Compound Alert'!R22 >= 7, "HIGH",IF( 'Compound Alert'!R22 >= 5, "MED","LOW")), IF( $B$8="Underlying Vulnerability", IF( 'Compound Alert'!Y22 >= 10, "HIGH",IF( 'Compound Alert'!Y22 >= 7, "MED","LOW")),IF( $B$8="Emerging Threat", IF( 'Compound Alert'!AF22 >= 10, "HIGH",IF( 'Compound Alert'!AF22 >= 7, "MED","LOW"))))) -> LOW | K53: =IF( $B$8="Overall Alert",IF( 'Compound Alert'!S22 >= 7, "HIGH",IF( 'Compound Alert'!S22 >= 5, "MED","LOW")), IF( $B$8="Underlying Vulnerability", IF( 'Compound Alert'!Z22 >= 10, "HIGH",IF( 'Compound Alert'!Z22 >= 7, "MED","LOW")),IF( $B$8="Emerging Threat", IF( 'Compound Alert'!AG22 >= 10, "HIGH",IF( 'Compound Alert'!AG22 >= 7, "MED","LOW"))))) -> HIGH | L53: =IF( $B$8="Overall Alert",IF( 'Compound Alert'!T22 >= 7, "HIGH",IF( 'Compound Alert'!T22 >= 5, "MED","LOW")), IF( $B$8="Underlying Vulnerability", IF( 'Compound Alert'!AA22 >= 10, "HIGH",IF( 'Compound Alert'!AA22 >= 7, "MED","LOW")),IF( $B$8="Emerging Threat", IF( 'Compound Alert'!AH22 >= 10, "HIGH",IF( 'Compound Alert'!AH22 >= 7, "MED","LOW"))))) -> LOW | M53: =IF( $B$8="Overall Alert",IF( 'Compound Alert'!U22 >= 7, "HIGH",IF( 'Compound Alert'!U22 >= 5, "MED","LOW")), IF( $B$8="Underlying Vulnerability", IF( 'Compound Alert'!AB22 >= 10, "HIGH",IF( 'Compound Alert'!AB22 >= 7, "MED","LOW")),IF( $B$8="Emerging Threat", IF( 'Compound Alert'!AI22 >= 10, "HIGH",IF( 'Compound Alert'!AI22 >= 7, "MED","LOW"))))) -> LOW | N53: =IF( $B$8="Overall Alert",IF( 'Compound Alert'!V22 >= 7, "HIGH",IF( 'Compound Alert'!V22 >= 5, "MED","LOW")), IF( $B$8="Underlying Vulnerability", IF( 'Compound Alert'!AC22 >= 10, "HIGH",IF( 'Compound Alert'!AC22 >= 7, "MED","LOW")),IF( $B$8="Emerging Threat", IF( 'Compound Alert'!AJ22 >= 10, "HIGH",IF( 'Compound Alert'!AJ22 >= 7, "MED","LOW"))))) -> MED | O53: =IF( $B$8="Overall Alert",IF( 'Compound Alert'!W22 >= 7, "HIGH",IF( 'Compound Alert'!W22 >= 5, "MED","LOW")), IF( $B$8="Underlying Vulnerability", IF( 'Compound Alert'!AD22 >= 10, "HIGH",IF( 'Compound Alert'!AD22 >= 7, "MED","LOW")),IF( $B$8="Emerging Threat", IF( 'Compound Alert'!AK22 >= 10, "HIGH",IF( 'Compound Alert'!AK22 >= 7, "MED","LOW"))))) -> HIGH
A54: 13 | B54: ='Compound Alert'!B143 -> Malawi | C54: ='Compound Alert'!C143 -> MWI | D54: ='Compound Alert'!D143 -> SSF Sub-Saharan Africa | E54: ='Compound Alert'!E143 -> IDA | F54: ='Compound Alert'!F143 -> 138 | G54: =IF($B$8="Overall Alert",'Compound Alert'!G143,IF($B$8="Underlying Vulnerability",'Compound Alert'!J143,IF($B$8="Emerging Threat",'Compound Alert'!M143))) -> 3 | H54: =IF($B$8="Overall Alert",'Compound Alert'!H143,IF($B$8="Underlying Vulnerability",'Compound Alert'!K143,IF($B$8="Emerging Threat",'Compound Alert'!N143))) -> 3 | I54: =ROUNDDOWN(G54,0) -> 3 | J54: =IF( $B$8="Overall Alert",IF( 'Compound Alert'!R143 >= 7, "HIGH",IF( 'Compound Alert'!R143 >= 5, "MED","LOW")), IF( $B$8="Underlying Vulnerability", IF( 'Compound Alert'!Y143 >= 10, "HIGH",IF( 'Compound Alert'!Y143 >= 7, "MED","LOW")),IF( $B$8="Emerging Threat", IF( 'Compound Alert'!AF143 >= 10, "HIGH",IF( 'Compound Alert'!AF143 >= 7, "MED","LOW"))))) -> HIGH | K54: =IF( $B$8="Overall Alert",IF( 'Compound Alert'!S143 >= 7, "HIGH",IF( 'Compound Alert'!S143 >= 5, "MED","LOW")), IF( $B$8="Underlying Vulnerability", IF( 'Compound Alert'!Z143 >= 10, "HIGH",IF( 'Compound Alert'!Z143 >= 7, "MED","LOW")),IF( $B$8="Emerging Threat", IF( 'Compound Alert'!AG143 >= 10, "HIGH",IF( 'Compound Alert'!AG143 >= 7, "MED","LOW"))))) -> MED | L54: =IF( $B$8="Overall Alert",IF( 'Compound Alert'!T143 >= 7, "HIGH",IF( 'Compound Alert'!T143 >= 5, "MED","LOW")), IF( $B$8="Underlying Vulnerability", IF( 'Compound Alert'!AA143 >= 10, "HIGH",IF( 'Compound Alert'!AA143 >= 7, "MED","LOW")),IF( $B$8="Emerging Threat", IF( 'Compound Alert'!AH143 >= 10, "HIGH",IF( 'Compound Alert'!AH143 >= 7, "MED","LOW"))))) -> MED | M54: =IF( $B$8="Overall Alert",IF( 'Compound Alert'!U143 >= 7, "HIGH",IF( 'Compound Alert'!U143 >= 5, "MED","LOW")), IF( $B$8="Underlying Vulnerability", IF( 'Compound Alert'!AB143 >= 10, "HIGH",IF( 'Compound Alert'!AB143 >= 7, "MED","LOW")),IF( $B$8="Emerging Threat", IF( 'Compound Alert'!AI143 >= 10, "HIGH",IF( 'Compound Alert'!AI143 >= 7, "MED","LOW"))))) -> MED | N54: =IF( $B$8="Overall Alert",IF( 'Compound Alert'!V143 >= 7, "HIGH",IF( 'Compound Alert'!V143 >= 5, "MED","LOW")), IF( $B$8="Underlying Vulnerability", IF( 'Compound Alert'!AC143 >= 10, "HIGH",IF( 'Compound Alert'!AC143 >= 7, "MED","LOW")),IF( $B$8="Emerging Threat", IF( 'Compound Alert'!AJ143 >= 10, "HIGH",IF( 'Compound Alert'!AJ143 >= 7, "MED","LOW"))))) -> MED | O54: =IF( $B$8="Overall Alert",IF( 'Compound Alert'!W143 >= 7, "HIGH",IF( 'Compound Alert'!W143 >= 5, "MED","LOW")), IF( $B$8="Underlying Vulnerability", IF( 'Compound Alert'!AD143 >= 10, "HIGH",IF( 'Compound Alert'!AD143 >= 7, "MED","LOW")),IF( $B$8="Emerging Threat", IF( 'Compound Alert'!AK143 >= 10, "HIGH",IF( 'Compound Alert'!AK143 >= 7, "MED","LOW"))))) -> LOW
A55: 14 | B55: ='Compound Alert'!B19 -> Burundi | C55: ='Compound Alert'!C19 -> BDI | D55: ='Compound Alert'!D19 -> SSF Sub-Saharan Africa | E55: ='Compound Alert'!E19 -> IDA | F55: ='Compound Alert'!F19 -> 14 | G55: =IF($B$8="Overall Alert",'Compound Alert'!G19,IF($B$8="Underlying Vulnerability",'Compound Alert'!J19,IF($B$8="Emerging Threat",'Compound Alert'!M19))) -> 2.5 | H55: =IF($B$8="Overall Alert",'Compound Alert'!H19,IF($B$8="Underlying Vulnerability",'Compound Alert'!K19,IF($B$8="Emerging Threat",'Compound Alert'!N19))) -> 2.5 | I55: =ROUNDDOWN(G55,0) -> 2 | J55: =IF( $B$8="Overall Alert",IF( 'Compound Alert'!R19 >= 7, "HIGH",IF( 'Compound Alert'!R19 >= 5, "MED","LOW")), IF( $B$8="Underlying Vulnerability", IF( 'Compound Alert'!Y19 >= 10, "HIGH",IF( 'Compound Alert'!Y19 >= 7, "MED","LOW")),IF( $B$8="Emerging Threat", IF( 'Compound Alert'!AF19 >= 10, "HIGH",IF( 'Compound Alert'!AF19 >= 7, "MED","LOW"))))) -> LOW | K55: =IF( $B$8="Overall Alert",IF( 'Compound Alert'!S19 >= 7, "HIGH",IF( 'Compound Alert'!S19 >= 5, "MED","LOW")), IF( $B$8="Underlying Vulnerability", IF( 'Compound Alert'!Z19 >= 10, "HIGH",IF( 'Compound Alert'!Z19 >= 7, "MED","LOW")),IF( $B$8="Emerging Threat", IF( 'Compound Alert'!AG19 >= 10, "HIGH",IF( 'Compound Alert'!AG19 >= 7, "MED","LOW"))))) -> HIGH | L55: =IF( $B$8="Overall Alert",IF( 'Compound Alert'!T19 >= 7, "HIGH",IF( 'Compound Alert'!T19 >= 5, "MED","LOW")), IF( $B$8="Underlying Vulnerability", IF( 'Compound Alert'!AA19 >= 10, "HIGH",IF( 'Compound Alert'!AA19 >= 7, "MED","LOW")),IF( $B$8="Emerging Threat", IF( 'Compound Alert'!AH19 >= 10, "HIGH",IF( 'Compound Alert'!AH19 >= 7, "MED","LOW"))))) -> MED | M55: =IF( $B$8="Overall Alert",IF( 'Compound Alert'!U19 >= 7, "HIGH",IF( 'Compound Alert'!U19 >= 5, "MED","LOW")), IF( $B$8="Underlying Vulnerability", IF( 'Compound Alert'!AB19 >= 10, "HIGH",IF( 'Compound Alert'!AB19 >= 7, "MED","LOW")),IF( $B$8="Emerging Threat", IF( 'Compound Alert'!AI19 >= 10, "HIGH",IF( 'Compound Alert'!AI19 >= 7, "MED","LOW"))))) -> LOW | N55: =IF( $B$8="Overall Alert",IF( 'Compound Alert'!V19 >= 7, "HIGH",IF( 'Compound Alert'!V19 >= 5, "MED","LOW")), IF( $B$8="Underlying Vulnerability", IF( 'Compound Alert'!AC19 >= 10, "HIGH",IF( 'Compound Alert'!AC19 >= 7, "MED","LOW")),IF( $B$8="Emerging Threat", IF( 'Compound Alert'!AJ19 >= 10, "HIGH",IF( 'Compound Alert'!AJ19 >= 7, "MED","LOW"))))) -> MED | O55: =IF( $B$8="Overall Alert",IF( 'Compound Alert'!W19 >= 7, "HIGH",IF( 'Compound Alert'!W19 >= 5, "MED","LOW")), IF( $B$8="Underlying Vulnerability", IF( 'Compound Alert'!AD19 >= 10, "HIGH",IF( 'Compound Alert'!AD19 >= 7, "MED","LOW")),IF( $B$8="Emerging Threat", IF( 'Compound Alert'!AK19 >= 10, "HIGH",IF( 'Compound Alert'!AK19 >= 7, "MED","LOW"))))) -> MED
A56: 15 | B56: ='Compound Alert'!B67 -> Ethiopia | C56: ='Compound Alert'!C67 -> ETH | D56: ='Compound Alert'!D67 -> SSF Sub-Saharan Africa | E56: ='Compound Alert'!E67 -> IDA | F56: ='Compound Alert'!F67 -> 62 | G56: =IF($B$8="Overall Alert",'Compound Alert'!G67,IF($B$8="Underlying Vulnerability",'Compound Alert'!J67,IF($B$8="Emerging Threat",'Compound Alert'!M67))) -> 2 | H56: =IF($B$8="Overall Alert",'Compound Alert'!H67,IF($B$8="Underlying Vulnerability",'Compound Alert'!K67,IF($B$8="Emerging Threat",'Compound Alert'!N67))) -> 2 | I56: =ROUNDDOWN(G56,0) -> 2 | J56: =IF( $B$8="Overall Alert",IF( 'Compound Alert'!R67 >= 7, "HIGH",IF( 'Compound Alert'!R67 >= 5, "MED","LOW")), IF( $B$8="Underlying Vulnerability", IF( 'Compound Alert'!Y67 >= 10, "HIGH",IF( 'Compound Alert'!Y67 >= 7, "MED","LOW")),IF( $B$8="Emerging Threat", IF( 'Compound Alert'!AF67 >= 10, "HIGH",IF( 'Compound Alert'!AF67 >= 7, "MED","LOW"))))) -> LOW | K56: =IF( $B$8="Overall Alert",IF( 'Compound Alert'!S67 >= 7, "HIGH",IF( 'Compound Alert'!S67 >= 5, "MED","LOW")), IF( $B$8="Underlying Vulnerability", IF( 'Compound Alert'!Z67 >= 10, "HIGH",IF( 'Compound Alert'!Z67 >= 7, "MED","LOW")),IF( $B$8="Emerging Threat", IF( 'Compound Alert'!AG67 >= 10, "HIGH",IF( 'Compound Alert'!AG67 >= 7, "MED","LOW"))))) -> HIGH | L56: =IF( $B$8="Overall Alert",IF( 'Compound Alert'!T67 >= 7, "HIGH",IF( 'Compound Alert'!T67 >= 5, "MED","LOW")), IF( $B$8="Underlying Vulnerability", IF( 'Compound Alert'!AA67 >= 10, "HIGH",IF( 'Compound Alert'!AA67 >= 7, "MED","LOW")),IF( $B$8="Emerging Threat", IF( 'Compound Alert'!AH67 >= 10, "HIGH",IF( 'Compound Alert'!AH67 >= 7, "MED","LOW"))))) -> LOW | M56: =IF( $B$8="Overall Alert",IF( 'Compound Alert'!U67 >= 7, "HIGH",IF( 'Compound Alert'!U67 >= 5, "MED","LOW")), IF( $B$8="Underlying Vulnerability", IF( 'Compound Alert'!AB67 >= 10, "HIGH",IF( 'Compound Alert'!AB67 >= 7, "MED","LOW")),IF( $B$8="Emerging Threat", IF( 'Compound Alert'!AI67 >= 10, "HIGH",IF( 'Compound Alert'!AI67 >= 7, "MED","LOW"))))) -> LOW | N56: =IF( $B$8="Overall Alert",IF( 'Compound Alert'!V67 >= 7, "HIGH",IF( 'Compound Alert'!V67 >= 5, "MED","LOW")), IF( $B$8="Underlying Vulnerability", IF( 'Compound Alert'!AC67 >= 10, "HIGH",IF( 'Compound Alert'!AC67 >= 7, "MED","LOW")),IF( $B$8="Emerging Threat", IF( 'Compound Alert'!AJ67 >= 10, "HIGH",IF( 'Compound Alert'!AJ67 >= 7, "MED","LOW"))))) -> MED | O56: =IF( $B$8="Overall Alert",IF( 'Compound Alert'!W67 >= 7, "HIGH",IF( 'Compound Alert'!W67 >= 5, "MED","LOW")), IF( $B$8="Underlying Vulnerability", IF( 'Compound Alert'!AD67 >= 10, "HIGH",IF( 'Compound Alert'!AD67 >= 7, "MED","LOW")),IF( $B$8="Emerging Threat", IF( 'Compound Alert'!AK67 >= 10, "HIGH",IF( 'Compound Alert'!AK67 >= 7, "MED","LOW"))))) -> MED
A57: 16 | B57: ='Compound Alert'!B220 -> Yemen, Rep. | C57: ='Compound Alert'!C220 -> YEM | D57: ='Compound Alert'!D220 -> MEA Middle East & North Africa | E57: ='Compound Alert'!E220 -> IDA | F57: ='Compound Alert'!F220 -> 0 | G57: =IF($B$8="Overall Alert",'Compound Alert'!G220,IF($B$8="Underlying Vulnerability",'Compound Alert'!J220,IF($B$8="Emerging Threat",'Compound Alert'!M220))) -> 5 | H57: =IF($B$8="Overall Alert",'Compound Alert'!H220,IF($B$8="Underlying Vulnerability",'Compound Alert'!K220,IF($B$8="Emerging Threat",'Compound Alert'!N220))) -> 5 | I57: =ROUNDDOWN(G57,0) -> 5 | J57: =IF( $B$8="Overall Alert",IF( 'Compound Alert'!R220 >= 7, "HIGH",IF( 'Compound Alert'!R220 >= 5, "MED","LOW")), IF( $B$8="Underlying Vulnerability", IF( 'Compound Alert'!Y220 >= 10, "HIGH",IF( 'Compound Alert'!Y220 >= 7, "MED","LOW")),IF( $B$8="Emerging Threat", IF( 'Compound Alert'!AF220 >= 10, "HIGH",IF( 'Compound Alert'!AF220 >= 7, "MED","LOW"))))) -> LOW | K57: =IF( $B$8="Overall Alert",IF( 'Compound Alert'!S220 >= 7, "HIGH",IF( 'Compound Alert'!S220 >= 5, "MED","LOW")), IF( $B$8="Underlying Vulnerability", IF( 'Compound Alert'!Z220 >= 10, "HIGH",IF( 'Compound Alert'!Z220 >= 7, "MED","LOW")),IF( $B$8="Emerging Threat", IF( 'Compound Alert'!AG220 >= 10, "HIGH",IF( 'Compound Alert'!AG220 >= 7, "MED","LOW"))))) -> HIGH | L57: =IF( $B$8="Overall Alert",IF( 'Compound Alert'!T220 >= 7, "HIGH",IF( 'Compound Alert'!T220 >= 5, "MED","LOW")), IF( $B$8="Underlying Vulnerability", IF( 'Compound Alert'!AA220 >= 10, "HIGH",IF( 'Compound Alert'!AA220 >= 7, "MED","LOW")),IF( $B$8="Emerging Threat", IF( 'Compound Alert'!AH220 >= 10, "HIGH",IF( 'Compound Alert'!AH220 >= 7, "MED","LOW"))))) -> HIGH | M57: =IF( $B$8="Overall Alert",IF( 'Compound Alert'!U220 >= 7, "HIGH",IF( 'Compound Alert'!U220 >= 5, "MED","LOW")), IF( $B$8="Underlying Vulnerability", IF( 'Compound Alert'!AB220 >= 10, "HIGH",IF( 'Compound Alert'!AB220 >= 7, "MED","LOW")),IF( $B$8="Emerging Threat", IF( 'Compound Alert'!AI220 >= 10, "HIGH",IF( 'Compound Alert'!AI220 >= 7, "MED","LOW"))))) -> HIGH | N57: =IF( $B$8="Overall Alert",IF( 'Compound Alert'!V220 >= 7, "HIGH",IF( 'Compound Alert'!V220 >= 5, "MED","LOW")), IF( $B$8="Underlying Vulnerability", IF( 'Compound Alert'!AC220 >= 10, "HIGH",IF( 'Compound Alert'!AC220 >= 7, "MED","LOW")),IF( $B$8="Emerging Threat", IF( 'Compound Alert'!AJ220 >= 10, "HIGH",IF( 'Compound Alert'!AJ220 >= 7, "MED","LOW"))))) -> HIGH | O57: =IF( $B$8="Overall Alert",IF( 'Compound Alert'!W220 >= 7, "HIGH",IF( 'Compound Alert'!W220 >= 5, "MED","LOW")), IF( $B$8="Underlying Vulnerability", IF( 'Compound Alert'!AD220 >= 10, "HIGH",IF( 'Compound Alert'!AD220 >= 7, "MED","LOW")),IF( $B$8="Emerging Threat", IF( 'Compound Alert'!AK220 >= 10, "HIGH",IF( 'Compound Alert'!AK220 >= 7, "MED","LOW"))))) -> HIGH
A58: 17 | B58: ='Compound Alert'!B45 -> Congo, Dem. Rep. | C58: ='Compound Alert'!C45 -> COD | D58: ='Compound Alert'!D45 -> SSF Sub-Saharan Africa | E58: ='Compound Alert'!E45 -> IDA | F58: ='Compound Alert'!F45 -> 40 | G58: =IF($B$8="Overall Alert",'Compound Alert'!G45,IF($B$8="Underlying Vulnerability",'Compound Alert'!J45,IF($B$8="Emerging Threat",'Compound Alert'!M45))) -> 3.5 | H58: =IF($B$8="Overall Alert",'Compound Alert'!H45,IF($B$8="Underlying Vulnerability",'Compound Alert'!K45,IF($B$8="Emerging Threat",'Compound Alert'!N45))) -> 3.5 | I58: =ROUNDDOWN(G58,0) -> 3 | J58: =IF( $B$8="Overall Alert",IF( 'Compound Alert'!R45 >= 7, "HIGH",IF( 'Compound Alert'!R45 >= 5, "MED","LOW")), IF( $B$8="Underlying Vulnerability", IF( 'Compound Alert'!Y45 >= 10, "HIGH",IF( 'Compound Alert'!Y45 >= 7, "MED","LOW")),IF( $B$8="Emerging Threat", IF( 'Compound Alert'!AF45 >= 10, "HIGH",IF( 'Compound Alert'!AF45 >= 7, "MED","LOW"))))) -> HIGH | K58: =IF( $B$8="Overall Alert",IF( 'Compound Alert'!S45 >= 7, "HIGH",IF( 'Compound Alert'!S45 >= 5, "MED","LOW")), IF( $B$8="Underlying Vulnerability", IF( 'Compound Alert'!Z45 >= 10, "HIGH",IF( 'Compound Alert'!Z45 >= 7, "MED","LOW")),IF( $B$8="Emerging Threat", IF( 'Compound Alert'!AG45 >= 10, "HIGH",IF( 'Compound Alert'!AG45 >= 7, "MED","LOW"))))) -> HIGH | L58: =IF( $B$8="Overall Alert",IF( 'Compound Alert'!T45 >= 7, "HIGH",IF( 'Compound Alert'!T45 >= 5, "MED","LOW")), IF( $B$8="Underlying Vulnerability", IF( 'Compound Alert'!AA45 >= 10, "HIGH",IF( 'Compound Alert'!AA45 >= 7, "MED","LOW")),IF( $B$8="Emerging Threat", IF( 'Compound Alert'!AH45 >= 10, "HIGH",IF( 'Compound Alert'!AH45 >= 7, "MED","LOW"))))) -> MED | M58: =IF( $B$8="Overall Alert",IF( 'Compound Alert'!U45 >= 7, "HIGH",IF( 'Compound Alert'!U45 >= 5, "MED","LOW")), IF( $B$8="Underlying Vulnerability", IF( 'Compound Alert'!AB45 >= 10, "HIGH",IF( 'Compound Alert'!AB45 >= 7, "MED","LOW")),IF( $B$8="Emerging Threat", IF( 'Compound Alert'!AI45 >= 10, "HIGH",IF( 'Compound Alert'!AI45 >= 7, "MED","LOW"))))) -> LOW | N58: =IF( $B$8="Overall Alert",IF( 'Compound Alert'!V45 >= 7, "HIGH",IF( 'Compound Alert'!V45 >= 5, "MED","LOW")), IF( $B$8="Underlying Vulnerability", IF( 'Compound Alert'!AC45 >= 10, "HIGH",IF( 'Compound Alert'!AC45 >= 7, "MED","LOW")),IF( $B$8="Emerging Threat", IF( 'Compound Alert'!AJ45 >= 10, "HIGH",IF( 'Compound Alert'!AJ45 >= 7, "MED","LOW"))))) -> HIGH | O58: =IF( $B$8="Overall Alert",IF( 'Compound Alert'!W45 >= 7, "HIGH",IF( 'Compound Alert'!W45 >= 5, "MED","LOW")), IF( $B$8="Underlying Vulnerability", IF( 'Compound Alert'!AD45 >= 10, "HIGH",IF( 'Compound Alert'!AD45 >= 7, "MED","LOW")),IF( $B$8="Emerging Threat", IF( 'Compound Alert'!AK45 >= 10, "HIGH",IF( 'Compound Alert'!AK45 >= 7, "MED","LOW"))))) -> LOW
A59: 18 | B59: ='Compound Alert'!B183 -> South Sudan | C59: ='Compound Alert'!C183 -> SSD | D59: ='Compound Alert'!D183 -> SSF Sub-Saharan Africa | E59: ='Compound Alert'!E183 -> IDA | F59: ='Compound Alert'!F183 -> 178 | G59: =IF($B$8="Overall Alert",'Compound Alert'!G183,IF($B$8="Underlying Vulnerability",'Compound Alert'!J183,IF($B$8="Emerging Threat",'Compound Alert'!M183))) -> 2 | H59: =IF($B$8="Overall Alert",'Compound Alert'!H183,IF($B$8="Underlying Vulnerability",'Compound Alert'!K183,IF($B$8="Emerging Threat",'Compound Alert'!N183))) -> 2 | I59: =ROUNDDOWN(G59,0) -> 2 | J59: =IF( $B$8="Overall Alert",IF( 'Compound Alert'!R183 >= 7, "HIGH",IF( 'Compound Alert'!R183 >= 5, "MED","LOW")), IF( $B$8="Underlying Vulnerability", IF( 'Compound Alert'!Y183 >= 10, "HIGH",IF( 'Compound Alert'!Y183 >= 7, "MED","LOW")),IF( $B$8="Emerging Threat", IF( 'Compound Alert'!AF183 >= 10, "HIGH",IF( 'Compound Alert'!AF183 >= 7, "MED","LOW"))))) -> LOW | K59: =IF( $B$8="Overall Alert",IF( 'Compound Alert'!S183 >= 7, "HIGH",IF( 'Compound Alert'!S183 >= 5, "MED","LOW")), IF( $B$8="Underlying Vulnerability", IF( 'Compound Alert'!Z183 >= 10, "HIGH",IF( 'Compound Alert'!Z183 >= 7, "MED","LOW")),IF( $B$8="Emerging Threat", IF( 'Compound Alert'!AG183 >= 10, "HIGH",IF( 'Compound Alert'!AG183 >= 7, "MED","LOW"))))) -> HIGH | L59: =IF( $B$8="Overall Alert",IF( 'Compound Alert'!T183 >= 7, "HIGH",IF( 'Compound Alert'!T183 >= 5, "MED","LOW")), IF( $B$8="Underlying Vulnerability", IF( 'Compound Alert'!AA183 >= 10, "HIGH",IF( 'Compound Alert'!AA183 >= 7, "MED","LOW")),IF( $B$8="Emerging Threat", IF( 'Compound Alert'!AH183 >= 10, "HIGH",IF( 'Compound Alert'!AH183 >= 7, "MED","LOW"))))) -> #N/A | M59: =IF( $B$8="Overall Alert",IF( 'Compound Alert'!U183 >= 7, "HIGH",IF( 'Compound Alert'!U183 >= 5, "MED","LOW")), IF( $B$8="Underlying Vulnerability", IF( 'Compound Alert'!AB183 >= 10, "HIGH",IF( 'Compound Alert'!AB183 >= 7, "MED","LOW")),IF( $B$8="Emerging Threat", IF( 'Compound Alert'!AI183 >= 10, "HIGH",IF( 'Compound Alert'!AI183 >= 7, "MED","LOW"))))) -> LOW | N59: =IF( $B$8="Overall Alert",IF( 'Compound Alert'!V183 >= 7, "HIGH",IF( 'Compound Alert'!V183 >= 5, "MED","LOW")), IF( $B$8="Underlying Vulnerability", IF( 'Compound Alert'!AC183 >= 10, "HIGH",IF( 'Compound Alert'!AC183 >= 7, "MED","LOW")),IF( $B$8="Emerging Threat", IF( 'Compound Alert'!AJ183 >= 10, "HIGH",IF( 'Compound Alert'!AJ183 >= 7, "MED","LOW"))))) -> MED | O59: =IF( $B$8="Overall Alert",IF( 'Compound Alert'!W183 >= 7, "HIGH",IF( 'Compound Alert'!W183 >= 5, "MED","LOW")), IF( $B$8="Underlying Vulnerability", IF( 'Compound Alert'!AD183 >= 10, "HIGH",IF( 'Compound Alert'!AD183 >= 7, "MED","LOW")),IF( $B$8="Emerging Threat", IF( 'Compound Alert'!AK183 >= 10, "HIGH",IF( 'Compound Alert'!AK183 >= 7, "MED","LOW"))))) -> MED
A60: 19 | B60: ='Compound Alert'!B207 -> Uganda | C60: ='Compound Alert'!C207 -> UGA | D60: ='Compound Alert'!D207 -> SSF Sub-Saharan Africa | E60: ='Compound Alert'!E207 -> IDA | F60: ='Compound Alert'!F207 -> 0 | G60: =IF($B$8="Overall Alert",'Compound Alert'!G207,IF($B$8="Underlying Vulnerability",'Compound Alert'!J207,IF($B$8="Emerging Threat",'Compound Alert'!M207))) -> 1.5 | H60: =IF($B$8="Overall Alert",'Compound Alert'!H207,IF($B$8="Underlying Vulnerability",'Compound Alert'!K207,IF($B$8="Emerging Threat",'Compound Alert'!N207))) -> 1.5 | I60: =ROUNDDOWN(G60,0) -> 1 | J60: =IF( $B$8="Overall Alert",IF( 'Compound Alert'!R207 >= 7, "HIGH",IF( 'Compound Alert'!R207 >= 5, "MED","LOW")), IF( $B$8="Underlying Vulnerability", IF( 'Compound Alert'!Y207 >= 10, "HIGH",IF( 'Compound Alert'!Y207 >= 7, "MED","LOW")),IF( $B$8="Emerging Threat", IF( 'Compound Alert'!AF207 >= 10, "HIGH",IF( 'Compound Alert'!AF207 >= 7, "MED","LOW"))))) -> LOW | K60: =IF( $B$8="Overall Alert",IF( 'Compound Alert'!S207 >= 7, "HIGH",IF( 'Compound Alert'!S207 >= 5, "MED","LOW")), IF( $B$8="Underlying Vulnerability", IF( 'Compound Alert'!Z207 >= 10, "HIGH",IF( 'Compound Alert'!Z207 >= 7, "MED","LOW")),IF( $B$8="Emerging Threat", IF( 'Compound Alert'!AG207 >= 10, "HIGH",IF( 'Compound Alert'!AG207 >= 7, "MED","LOW"))))) -> MED | L60: =IF( $B$8="Overall Alert",IF( 'Compound Alert'!T207 >= 7, "HIGH",IF( 'Compound Alert'!T207 >= 5, "MED","LOW")), IF( $B$8="Underlying Vulnerability", IF( 'Compound Alert'!AA207 >= 10, "HIGH",IF( 'Compound Alert'!AA207 >= 7, "MED","LOW")),IF( $B$8="Emerging Threat", IF( 'Compound Alert'!AH207 >= 10, "HIGH",IF( 'Compound Alert'!AH207 >= 7, "MED","LOW"))))) -> LOW | M60: =IF( $B$8="Overall Alert",IF( 'Compound Alert'!U207 >= 7, "HIGH",IF( 'Compound Alert'!U207 >= 5, "MED","LOW")), IF( $B$8="Underlying Vulnerability", IF( 'Compound Alert'!AB207 >= 10, "HIGH",IF( 'Compound Alert'!AB207 >= 7, "MED","LOW")),IF( $B$8="Emerging Threat", IF( 'Compound Alert'!AI207 >= 10, "HIGH",IF( 'Compound Alert'!AI207 >= 7, "MED","LOW"))))) -> LOW | N60: =IF( $B$8="Overall Alert",IF( 'Compound Alert'!V207 >= 7, "HIGH",IF( 'Compound Alert'!V207 >= 5, "MED","LOW")), IF( $B$8="Underlying Vulnerability", IF( 'Compound Alert'!AC207 >= 10, "HIGH",IF( 'Compound Alert'!AC207 >= 7, "MED","LOW")),IF( $B$8="Emerging Threat", IF( 'Compound Alert'!AJ207 >= 10, "HIGH",IF( 'Compound Alert'!AJ207 >= 7, "MED","LOW"))))) -> LOW | O60: =IF( $B$8="Overall Alert",IF( 'Compound Alert'!W207 >= 7, "HIGH",IF( 'Compound Alert'!W207 >= 5, "MED","LOW")), IF( $B$8="Underlying Vulnerability", IF( 'Compound Alert'!AD207 >= 10, "HIGH",IF( 'Compound Alert'!AD207 >= 7, "MED","LOW")),IF( $B$8="Emerging Threat", IF( 'Compound Alert'!AK207 >= 10, "HIGH",IF( 'Compound Alert'!AK207 >= 7, "MED","LOW"))))) -> HIGH
A61: 20 | B61: ='Compound Alert'!B7 -> Afghanistan | C61: ='Compound Alert'!C7 -> AFG | D61: ='Compound Alert'!D7 -> SAS South Asia | E61: ='Compound Alert'!E7 -> IDA | F61: ='Compound Alert'!F7 -> 2 | G61: =IF($B$8="Overall Alert",'Compound Alert'!G7,IF($B$8="Underlying Vulnerability",'Compound Alert'!J7,IF($B$8="Emerging Threat",'Compound Alert'!M7))) -> 4 | H61: =IF($B$8="Overall Alert",'Compound Alert'!H7,IF($B$8="Underlying Vulnerability",'Compound Alert'!K7,IF($B$8="Emerging Threat",'Compound Alert'!N7))) -> 4 | I61: =ROUNDDOWN(G61,0) -> 4 | J61: =IF( $B$8="Overall Alert",IF( 'Compound Alert'!R7 >= 7, "HIGH",IF( 'Compound Alert'!R7 >= 5, "MED","LOW")), IF( $B$8="Underlying Vulnerability", IF( 'Compound Alert'!Y7 >= 10, "HIGH",IF( 'Compound Alert'!Y7 >= 7, "MED","LOW")),IF( $B$8="Emerging Threat", IF( 'Compound Alert'!AF7 >= 10, "HIGH",IF( 'Compound Alert'!AF7 >= 7, "MED","LOW"))))) -> LOW | K61: =IF( $B$8="Overall Alert",IF( 'Compound Alert'!S7 >= 7, "HIGH",IF( 'Compound Alert'!S7 >= 5, "MED","LOW")), IF( $B$8="Underlying Vulnerability", IF( 'Compound Alert'!Z7 >= 10, "HIGH",IF( 'Compound Alert'!Z7 >= 7, "MED","LOW")),IF( $B$8="Emerging Threat", IF( 'Compound Alert'!AG7 >= 10, "HIGH",IF( 'Compound Alert'!AG7 >= 7, "MED","LOW"))))) -> HIGH | L61: =IF( $B$8="Overall Alert",IF( 'Compound Alert'!T7 >= 7, "HIGH",IF( 'Compound Alert'!T7 >= 5, "MED","LOW")), IF( $B$8="Underlying Vulnerability", IF( 'Compound Alert'!AA7 >= 10, "HIGH",IF( 'Compound Alert'!AA7 >= 7, "MED","LOW")),IF( $B$8="Emerging Threat", IF( 'Compound Alert'!AH7 >= 10, "HIGH",IF( 'Compound Alert'!AH7 >= 7, "MED","LOW"))))) -> HIGH | M61: =IF( $B$8="Overall Alert",IF( 'Compound Alert'!U7 >= 7, "HIGH",IF( 'Compound Alert'!U7 >= 5, "MED","LOW")), IF( $B$8="Underlying Vulnerability", IF( 'Compound Alert'!AB7 >= 10, "HIGH",IF( 'Compound Alert'!AB7 >= 7, "MED","LOW")),IF( $B$8="Emerging Threat", IF( 'Compound Alert'!AI7 >= 10, "HIGH",IF( 'Compound Alert'!AI7 >= 7, "MED","LOW"))))) -> LOW | N61: =IF( $B$8="Overall Alert",IF( 'Compound Alert'!V7 >= 7, "HIGH",IF( 'Compound Alert'!V7 >= 5, "MED","LOW")), IF( $B$8="Underlying Vulnerability", IF( 'Compound Alert'!AC7 >= 10, "HIGH",IF( 'Compound Alert'!AC7 >= 7, "MED","LOW")),IF( $B$8="Emerging Threat", IF( 'Compound Alert'!AJ7 >= 10, "HIGH",IF( 'Compound Alert'!AJ7 >= 7, "MED","LOW"))))) -> HIGH | O61: =IF( $B$8="Overall Alert",IF( 'Compound Alert'!W7 >= 7, "HIGH",IF( 'Compound Alert'!W7 >= 5, "MED","LOW")), IF( $B$8="Underlying Vulnerability", IF( 'Compound Alert'!AD7 >= 10, "HIGH",IF( 'Compound Alert'!AD7 >= 7, "MED","LOW")),IF( $B$8="Emerging Threat", IF( 'Compound Alert'!AK7 >= 10, "HIGH",IF( 'Compound Alert'!AK7 >= 7, "MED","LOW"))))) -> HIGH
A62: 21 | B62: ='Compound Alert'!B46 -> Congo, Rep. | C62: ='Compound Alert'!C46 -> COG | D62: ='Compound Alert'!D46 -> SSF Sub-Saharan Africa | E62: ='Compound Alert'!E46 -> Blend | F62: ='Compound Alert'!F46 -> 41 | G62: =IF($B$8="Overall Alert",'Compound Alert'!G46,IF($B$8="Underlying Vulnerability",'Compound Alert'!J46,IF($B$8="Emerging Threat",'Compound Alert'!M46))) -> 0 | H62: =IF($B$8="Overall Alert",'Compound Alert'!H46,IF($B$8="Underlying Vulnerability",'Compound Alert'!K46,IF($B$8="Emerging Threat",'Compound Alert'!N46))) -> 0 | I62: =ROUNDDOWN(G62,0) -> 0 | J62: =IF( $B$8="Overall Alert",IF( 'Compound Alert'!R46 >= 7, "HIGH",IF( 'Compound Alert'!R46 >= 5, "MED","LOW")), IF( $B$8="Underlying Vulnerability", IF( 'Compound Alert'!Y46 >= 10, "HIGH",IF( 'Compound Alert'!Y46 >= 7, "MED","LOW")),IF( $B$8="Emerging Threat", IF( 'Compound Alert'!AF46 >= 10, "HIGH",IF( 'Compound Alert'!AF46 >= 7, "MED","LOW"))))) -> LOW | K62: =IF( $B$8="Overall Alert",IF( 'Compound Alert'!S46 >= 7, "HIGH",IF( 'Compound Alert'!S46 >= 5, "MED","LOW")), IF( $B$8="Underlying Vulnerability", IF( 'Compound Alert'!Z46 >= 10, "HIGH",IF( 'Compound Alert'!Z46 >= 7, "MED","LOW")),IF( $B$8="Emerging Threat", IF( 'Compound Alert'!AG46 >= 10, "HIGH",IF( 'Compound Alert'!AG46 >= 7, "MED","LOW"))))) -> LOW | L62: =IF( $B$8="Overall Alert",IF( 'Compound Alert'!T46 >= 7, "HIGH",IF( 'Compound Alert'!T46 >= 5, "MED","LOW")), IF( $B$8="Underlying Vulnerability", IF( 'Compound Alert'!AA46 >= 10, "HIGH",IF( 'Compound Alert'!AA46 >= 7, "MED","LOW")),IF( $B$8="Emerging Threat", IF( 'Compound Alert'!AH46 >= 10, "HIGH",IF( 'Compound Alert'!AH46 >= 7, "MED","LOW"))))) -> LOW | M62: =IF( $B$8="Overall Alert",IF( 'Compound Alert'!U46 >= 7, "HIGH",IF( 'Compound Alert'!U46 >= 5, "MED","LOW")), IF( $B$8="Underlying Vulnerability", IF( 'Compound Alert'!AB46 >= 10, "HIGH",IF( 'Compound Alert'!AB46 >= 7, "MED","LOW")),IF( $B$8="Emerging Threat", IF( 'Compound Alert'!AI46 >= 10, "HIGH",IF( 'Compound Alert'!AI46 >= 7, "MED","LOW"))))) -> LOW | N62: =IF( $B$8="Overall Alert",IF( 'Compound Alert'!V46 >= 7, "HIGH",IF( 'Compound Alert'!V46 >= 5, "MED","LOW")), IF( $B$8="Underlying Vulnerability", IF( 'Compound Alert'!AC46 >= 10, "HIGH",IF( 'Compound Alert'!AC46 >= 7, "MED","LOW")),IF( $B$8="Emerging Threat", IF( 'Compound Alert'!AJ46 >= 10, "HIGH",IF( 'Compound Alert'!AJ46 >= 7, "MED","LOW"))))) -> LOW | O62: =IF( $B$8="Overall Alert",IF( 'Compound Alert'!W46 >= 7, "HIGH",IF( 'Compound Alert'!W46 >= 5, "MED","LOW")), IF( $B$8="Underlying Vulnerability", IF( 'Compound Alert'!AD46 >= 10, "HIGH",IF( 'Compound Alert'!AD46 >= 7, "MED","LOW")),IF( $B$8="Emerging Threat", IF( 'Compound Alert'!AK46 >= 10, "HIGH",IF( 'Compound Alert'!AK46 >= 7, "MED","LOW"))))) -> LOW
A63: 22 | B63: ='Compound Alert'!B223 -> Zimbabwe | C63: ='Compound Alert'!C223 -> ZWE | D63: ='Compound Alert'!D223 -> SSF Sub-Saharan Africa | E63: ='Compound Alert'!E223 -> Blend | F63: ='Compound Alert'!F223 -> 0 | G63: =IF($B$8="Overall Alert",'Compound Alert'!G223,IF($B$8="Underlying Vulnerability",'Compound Alert'!J223,IF($B$8="Emerging Threat",'Compound Alert'!M223))) -> 4.5 | H63: =IF($B$8="Overall Alert",'Compound Alert'!H223,IF($B$8="Underlying Vulnerability",'Compound Alert'!K223,IF($B$8="Emerging Threat",'Compound Alert'!N223))) -> 4.5 | I63: =ROUNDDOWN(G63,0) -> 4 | J63: =IF( $B$8="Overall Alert",IF( 'Compound Alert'!R223 >= 7, "HIGH",IF( 'Compound Alert'!R223 >= 5, "MED","LOW")), IF( $B$8="Underlying Vulnerability", IF( 'Compound Alert'!Y223 >= 10, "HIGH",IF( 'Compound Alert'!Y223 >= 7, "MED","LOW")),IF( $B$8="Emerging Threat", IF( 'Compound Alert'!AF223 >= 10, "HIGH",IF( 'Compound Alert'!AF223 >= 7, "MED","LOW"))))) -> HIGH | K63: =IF( $B$8="Overall Alert",IF( 'Compound Alert'!S223 >= 7, "HIGH",IF( 'Compound Alert'!S223 >= 5, "MED","LOW")), IF( $B$8="Underlying Vulnerability", IF( 'Compound Alert'!Z223 >= 10, "HIGH",IF( 'Compound Alert'!Z223 >= 7, "MED","LOW")),IF( $B$8="Emerging Threat", IF( 'Compound Alert'!AG223 >= 10, "HIGH",IF( 'Compound Alert'!AG223 >= 7, "MED","LOW"))))) -> HIGH | L63: =IF( $B$8="Overall Alert",IF( 'Compound Alert'!T223 >= 7, "HIGH",IF( 'Compound Alert'!T223 >= 5, "MED","LOW")), IF( $B$8="Underlying Vulnerability", IF( 'Compound Alert'!AA223 >= 10, "HIGH",IF( 'Compound Alert'!AA223 >= 7, "MED","LOW")),IF( $B$8="Emerging Threat", IF( 'Compound Alert'!AH223 >= 10, "HIGH",IF( 'Compound Alert'!AH223 >= 7, "MED","LOW"))))) -> HIGH | M63: =IF( $B$8="Overall Alert",IF( 'Compound Alert'!U223 >= 7, "HIGH",IF( 'Compound Alert'!U223 >= 5, "MED","LOW")), IF( $B$8="Underlying Vulnerability", IF( 'Compound Alert'!AB223 >= 10, "HIGH",IF( 'Compound Alert'!AB223 >= 7, "MED","LOW")),IF( $B$8="Emerging Threat", IF( 'Compound Alert'!AI223 >= 10, "HIGH",IF( 'Compound Alert'!AI223 >= 7, "MED","LOW"))))) -> LOW | N63: =IF( $B$8="Overall Alert",IF( 'Compound Alert'!V223 >= 7, "HIGH",IF( 'Compound Alert'!V223 >= 5, "MED","LOW")), IF( $B$8="Underlying Vulnerability", IF( 'Compound Alert'!AC223 >= 10, "HIGH",IF( 'Compound Alert'!AC223 >= 7, "MED","LOW")),IF( $B$8="Emerging Threat", IF( 'Compound Alert'!AJ223 >= 10, "HIGH",IF( 'Compound Alert'!AJ223 >= 7, "MED","LOW"))))) -> MED | O63: =IF( $B$8="Overall Alert",IF( 'Compound Alert'!W223 >= 7, "HIGH",IF( 'Compound Alert'!W223 >= 5, "MED","LOW")), IF( $B$8="Underlying Vulnerability", IF( 'Compound Alert'!AD223 >= 10, "HIGH",IF( 'Compound Alert'!AD223 >= 7, "MED","LOW")),IF( $B$8="Emerging Threat", IF( 'Compound Alert'!AK223 >= 10, "HIGH",IF( 'Compound Alert'!AK223 >= 7, "MED","LOW"))))) -> HIGH
A64: 23 | B64: ='Compound Alert'!B167 -> West Bank and Gaza | C64: ='Compound Alert'!C167 -> PSE | D64: ='Compound Alert'!D167 -> MEA Middle East & North Africa | E64: ='Compound Alert'!E167 -> NA | F64: ='Compound Alert'!F167 -> 162 | G64: =IF($B$8="Overall Alert",'Compound Alert'!G167,IF($B$8="Underlying Vulnerability",'Compound Alert'!J167,IF($B$8="Emerging Threat",'Compound Alert'!M167))) -> 1 | H64: =IF($B$8="Overall Alert",'Compound Alert'!H167,IF($B$8="Underlying Vulnerability",'Compound Alert'!K167,IF($B$8="Emerging Threat",'Compound Alert'!N167))) -> 1 | I64: =ROUNDDOWN(G64,0) -> 1 | J64: =IF( $B$8="Overall Alert",IF( 'Compound Alert'!R167 >= 7, "HIGH",IF( 'Compound Alert'!R167 >= 5, "MED","LOW")), IF( $B$8="Underlying Vulnerability", IF( 'Compound Alert'!Y167 >= 10, "HIGH",IF( 'Compound Alert'!Y167 >= 7, "MED","LOW")),IF( $B$8="Emerging Threat", IF( 'Compound Alert'!AF167 >= 10, "HIGH",IF( 'Compound Alert'!AF167 >= 7, "MED","LOW"))))) -> LOW | K64: =IF( $B$8="Overall Alert",IF( 'Compound Alert'!S167 >= 7, "HIGH",IF( 'Compound Alert'!S167 >= 5, "MED","LOW")), IF( $B$8="Underlying Vulnerability", IF( 'Compound Alert'!Z167 >= 10, "HIGH",IF( 'Compound Alert'!Z167 >= 7, "MED","LOW")),IF( $B$8="Emerging Threat", IF( 'Compound Alert'!AG167 >= 10, "HIGH",IF( 'Compound Alert'!AG167 >= 7, "MED","LOW"))))) -> MED | L64: =IF( $B$8="Overall Alert",IF( 'Compound Alert'!T167 >= 7, "HIGH",IF( 'Compound Alert'!T167 >= 5, "MED","LOW")), IF( $B$8="Underlying Vulnerability", IF( 'Compound Alert'!AA167 >= 10, "HIGH",IF( 'Compound Alert'!AA167 >= 7, "MED","LOW")),IF( $B$8="Emerging Threat", IF( 'Compound Alert'!AH167 >= 10, "HIGH",IF( 'Compound Alert'!AH167 >= 7, "MED","LOW"))))) -> MED | M64: =IF( $B$8="Overall Alert",IF( 'Compound Alert'!U167 >= 7, "HIGH",IF( 'Compound Alert'!U167 >= 5, "MED","LOW")), IF( $B$8="Underlying Vulnerability", IF( 'Compound Alert'!AB167 >= 10, "HIGH",IF( 'Compound Alert'!AB167 >= 7, "MED","LOW")),IF( $B$8="Emerging Threat", IF( 'Compound Alert'!AI167 >= 10, "HIGH",IF( 'Compound Alert'!AI167 >= 7, "MED","LOW"))))) -> LOW | N64: =IF( $B$8="Overall Alert",IF( 'Compound Alert'!V167 >= 7, "HIGH",IF( 'Compound Alert'!V167 >= 5, "MED","LOW")), IF( $B$8="Underlying Vulnerability", IF( 'Compound Alert'!AC167 >= 10, "HIGH",IF( 'Compound Alert'!AC167 >= 7, "MED","LOW")),IF( $B$8="Emerging Threat", IF( 'Compound Alert'!AJ167 >= 10, "HIGH",IF( 'Compound Alert'!AJ167 >= 7, "MED","LOW"))))) -> LOW | O64: =IF( $B$8="Overall Alert",IF( 'Compound Alert'!W167 >= 7, "HIGH",IF( 'Compound Alert'!W167 >= 5, "MED","LOW")), IF( $B$8="Underlying Vulnerability", IF( 'Compound Alert'!AD167 >= 10, "HIGH",IF( 'Compound Alert'!AD167 >= 7, "MED","LOW")),IF( $B$8="Emerging Threat", IF( 'Compound Alert'!AK167 >= 10, "HIGH",IF( 'Compound Alert'!AK167 >= 7, "MED","LOW"))))) -> LOW
A65: 24 | B65: ='Compound Alert'!B23 -> Bangladesh | C65: ='Compound Alert'!C23 -> BGD | D65: ='Compound Alert'!D23 -> SAS South Asia | E65: ='Compound Alert'!E23 -> IDA | F65: ='Compound Alert'!F23 -> 18 | G65: =IF($B$8="Overall Alert",'Compound Alert'!G23,IF($B$8="Underlying Vulnerability",'Compound Alert'!J23,IF($B$8="Emerging Threat",'Compound Alert'!M23))) -> 2 | H65: =IF($B$8="Overall Alert",'Compound Alert'!H23,IF($B$8="Underlying Vulnerability",'Compound Alert'!K23,IF($B$8="Emerging Threat",'Compound Alert'!N23))) -> 2 | I65: =ROUNDDOWN(G65,0) -> 2 | J65: =IF( $B$8="Overall Alert",IF( 'Compound Alert'!R23 >= 7, "HIGH",IF( 'Compound Alert'!R23 >= 5, "MED","LOW")), IF( $B$8="Underlying Vulnerability", IF( 'Compound Alert'!Y23 >= 10, "HIGH",IF( 'Compound Alert'!Y23 >= 7, "MED","LOW")),IF( $B$8="Emerging Threat", IF( 'Compound Alert'!AF23 >= 10, "HIGH",IF( 'Compound Alert'!AF23 >= 7, "MED","LOW"))))) -> HIGH | K65: =IF( $B$8="Overall Alert",IF( 'Compound Alert'!S23 >= 7, "HIGH",IF( 'Compound Alert'!S23 >= 5, "MED","LOW")), IF( $B$8="Underlying Vulnerability", IF( 'Compound Alert'!Z23 >= 10, "HIGH",IF( 'Compound Alert'!Z23 >= 7, "MED","LOW")),IF( $B$8="Emerging Threat", IF( 'Compound Alert'!AG23 >= 10, "HIGH",IF( 'Compound Alert'!AG23 >= 7, "MED","LOW"))))) -> LOW | L65: =IF( $B$8="Overall Alert",IF( 'Compound Alert'!T23 >= 7, "HIGH",IF( 'Compound Alert'!T23 >= 5, "MED","LOW")), IF( $B$8="Underlying Vulnerability", IF( 'Compound Alert'!AA23 >= 10, "HIGH",IF( 'Compound Alert'!AA23 >= 7, "MED","LOW")),IF( $B$8="Emerging Threat", IF( 'Compound Alert'!AH23 >= 10, "HIGH",IF( 'Compound Alert'!AH23 >= 7, "MED","LOW"))))) -> LOW | M65: =IF( $B$8="Overall Alert",IF( 'Compound Alert'!U23 >= 7, "HIGH",IF( 'Compound Alert'!U23 >= 5, "MED","LOW")), IF( $B$8="Underlying Vulnerability", IF( 'Compound Alert'!AB23 >= 10, "HIGH",IF( 'Compound Alert'!AB23 >= 7, "MED","LOW")),IF( $B$8="Emerging Threat", IF( 'Compound Alert'!AI23 >= 10, "HIGH",IF( 'Compound Alert'!AI23 >= 7, "MED","LOW"))))) -> LOW | N65: =IF( $B$8="Overall Alert",IF( 'Compound Alert'!V23 >= 7, "HIGH",IF( 'Compound Alert'!V23 >= 5, "MED","LOW")), IF( $B$8="Underlying Vulnerability", IF( 'Compound Alert'!AC23 >= 10, "HIGH",IF( 'Compound Alert'!AC23 >= 7, "MED","LOW")),IF( $B$8="Emerging Threat", IF( 'Compound Alert'!AJ23 >= 10, "HIGH",IF( 'Compound Alert'!AJ23 >= 7, "MED","LOW"))))) -> HIGH | O65: =IF( $B$8="Overall Alert",IF( 'Compound Alert'!W23 >= 7, "HIGH",IF( 'Compound Alert'!W23 >= 5, "MED","LOW")), IF( $B$8="Underlying Vulnerability", IF( 'Compound Alert'!AD23 >= 10, "HIGH",IF( 'Compound Alert'!AD23 >= 7, "MED","LOW")),IF( $B$8="Emerging Threat", IF( 'Compound Alert'!AK23 >= 10, "HIGH",IF( 'Compound Alert'!AK23 >= 7, "MED","LOW"))))) -> LOW
A66: 25 | B66: ='Compound Alert'!B106 -> Kenya | C66: ='Compound Alert'!C106 -> KEN | D66: ='Compound Alert'!D106 -> SSF Sub-Saharan Africa | E66: ='Compound Alert'!E106 -> Blend | F66: ='Compound Alert'!F106 -> 101 | G66: =IF($B$8="Overall Alert",'Compound Alert'!G106,IF($B$8="Underlying Vulnerability",'Compound Alert'!J106,IF($B$8="Emerging Threat",'Compound Alert'!M106))) -> 2.5 | H66: =IF($B$8="Overall Alert",'Compound Alert'!H106,IF($B$8="Underlying Vulnerability",'Compound Alert'!K106,IF($B$8="Emerging Threat",'Compound Alert'!N106))) -> 2.5 | I66: =ROUNDDOWN(G66,0) -> 2 | J66: =IF( $B$8="Overall Alert",IF( 'Compound Alert'!R106 >= 7, "HIGH",IF( 'Compound Alert'!R106 >= 5, "MED","LOW")), IF( $B$8="Underlying Vulnerability", IF( 'Compound Alert'!Y106 >= 10, "HIGH",IF( 'Compound Alert'!Y106 >= 7, "MED","LOW")),IF( $B$8="Emerging Threat", IF( 'Compound Alert'!AF106 >= 10, "HIGH",IF( 'Compound Alert'!AF106 >= 7, "MED","LOW"))))) -> LOW | K66: =IF( $B$8="Overall Alert",IF( 'Compound Alert'!S106 >= 7, "HIGH",IF( 'Compound Alert'!S106 >= 5, "MED","LOW")), IF( $B$8="Underlying Vulnerability", IF( 'Compound Alert'!Z106 >= 10, "HIGH",IF( 'Compound Alert'!Z106 >= 7, "MED","LOW")),IF( $B$8="Emerging Threat", IF( 'Compound Alert'!AG106 >= 10, "HIGH",IF( 'Compound Alert'!AG106 >= 7, "MED","LOW"))))) -> HIGH | L66: =IF( $B$8="Overall Alert",IF( 'Compound Alert'!T106 >= 7, "HIGH",IF( 'Compound Alert'!T106 >= 5, "MED","LOW")), IF( $B$8="Underlying Vulnerability", IF( 'Compound Alert'!AA106 >= 10, "HIGH",IF( 'Compound Alert'!AA106 >= 7, "MED","LOW")),IF( $B$8="Emerging Threat", IF( 'Compound Alert'!AH106 >= 10, "HIGH",IF( 'Compound Alert'!AH106 >= 7, "MED","LOW"))))) -> MED | M66: =IF( $B$8="Overall Alert",IF( 'Compound Alert'!U106 >= 7, "HIGH",IF( 'Compound Alert'!U106 >= 5, "MED","LOW")), IF( $B$8="Underlying Vulnerability", IF( 'Compound Alert'!AB106 >= 10, "HIGH",IF( 'Compound Alert'!AB106 >= 7, "MED","LOW")),IF( $B$8="Emerging Threat", IF( 'Compound Alert'!AI106 >= 10, "HIGH",IF( 'Compound Alert'!AI106 >= 7, "MED","LOW"))))) -> LOW | N66: =IF( $B$8="Overall Alert",IF( 'Compound Alert'!V106 >= 7, "HIGH",IF( 'Compound Alert'!V106 >= 5, "MED","LOW")), IF( $B$8="Underlying Vulnerability", IF( 'Compound Alert'!AC106 >= 10, "HIGH",IF( 'Compound Alert'!AC106 >= 7, "MED","LOW")),IF( $B$8="Emerging Threat", IF( 'Compound Alert'!AJ106 >= 10, "HIGH",IF( 'Compound Alert'!AJ106 >= 7, "MED","LOW"))))) -> HIGH | O66: =IF( $B$8="Overall Alert",IF( 'Compound Alert'!W106 >= 7, "HIGH",IF( 'Compound Alert'!W106 >= 5, "MED","LOW")), IF( $B$8="Underlying Vulnerability", IF( 'Compound Alert'!AD106 >= 10, "HIGH",IF( 'Compound Alert'!AD106 >= 7, "MED","LOW")),IF( $B$8="Emerging Threat", IF( 'Compound Alert'!AK106 >= 10, "HIGH",IF( 'Compound Alert'!AK106 >= 7, "MED","LOW"))))) -> LOW
A67: 26 | B67: ='Compound Alert'!B44 -> Cameroon | C67: ='Compound Alert'!C44 -> CMR | D67: ='Compound Alert'!D44 -> SSF Sub-Saharan Africa | E67: ='Compound Alert'!E44 -> Blend | F67: ='Compound Alert'!F44 -> 39 | G67: =IF($B$8="Overall Alert",'Compound Alert'!G44,IF($B$8="Underlying Vulnerability",'Compound Alert'!J44,IF($B$8="Emerging Threat",'Compound Alert'!M44))) -> 1 | H67: =IF($B$8="Overall Alert",'Compound Alert'!H44,IF($B$8="Underlying Vulnerability",'Compound Alert'!K44,IF($B$8="Emerging Threat",'Compound Alert'!N44))) -> 1 | I67: =ROUNDDOWN(G67,0) -> 1 | J67: =IF( $B$8="Overall Alert",IF( 'Compound Alert'!R44 >= 7, "HIGH",IF( 'Compound Alert'!R44 >= 5, "MED","LOW")), IF( $B$8="Underlying Vulnerability", IF( 'Compound Alert'!Y44 >= 10, "HIGH",IF( 'Compound Alert'!Y44 >= 7, "MED","LOW")),IF( $B$8="Emerging Threat", IF( 'Compound Alert'!AF44 >= 10, "HIGH",IF( 'Compound Alert'!AF44 >= 7, "MED","LOW"))))) -> LOW | K67: =IF( $B$8="Overall Alert",IF( 'Compound Alert'!S44 >= 7, "HIGH",IF( 'Compound Alert'!S44 >= 5, "MED","LOW")), IF( $B$8="Underlying Vulnerability", IF( 'Compound Alert'!Z44 >= 10, "HIGH",IF( 'Compound Alert'!Z44 >= 7, "MED","LOW")),IF( $B$8="Emerging Threat", IF( 'Compound Alert'!AG44 >= 10, "HIGH",IF( 'Compound Alert'!AG44 >= 7, "MED","LOW"))))) -> HIGH | L67: =IF( $B$8="Overall Alert",IF( 'Compound Alert'!T44 >= 7, "HIGH",IF( 'Compound Alert'!T44 >= 5, "MED","LOW")), IF( $B$8="Underlying Vulnerability", IF( 'Compound Alert'!AA44 >= 10, "HIGH",IF( 'Compound Alert'!AA44 >= 7, "MED","LOW")),IF( $B$8="Emerging Threat", IF( 'Compound Alert'!AH44 >= 10, "HIGH",IF( 'Compound Alert'!AH44 >= 7, "MED","LOW"))))) -> LOW | M67: =IF( $B$8="Overall Alert",IF( 'Compound Alert'!U44 >= 7, "HIGH",IF( 'Compound Alert'!U44 >= 5, "MED","LOW")), IF( $B$8="Underlying Vulnerability", IF( 'Compound Alert'!AB44 >= 10, "HIGH",IF( 'Compound Alert'!AB44 >= 7, "MED","LOW")),IF( $B$8="Emerging Threat", IF( 'Compound Alert'!AI44 >= 10, "HIGH",IF( 'Compound Alert'!AI44 >= 7, "MED","LOW"))))) -> LOW | N67: =IF( $B$8="Overall Alert",IF( 'Compound Alert'!V44 >= 7, "HIGH",IF( 'Compound Alert'!V44 >= 5, "MED","LOW")), IF( $B$8="Underlying Vulnerability", IF( 'Compound Alert'!AC44 >= 10, "HIGH",IF( 'Compound Alert'!AC44 >= 7, "MED","LOW")),IF( $B$8="Emerging Threat", IF( 'Compound Alert'!AJ44 >= 10, "HIGH",IF( 'Compound Alert'!AJ44 >= 7, "MED","LOW"))))) -> LOW | O67: =IF( $B$8="Overall Alert",IF( 'Compound Alert'!W44 >= 7, "HIGH",IF( 'Compound Alert'!W44 >= 5, "MED","LOW")), IF( $B$8="Underlying Vulnerability", IF( 'Compound Alert'!AD44 >= 10, "HIGH",IF( 'Compound Alert'!AD44 >= 7, "MED","LOW")),IF( $B$8="Emerging Threat", IF( 'Compound Alert'!AK44 >= 10, "HIGH",IF( 'Compound Alert'!AK44 >= 7, "MED","LOW"))))) -> LOW
A68: 27 | B68: ='Compound Alert'!B85 -> Guatemala | C68: ='Compound Alert'!C85 -> GTM | D68: ='Compound Alert'!D85 -> LCN Latin America & Caribbean | E68: ='Compound Alert'!E85 -> IBRD | F68: ='Compound Alert'!F85 -> 80 | G68: =IF($B$8="Overall Alert",'Compound Alert'!G85,IF($B$8="Underlying Vulnerability",'Compound Alert'!J85,IF($B$8="Emerging Threat",'Compound Alert'!M85))) -> 1 | H68: =IF($B$8="Overall Alert",'Compound Alert'!H85,IF($B$8="Underlying Vulnerability",'Compound Alert'!K85,IF($B$8="Emerging Threat",'Compound Alert'!N85))) -> 1 | I68: =ROUNDDOWN(G68,0) -> 1 | J68: =IF( $B$8="Overall Alert",IF( 'Compound Alert'!R85 >= 7, "HIGH",IF( 'Compound Alert'!R85 >= 5, "MED","LOW")), IF( $B$8="Underlying Vulnerability", IF( 'Compound Alert'!Y85 >= 10, "HIGH",IF( 'Compound Alert'!Y85 >= 7, "MED","LOW")),IF( $B$8="Emerging Threat", IF( 'Compound Alert'!AF85 >= 10, "HIGH",IF( 'Compound Alert'!AF85 >= 7, "MED","LOW"))))) -> LOW | K68: =IF( $B$8="Overall Alert",IF( 'Compound Alert'!S85 >= 7, "HIGH",IF( 'Compound Alert'!S85 >= 5, "MED","LOW")), IF( $B$8="Underlying Vulnerability", IF( 'Compound Alert'!Z85 >= 10, "HIGH",IF( 'Compound Alert'!Z85 >= 7, "MED","LOW")),IF( $B$8="Emerging Threat", IF( 'Compound Alert'!AG85 >= 10, "HIGH",IF( 'Compound Alert'!AG85 >= 7, "MED","LOW"))))) -> MED | L68: =IF( $B$8="Overall Alert",IF( 'Compound Alert'!T85 >= 7, "HIGH",IF( 'Compound Alert'!T85 >= 5, "MED","LOW")), IF( $B$8="Underlying Vulnerability", IF( 'Compound Alert'!AA85 >= 10, "HIGH",IF( 'Compound Alert'!AA85 >= 7, "MED","LOW")),IF( $B$8="Emerging Threat", IF( 'Compound Alert'!AH85 >= 10, "HIGH",IF( 'Compound Alert'!AH85 >= 7, "MED","LOW"))))) -> LOW | M68: =IF( $B$8="Overall Alert",IF( 'Compound Alert'!U85 >= 7, "HIGH",IF( 'Compound Alert'!U85 >= 5, "MED","LOW")), IF( $B$8="Underlying Vulnerability", IF( 'Compound Alert'!AB85 >= 10, "HIGH",IF( 'Compound Alert'!AB85 >= 7, "MED","LOW")),IF( $B$8="Emerging Threat", IF( 'Compound Alert'!AI85 >= 10, "HIGH",IF( 'Compound Alert'!AI85 >= 7, "MED","LOW"))))) -> LOW | N68: =IF( $B$8="Overall Alert",IF( 'Compound Alert'!V85 >= 7, "HIGH",IF( 'Compound Alert'!V85 >= 5, "MED","LOW")), IF( $B$8="Underlying Vulnerability", IF( 'Compound Alert'!AC85 >= 10, "HIGH",IF( 'Compound Alert'!AC85 >= 7, "MED","LOW")),IF( $B$8="Emerging Threat", IF( 'Compound Alert'!AJ85 >= 10, "HIGH",IF( 'Compound Alert'!AJ85 >= 7, "MED","LOW"))))) -> LOW | O68: =IF( $B$8="Overall Alert",IF( 'Compound Alert'!W85 >= 7, "HIGH",IF( 'Compound Alert'!W85 >= 5, "MED","LOW")), IF( $B$8="Underlying Vulnerability", IF( 'Compound Alert'!AD85 >= 10, "HIGH",IF( 'Compound Alert'!AD85 >= 7, "MED","LOW")),IF( $B$8="Emerging Threat", IF( 'Compound Alert'!AK85 >= 10, "HIGH",IF( 'Compound Alert'!AK85 >= 7, "MED","LOW"))))) -> MED
A69: 28 | B69: ='Compound Alert'!B114 -> Lebanon | C69: ='Compound Alert'!C114 -> LBN | D69: ='Compound Alert'!D114 -> MEA Middle East & North Africa | E69: ='Compound Alert'!E114 -> IBRD | F69: ='Compound Alert'!F114 -> 109 | G69: =IF($B$8="Overall Alert",'Compound Alert'!G114,IF($B$8="Underlying Vulnerability",'Compound Alert'!J114,IF($B$8="Emerging Threat",'Compound Alert'!M114))) -> 1.5 | H69: =IF($B$8="Overall Alert",'Compound Alert'!H114,IF($B$8="Underlying Vulnerability",'Compound Alert'!K114,IF($B$8="Emerging Threat",'Compound Alert'!N114))) -> 1.5 | I69: =ROUNDDOWN(G69,0) -> 1 | J69: =IF( $B$8="Overall Alert",IF( 'Compound Alert'!R114 >= 7, "HIGH",IF( 'Compound Alert'!R114 >= 5, "MED","LOW")), IF( $B$8="Underlying Vulnerability", IF( 'Compound Alert'!Y114 >= 10, "HIGH",IF( 'Compound Alert'!Y114 >= 7, "MED","LOW")),IF( $B$8="Emerging Threat", IF( 'Compound Alert'!AF114 >= 10, "HIGH",IF( 'Compound Alert'!AF114 >= 7, "MED","LOW"))))) -> LOW | K69: =IF( $B$8="Overall Alert",IF( 'Compound Alert'!S114 >= 7, "HIGH",IF( 'Compound Alert'!S114 >= 5, "MED","LOW")), IF( $B$8="Underlying Vulnerability", IF( 'Compound Alert'!Z114 >= 10, "HIGH",IF( 'Compound Alert'!Z114 >= 7, "MED","LOW")),IF( $B$8="Emerging Threat", IF( 'Compound Alert'!AG114 >= 10, "HIGH",IF( 'Compound Alert'!AG114 >= 7, "MED","LOW"))))) -> LOW | L69: =IF( $B$8="Overall Alert",IF( 'Compound Alert'!T114 >= 7, "HIGH",IF( 'Compound Alert'!T114 >= 5, "MED","LOW")), IF( $B$8="Underlying Vulnerability", IF( 'Compound Alert'!AA114 >= 10, "HIGH",IF( 'Compound Alert'!AA114 >= 7, "MED","LOW")),IF( $B$8="Emerging Threat", IF( 'Compound Alert'!AH114 >= 10, "HIGH",IF( 'Compound Alert'!AH114 >= 7, "MED","LOW"))))) -> HIGH | M69: =IF( $B$8="Overall Alert",IF( 'Compound Alert'!U114 >= 7, "HIGH",IF( 'Compound Alert'!U114 >= 5, "MED","LOW")), IF( $B$8="Underlying Vulnerability", IF( 'Compound Alert'!AB114 >= 10, "HIGH",IF( 'Compound Alert'!AB114 >= 7, "MED","LOW")),IF( $B$8="Emerging Threat", IF( 'Compound Alert'!AI114 >= 10, "HIGH",IF( 'Compound Alert'!AI114 >= 7, "MED","LOW"))))) -> LOW | N69: =IF( $B$8="Overall Alert",IF( 'Compound Alert'!V114 >= 7, "HIGH",IF( 'Compound Alert'!V114 >= 5, "MED","LOW")), IF( $B$8="Underlying Vulnerability", IF( 'Compound Alert'!AC114 >= 10, "HIGH",IF( 'Compound Alert'!AC114 >= 7, "MED","LOW")),IF( $B$8="Emerging Threat", IF( 'Compound Alert'!AJ114 >= 10, "HIGH",IF( 'Compound Alert'!AJ114 >= 7, "MED","LOW"))))) -> LOW | O69: =IF( $B$8="Overall Alert",IF( 'Compound Alert'!W114 >= 7, "HIGH",IF( 'Compound Alert'!W114 >= 5, "MED","LOW")), IF( $B$8="Underlying Vulnerability", IF( 'Compound Alert'!AD114 >= 10, "HIGH",IF( 'Compound Alert'!AD114 >= 7, "MED","LOW")),IF( $B$8="Emerging Threat", IF( 'Compound Alert'!AK114 >= 10, "HIGH",IF( 'Compound Alert'!AK114 >= 7, "MED","LOW"))))) -> MED
A70: 29 | B70: ='Compound Alert'!B140 -> Mozambique | C70: ='Compound Alert'!C140 -> MOZ | D70: ='Compound Alert'!D140 -> SSF Sub-Saharan Africa | E70: ='Compound Alert'!E140 -> IDA | F70: ='Compound Alert'!F140 -> 135 | G70: =IF($B$8="Overall Alert",'Compound Alert'!G140,IF($B$8="Underlying Vulnerability",'Compound Alert'!J140,IF($B$8="Emerging Threat",'Compound Alert'!M140))) -> 1 | H70: =IF($B$8="Overall Alert",'Compound Alert'!H140,IF($B$8="Underlying Vulnerability",'Compound Alert'!K140,IF($B$8="Emerging Threat",'Compound Alert'!N140))) -> 1 | I70: =ROUNDDOWN(G70,0) -> 1 | J70: =IF( $B$8="Overall Alert",IF( 'Compound Alert'!R140 >= 7, "HIGH",IF( 'Compound Alert'!R140 >= 5, "MED","LOW")), IF( $B$8="Underlying Vulnerability", IF( 'Compound Alert'!Y140 >= 10, "HIGH",IF( 'Compound Alert'!Y140 >= 7, "MED","LOW")),IF( $B$8="Emerging Threat", IF( 'Compound Alert'!AF140 >= 10, "HIGH",IF( 'Compound Alert'!AF140 >= 7, "MED","LOW"))))) -> LOW | K70: =IF( $B$8="Overall Alert",IF( 'Compound Alert'!S140 >= 7, "HIGH",IF( 'Compound Alert'!S140 >= 5, "MED","LOW")), IF( $B$8="Underlying Vulnerability", IF( 'Compound Alert'!Z140 >= 10, "HIGH",IF( 'Compound Alert'!Z140 >= 7, "MED","LOW")),IF( $B$8="Emerging Threat", IF( 'Compound Alert'!AG140 >= 10, "HIGH",IF( 'Compound Alert'!AG140 >= 7, "MED","LOW"))))) -> HIGH | L70: =IF( $B$8="Overall Alert",IF( 'Compound Alert'!T140 >= 7, "HIGH",IF( 'Compound Alert'!T140 >= 5, "MED","LOW")), IF( $B$8="Underlying Vulnerability", IF( 'Compound Alert'!AA140 >= 10, "HIGH",IF( 'Compound Alert'!AA140 >= 7, "MED","LOW")),IF( $B$8="Emerging Threat", IF( 'Compound Alert'!AH140 >= 10, "HIGH",IF( 'Compound Alert'!AH140 >= 7, "MED","LOW"))))) -> LOW | M70: =IF( $B$8="Overall Alert",IF( 'Compound Alert'!U140 >= 7, "HIGH",IF( 'Compound Alert'!U140 >= 5, "MED","LOW")), IF( $B$8="Underlying Vulnerability", IF( 'Compound Alert'!AB140 >= 10, "HIGH",IF( 'Compound Alert'!AB140 >= 7, "MED","LOW")),IF( $B$8="Emerging Threat", IF( 'Compound Alert'!AI140 >= 10, "HIGH",IF( 'Compound Alert'!AI140 >= 7, "MED","LOW"))))) -> LOW | N70: =IF( $B$8="Overall Alert",IF( 'Compound Alert'!V140 >= 7, "HIGH",IF( 'Compound Alert'!V140 >= 5, "MED","LOW")), IF( $B$8="Underlying Vulnerability", IF( 'Compound Alert'!AC140 >= 10, "HIGH",IF( 'Compound Alert'!AC140 >= 7, "MED","LOW")),IF( $B$8="Emerging Threat", IF( 'Compound Alert'!AJ140 >= 10, "HIGH",IF( 'Compound Alert'!AJ140 >= 7, "MED","LOW"))))) -> LOW | O70: =IF( $B$8="Overall Alert",IF( 'Compound Alert'!W140 >= 7, "HIGH",IF( 'Compound Alert'!W140 >= 5, "MED","LOW")), IF( $B$8="Underlying Vulnerability", IF( 'Compound Alert'!AD140 >= 10, "HIGH",IF( 'Compound Alert'!AD140 >= 7, "MED","LOW")),IF( $B$8="Emerging Threat", IF( 'Compound Alert'!AK140 >= 10, "HIGH",IF( 'Compound Alert'!AK140 >= 7, "MED","LOW"))))) -> LOW
A71: 30 | B71: ='Compound Alert'!B63 -> Egypt, Arab Rep. | C71: ='Compound Alert'!C63 -> EGY | D71: ='Compound Alert'!D63 -> MEA Middle East & North Africa | E71: ='Compound Alert'!E63 -> IBRD | F71: ='Compound Alert'!F63 -> 58 | G71: =IF($B$8="Overall Alert",'Compound Alert'!G63,IF($B$8="Underlying Vulnerability",'Compound Alert'!J63,IF($B$8="Emerging Threat",'Compound Alert'!M63))) -> 0.5 | H71: =IF($B$8="Overall Alert",'Compound Alert'!H63,IF($B$8="Underlying Vulnerability",'Compound Alert'!K63,IF($B$8="Emerging Threat",'Compound Alert'!N63))) -> 0.5 | I71: =ROUNDDOWN(G71,0) -> 0 | J71: =IF( $B$8="Overall Alert",IF( 'Compound Alert'!R63 >= 7, "HIGH",IF( 'Compound Alert'!R63 >= 5, "MED","LOW")), IF( $B$8="Underlying Vulnerability", IF( 'Compound Alert'!Y63 >= 10, "HIGH",IF( 'Compound Alert'!Y63 >= 7, "MED","LOW")),IF( $B$8="Emerging Threat", IF( 'Compound Alert'!AF63 >= 10, "HIGH",IF( 'Compound Alert'!AF63 >= 7, "MED","LOW"))))) -> LOW | K71: =IF( $B$8="Overall Alert",IF( 'Compound Alert'!S63 >= 7, "HIGH",IF( 'Compound Alert'!S63 >= 5, "MED","LOW")), IF( $B$8="Underlying Vulnerability", IF( 'Compound Alert'!Z63 >= 10, "HIGH",IF( 'Compound Alert'!Z63 >= 7, "MED","LOW")),IF( $B$8="Emerging Threat", IF( 'Compound Alert'!AG63 >= 10, "HIGH",IF( 'Compound Alert'!AG63 >= 7, "MED","LOW"))))) -> LOW | L71: =IF( $B$8="Overall Alert",IF( 'Compound Alert'!T63 >= 7, "HIGH",IF( 'Compound Alert'!T63 >= 5, "MED","LOW")), IF( $B$8="Underlying Vulnerability", IF( 'Compound Alert'!AA63 >= 10, "HIGH",IF( 'Compound Alert'!AA63 >= 7, "MED","LOW")),IF( $B$8="Emerging Threat", IF( 'Compound Alert'!AH63 >= 10, "HIGH",IF( 'Compound Alert'!AH63 >= 7, "MED","LOW"))))) -> LOW | M71: =IF( $B$8="Overall Alert",IF( 'Compound Alert'!U63 >= 7, "HIGH",IF( 'Compound Alert'!U63 >= 5, "MED","LOW")), IF( $B$8="Underlying Vulnerability", IF( 'Compound Alert'!AB63 >= 10, "HIGH",IF( 'Compound Alert'!AB63 >= 7, "MED","LOW")),IF( $B$8="Emerging Threat", IF( 'Compound Alert'!AI63 >= 10, "HIGH",IF( 'Compound Alert'!AI63 >= 7, "MED","LOW"))))) -> LOW | N71: =IF( $B$8="Overall Alert",IF( 'Compound Alert'!V63 >= 7, "HIGH",IF( 'Compound Alert'!V63 >= 5, "MED","LOW")), IF( $B$8="Underlying Vulnerability", IF( 'Compound Alert'!AC63 >= 10, "HIGH",IF( 'Compound Alert'!AC63 >= 7, "MED","LOW")),IF( $B$8="Emerging Threat", IF( 'Compound Alert'!AJ63 >= 10, "HIGH",IF( 'Compound Alert'!AJ63 >= 7, "MED","LOW"))))) -> LOW | O71: =IF( $B$8="Overall Alert",IF( 'Compound Alert'!W63 >= 7, "HIGH",IF( 'Compound Alert'!W63 >= 5, "MED","LOW")), IF( $B$8="Underlying Vulnerability", IF( 'Compound Alert'!AD63 >= 10, "HIGH",IF( 'Compound Alert'!AD63 >= 7, "MED","LOW")),IF( $B$8="Emerging Threat", IF( 'Compound Alert'!AK63 >= 10, "HIGH",IF( 'Compound Alert'!AK63 >= 7, "MED","LOW"))))) -> MED
A72: 31 | B72: ='Compound Alert'!B31 -> Bolivia | C72: ='Compound Alert'!C31 -> BOL | D72: ='Compound Alert'!D31 -> LCN Latin America & Caribbean | E72: ='Compound Alert'!E31 -> IBRD | F72: ='Compound Alert'!F31 -> 26 | G72: =IF($B$8="Overall Alert",'Compound Alert'!G31,IF($B$8="Underlying Vulnerability",'Compound Alert'!J31,IF($B$8="Emerging Threat",'Compound Alert'!M31))) -> 0 | H72: =IF($B$8="Overall Alert",'Compound Alert'!H31,IF($B$8="Underlying Vulnerability",'Compound Alert'!K31,IF($B$8="Emerging Threat",'Compound Alert'!N31))) -> 0 | I72: =ROUNDDOWN(G72,0) -> 0 | J72: =IF( $B$8="Overall Alert",IF( 'Compound Alert'!R31 >= 7, "HIGH",IF( 'Compound Alert'!R31 >= 5, "MED","LOW")), IF( $B$8="Underlying Vulnerability", IF( 'Compound Alert'!Y31 >= 10, "HIGH",IF( 'Compound Alert'!Y31 >= 7, "MED","LOW")),IF( $B$8="Emerging Threat", IF( 'Compound Alert'!AF31 >= 10, "HIGH",IF( 'Compound Alert'!AF31 >= 7, "MED","LOW"))))) -> LOW | K72: =IF( $B$8="Overall Alert",IF( 'Compound Alert'!S31 >= 7, "HIGH",IF( 'Compound Alert'!S31 >= 5, "MED","LOW")), IF( $B$8="Underlying Vulnerability", IF( 'Compound Alert'!Z31 >= 10, "HIGH",IF( 'Compound Alert'!Z31 >= 7, "MED","LOW")),IF( $B$8="Emerging Threat", IF( 'Compound Alert'!AG31 >= 10, "HIGH",IF( 'Compound Alert'!AG31 >= 7, "MED","LOW"))))) -> LOW | L72: =IF( $B$8="Overall Alert",IF( 'Compound Alert'!T31 >= 7, "HIGH",IF( 'Compound Alert'!T31 >= 5, "MED","LOW")), IF( $B$8="Underlying Vulnerability", IF( 'Compound Alert'!AA31 >= 10, "HIGH",IF( 'Compound Alert'!AA31 >= 7, "MED","LOW")),IF( $B$8="Emerging Threat", IF( 'Compound Alert'!AH31 >= 10, "HIGH",IF( 'Compound Alert'!AH31 >= 7, "MED","LOW"))))) -> LOW | M72: =IF( $B$8="Overall Alert",IF( 'Compound Alert'!U31 >= 7, "HIGH",IF( 'Compound Alert'!U31 >= 5, "MED","LOW")), IF( $B$8="Underlying Vulnerability", IF( 'Compound Alert'!AB31 >= 10, "HIGH",IF( 'Compound Alert'!AB31 >= 7, "MED","LOW")),IF( $B$8="Emerging Threat", IF( 'Compound Alert'!AI31 >= 10, "HIGH",IF( 'Compound Alert'!AI31 >= 7, "MED","LOW"))))) -> LOW | N72: =IF( $B$8="Overall Alert",IF( 'Compound Alert'!V31 >= 7, "HIGH",IF( 'Compound Alert'!V31 >= 5, "MED","LOW")), IF( $B$8="Underlying Vulnerability", IF( 'Compound Alert'!AC31 >= 10, "HIGH",IF( 'Compound Alert'!AC31 >= 7, "MED","LOW")),IF( $B$8="Emerging Threat", IF( 'Compound Alert'!AJ31 >= 10, "HIGH",IF( 'Compound Alert'!AJ31 >= 7, "MED","LOW"))))) -> LOW | O72: =IF( $B$8="Overall Alert",IF( 'Compound Alert'!W31 >= 7, "HIGH",IF( 'Compound Alert'!W31 >= 5, "MED","LOW")), IF( $B$8="Underlying Vulnerability", IF( 'Compound Alert'!AD31 >= 10, "HIGH",IF( 'Compound Alert'!AD31 >= 7, "MED","LOW")),IF( $B$8="Emerging Threat", IF( 'Compound Alert'!AK31 >= 10, "HIGH",IF( 'Compound Alert'!AK31 >= 7, "MED","LOW"))))) -> LOW
A73: 32 | B73: ='Compound Alert'!B164 -> Korea, Dem. People's Rep. | C73: ='Compound Alert'!C164 -> PRK | D73: ='Compound Alert'!D164 -> EAS East Asia & Pacific | E73: ='Compound Alert'!E164 -> NA | F73: ='Compound Alert'!F164 -> 159 | G73: =IF($B$8="Overall Alert",'Compound Alert'!G164,IF($B$8="Underlying Vulnerability",'Compound Alert'!J164,IF($B$8="Emerging Threat",'Compound Alert'!M164))) -> 0.5 | H73: =IF($B$8="Overall Alert",'Compound Alert'!H164,IF($B$8="Underlying Vulnerability",'Compound Alert'!K164,IF($B$8="Emerging Threat",'Compound Alert'!N164))) -> 0.5 | I73: =ROUNDDOWN(G73,0) -> 0 | J73: =IF( $B$8="Overall Alert",IF( 'Compound Alert'!R164 >= 7, "HIGH",IF( 'Compound Alert'!R164 >= 5, "MED","LOW")), IF( $B$8="Underlying Vulnerability", IF( 'Compound Alert'!Y164 >= 10, "HIGH",IF( 'Compound Alert'!Y164 >= 7, "MED","LOW")),IF( $B$8="Emerging Threat", IF( 'Compound Alert'!AF164 >= 10, "HIGH",IF( 'Compound Alert'!AF164 >= 7, "MED","LOW"))))) -> LOW | K73: =IF( $B$8="Overall Alert",IF( 'Compound Alert'!S164 >= 7, "HIGH",IF( 'Compound Alert'!S164 >= 5, "MED","LOW")), IF( $B$8="Underlying Vulnerability", IF( 'Compound Alert'!Z164 >= 10, "HIGH",IF( 'Compound Alert'!Z164 >= 7, "MED","LOW")),IF( $B$8="Emerging Threat", IF( 'Compound Alert'!AG164 >= 10, "HIGH",IF( 'Compound Alert'!AG164 >= 7, "MED","LOW"))))) -> LOW | L73: =IF( $B$8="Overall Alert",IF( 'Compound Alert'!T164 >= 7, "HIGH",IF( 'Compound Alert'!T164 >= 5, "MED","LOW")), IF( $B$8="Underlying Vulnerability", IF( 'Compound Alert'!AA164 >= 10, "HIGH",IF( 'Compound Alert'!AA164 >= 7, "MED","LOW")),IF( $B$8="Emerging Threat", IF( 'Compound Alert'!AH164 >= 10, "HIGH",IF( 'Compound Alert'!AH164 >= 7, "MED","LOW"))))) -> MED | M73: =IF( $B$8="Overall Alert",IF( 'Compound Alert'!U164 >= 7, "HIGH",IF( 'Compound Alert'!U164 >= 5, "MED","LOW")), IF( $B$8="Underlying Vulnerability", IF( 'Compound Alert'!AB164 >= 10, "HIGH",IF( 'Compound Alert'!AB164 >= 7, "MED","LOW")),IF( $B$8="Emerging Threat", IF( 'Compound Alert'!AI164 >= 10, "HIGH",IF( 'Compound Alert'!AI164 >= 7, "MED","LOW"))))) -> LOW | N73: =IF( $B$8="Overall Alert",IF( 'Compound Alert'!V164 >= 7, "HIGH",IF( 'Compound Alert'!V164 >= 5, "MED","LOW")), IF( $B$8="Underlying Vulnerability", IF( 'Compound Alert'!AC164 >= 10, "HIGH",IF( 'Compound Alert'!AC164 >= 7, "MED","LOW")),IF( $B$8="Emerging Threat", IF( 'Compound Alert'!AJ164 >= 10, "HIGH",IF( 'Compound Alert'!AJ164 >= 7, "MED","LOW"))))) -> LOW | O73: =IF( $B$8="Overall Alert",IF( 'Compound Alert'!W164 >= 7, "HIGH",IF( 'Compound Alert'!W164 >= 5, "MED","LOW")), IF( $B$8="Underlying Vulnerability", IF( 'Compound Alert'!AD164 >= 10, "HIGH",IF( 'Compound Alert'!AD164 >= 7, "MED","LOW")),IF( $B$8="Emerging Threat", IF( 'Compound Alert'!AK164 >= 10, "HIGH",IF( 'Compound Alert'!AK164 >= 7, "MED","LOW"))))) -> LOW
A74: 33 | B74: ='Compound Alert'!B213 -> Venezuela, RB | C74: ='Compound Alert'!C213 -> VEN | D74: ='Compound Alert'!D213 -> LCN Latin America & Caribbean | E74: ='Compound Alert'!E213 -> IBRD | F74: ='Compound Alert'!F213 -> 0 | G74: =IF($B$8="Overall Alert",'Compound Alert'!G213,IF($B$8="Underlying Vulnerability",'Compound Alert'!J213,IF($B$8="Emerging Threat",'Compound Alert'!M213))) -> 1.5 | H74: =IF($B$8="Overall Alert",'Compound Alert'!H213,IF($B$8="Underlying Vulnerability",'Compound Alert'!K213,IF($B$8="Emerging Threat",'Compound Alert'!N213))) -> 1.5 | I74: =ROUNDDOWN(G74,0) -> 1 | J74: =IF( $B$8="Overall Alert",IF( 'Compound Alert'!R213 >= 7, "HIGH",IF( 'Compound Alert'!R213 >= 5, "MED","LOW")), IF( $B$8="Underlying Vulnerability", IF( 'Compound Alert'!Y213 >= 10, "HIGH",IF( 'Compound Alert'!Y213 >= 7, "MED","LOW")),IF( $B$8="Emerging Threat", IF( 'Compound Alert'!AF213 >= 10, "HIGH",IF( 'Compound Alert'!AF213 >= 7, "MED","LOW"))))) -> LOW | K74: =IF( $B$8="Overall Alert",IF( 'Compound Alert'!S213 >= 7, "HIGH",IF( 'Compound Alert'!S213 >= 5, "MED","LOW")), IF( $B$8="Underlying Vulnerability", IF( 'Compound Alert'!Z213 >= 10, "HIGH",IF( 'Compound Alert'!Z213 >= 7, "MED","LOW")),IF( $B$8="Emerging Threat", IF( 'Compound Alert'!AG213 >= 10, "HIGH",IF( 'Compound Alert'!AG213 >= 7, "MED","LOW"))))) -> LOW | L74: =IF( $B$8="Overall Alert",IF( 'Compound Alert'!T213 >= 7, "HIGH",IF( 'Compound Alert'!T213 >= 5, "MED","LOW")), IF( $B$8="Underlying Vulnerability", IF( 'Compound Alert'!AA213 >= 10, "HIGH",IF( 'Compound Alert'!AA213 >= 7, "MED","LOW")),IF( $B$8="Emerging Threat", IF( 'Compound Alert'!AH213 >= 10, "HIGH",IF( 'Compound Alert'!AH213 >= 7, "MED","LOW"))))) -> HIGH | M74: =IF( $B$8="Overall Alert",IF( 'Compound Alert'!U213 >= 7, "HIGH",IF( 'Compound Alert'!U213 >= 5, "MED","LOW")), IF( $B$8="Underlying Vulnerability", IF( 'Compound Alert'!AB213 >= 10, "HIGH",IF( 'Compound Alert'!AB213 >= 7, "MED","LOW")),IF( $B$8="Emerging Threat", IF( 'Compound Alert'!AI213 >= 10, "HIGH",IF( 'Compound Alert'!AI213 >= 7, "MED","LOW"))))) -> LOW | N74: =IF( $B$8="Overall Alert",IF( 'Compound Alert'!V213 >= 7, "HIGH",IF( 'Compound Alert'!V213 >= 5, "MED","LOW")), IF( $B$8="Underlying Vulnerability", IF( 'Compound Alert'!AC213 >= 10, "HIGH",IF( 'Compound Alert'!AC213 >= 7, "MED","LOW")),IF( $B$8="Emerging Threat", IF( 'Compound Alert'!AJ213 >= 10, "HIGH",IF( 'Compound Alert'!AJ213 >= 7, "MED","LOW"))))) -> LOW | O74: =IF( $B$8="Overall Alert",IF( 'Compound Alert'!W213 >= 7, "HIGH",IF( 'Compound Alert'!W213 >= 5, "MED","LOW")), IF( $B$8="Underlying Vulnerability", IF( 'Compound Alert'!AD213 >= 10, "HIGH",IF( 'Compound Alert'!AD213 >= 7, "MED","LOW")),IF( $B$8="Emerging Threat", IF( 'Compound Alert'!AK213 >= 10, "HIGH",IF( 'Compound Alert'!AK213 >= 7, "MED","LOW"))))) -> MED
A75: 34 | B75: ='Compound Alert'!B161 -> Papua New Guinea | C75: ='Compound Alert'!C161 -> PNG | D75: ='Compound Alert'!D161 -> EAS East Asia & Pacific | E75: ='Compound Alert'!E161 -> Blend | F75: ='Compound Alert'!F161 -> 156 | G75: =IF($B$8="Overall Alert",'Compound Alert'!G161,IF($B$8="Underlying Vulnerability",'Compound Alert'!J161,IF($B$8="Emerging Threat",'Compound Alert'!M161))) -> 1.5 | H75: =IF($B$8="Overall Alert",'Compound Alert'!H161,IF($B$8="Underlying Vulnerability",'Compound Alert'!K161,IF($B$8="Emerging Threat",'Compound Alert'!N161))) -> 1.5 | I75: =ROUNDDOWN(G75,0) -> 1 | J75: =IF( $B$8="Overall Alert",IF( 'Compound Alert'!R161 >= 7, "HIGH",IF( 'Compound Alert'!R161 >= 5, "MED","LOW")), IF( $B$8="Underlying Vulnerability", IF( 'Compound Alert'!Y161 >= 10, "HIGH",IF( 'Compound Alert'!Y161 >= 7, "MED","LOW")),IF( $B$8="Emerging Threat", IF( 'Compound Alert'!AF161 >= 10, "HIGH",IF( 'Compound Alert'!AF161 >= 7, "MED","LOW"))))) -> LOW | K75: =IF( $B$8="Overall Alert",IF( 'Compound Alert'!S161 >= 7, "HIGH",IF( 'Compound Alert'!S161 >= 5, "MED","LOW")), IF( $B$8="Underlying Vulnerability", IF( 'Compound Alert'!Z161 >= 10, "HIGH",IF( 'Compound Alert'!Z161 >= 7, "MED","LOW")),IF( $B$8="Emerging Threat", IF( 'Compound Alert'!AG161 >= 10, "HIGH",IF( 'Compound Alert'!AG161 >= 7, "MED","LOW"))))) -> LOW | L75: =IF( $B$8="Overall Alert",IF( 'Compound Alert'!T161 >= 7, "HIGH",IF( 'Compound Alert'!T161 >= 5, "MED","LOW")), IF( $B$8="Underlying Vulnerability", IF( 'Compound Alert'!AA161 >= 10, "HIGH",IF( 'Compound Alert'!AA161 >= 7, "MED","LOW")),IF( $B$8="Emerging Threat", IF( 'Compound Alert'!AH161 >= 10, "HIGH",IF( 'Compound Alert'!AH161 >= 7, "MED","LOW"))))) -> MED | M75: =IF( $B$8="Overall Alert",IF( 'Compound Alert'!U161 >= 7, "HIGH",IF( 'Compound Alert'!U161 >= 5, "MED","LOW")), IF( $B$8="Underlying Vulnerability", IF( 'Compound Alert'!AB161 >= 10, "HIGH",IF( 'Compound Alert'!AB161 >= 7, "MED","LOW")),IF( $B$8="Emerging Threat", IF( 'Compound Alert'!AI161 >= 10, "HIGH",IF( 'Compound Alert'!AI161 >= 7, "MED","LOW"))))) -> LOW | N75: =IF( $B$8="Overall Alert",IF( 'Compound Alert'!V161 >= 7, "HIGH",IF( 'Compound Alert'!V161 >= 5, "MED","LOW")), IF( $B$8="Underlying Vulnerability", IF( 'Compound Alert'!AC161 >= 10, "HIGH",IF( 'Compound Alert'!AC161 >= 7, "MED","LOW")),IF( $B$8="Emerging Threat", IF( 'Compound Alert'!AJ161 >= 10, "HIGH",IF( 'Compound Alert'!AJ161 >= 7, "MED","LOW"))))) -> HIGH | O75: =IF( $B$8="Overall Alert",IF( 'Compound Alert'!W161 >= 7, "HIGH",IF( 'Compound Alert'!W161 >= 5, "MED","LOW")), IF( $B$8="Underlying Vulnerability", IF( 'Compound Alert'!AD161 >= 10, "HIGH",IF( 'Compound Alert'!AD161 >= 7, "MED","LOW")),IF( $B$8="Emerging Threat", IF( 'Compound Alert'!AK161 >= 10, "HIGH",IF( 'Compound Alert'!AK161 >= 7, "MED","LOW"))))) -> LOW
A76: 35 | B76: ='Compound Alert'!B57 -> Djibouti | C76: ='Compound Alert'!C57 -> DJI | D76: ='Compound Alert'!D57 -> MEA Middle East & North Africa | E76: ='Compound Alert'!E57 -> IDA | F76: ='Compound Alert'!F57 -> 52 | G76: =IF($B$8="Overall Alert",'Compound Alert'!G57,IF($B$8="Underlying Vulnerability",'Compound Alert'!J57,IF($B$8="Emerging Threat",'Compound Alert'!M57))) -> 2 | H76: =IF($B$8="Overall Alert",'Compound Alert'!H57,IF($B$8="Underlying Vulnerability",'Compound Alert'!K57,IF($B$8="Emerging Threat",'Compound Alert'!N57))) -> 2 | I76: =ROUNDDOWN(G76,0) -> 2 | J76: =IF( $B$8="Overall Alert",IF( 'Compound Alert'!R57 >= 7, "HIGH",IF( 'Compound Alert'!R57 >= 5, "MED","LOW")), IF( $B$8="Underlying Vulnerability", IF( 'Compound Alert'!Y57 >= 10, "HIGH",IF( 'Compound Alert'!Y57 >= 7, "MED","LOW")),IF( $B$8="Emerging Threat", IF( 'Compound Alert'!AF57 >= 10, "HIGH",IF( 'Compound Alert'!AF57 >= 7, "MED","LOW"))))) -> LOW | K76: =IF( $B$8="Overall Alert",IF( 'Compound Alert'!S57 >= 7, "HIGH",IF( 'Compound Alert'!S57 >= 5, "MED","LOW")), IF( $B$8="Underlying Vulnerability", IF( 'Compound Alert'!Z57 >= 10, "HIGH",IF( 'Compound Alert'!Z57 >= 7, "MED","LOW")),IF( $B$8="Emerging Threat", IF( 'Compound Alert'!AG57 >= 10, "HIGH",IF( 'Compound Alert'!AG57 >= 7, "MED","LOW"))))) -> MED | L76: =IF( $B$8="Overall Alert",IF( 'Compound Alert'!T57 >= 7, "HIGH",IF( 'Compound Alert'!T57 >= 5, "MED","LOW")), IF( $B$8="Underlying Vulnerability", IF( 'Compound Alert'!AA57 >= 10, "HIGH",IF( 'Compound Alert'!AA57 >= 7, "MED","LOW")),IF( $B$8="Emerging Threat", IF( 'Compound Alert'!AH57 >= 10, "HIGH",IF( 'Compound Alert'!AH57 >= 7, "MED","LOW"))))) -> MED | M76: =IF( $B$8="Overall Alert",IF( 'Compound Alert'!U57 >= 7, "HIGH",IF( 'Compound Alert'!U57 >= 5, "MED","LOW")), IF( $B$8="Underlying Vulnerability", IF( 'Compound Alert'!AB57 >= 10, "HIGH",IF( 'Compound Alert'!AB57 >= 7, "MED","LOW")),IF( $B$8="Emerging Threat", IF( 'Compound Alert'!AI57 >= 10, "HIGH",IF( 'Compound Alert'!AI57 >= 7, "MED","LOW"))))) -> LOW | N76: =IF( $B$8="Overall Alert",IF( 'Compound Alert'!V57 >= 7, "HIGH",IF( 'Compound Alert'!V57 >= 5, "MED","LOW")), IF( $B$8="Underlying Vulnerability", IF( 'Compound Alert'!AC57 >= 10, "HIGH",IF( 'Compound Alert'!AC57 >= 7, "MED","LOW")),IF( $B$8="Emerging Threat", IF( 'Compound Alert'!AJ57 >= 10, "HIGH",IF( 'Compound Alert'!AJ57 >= 7, "MED","LOW"))))) -> HIGH | O76: =IF( $B$8="Overall Alert",IF( 'Compound Alert'!W57 >= 7, "HIGH",IF( 'Compound Alert'!W57 >= 5, "MED","LOW")), IF( $B$8="Underlying Vulnerability", IF( 'Compound Alert'!AD57 >= 10, "HIGH",IF( 'Compound Alert'!AD57 >= 7, "MED","LOW")),IF( $B$8="Emerging Threat", IF( 'Compound Alert'!AK57 >= 10, "HIGH",IF( 'Compound Alert'!AK57 >= 7, "MED","LOW"))))) -> LOW
A77: 36 | B77: ='Compound Alert'!B51 -> Cuba | C77: ='Compound Alert'!C51 -> CUB | D77: ='Compound Alert'!D51 -> LCN Latin America & Caribbean | E77: ='Compound Alert'!E51 -> NA | F77: ='Compound Alert'!F51 -> 46 | G77: =IF($B$8="Overall Alert",'Compound Alert'!G51,IF($B$8="Underlying Vulnerability",'Compound Alert'!J51,IF($B$8="Emerging Threat",'Compound Alert'!M51))) -> 1.5 | H77: =IF($B$8="Overall Alert",'Compound Alert'!H51,IF($B$8="Underlying Vulnerability",'Compound Alert'!K51,IF($B$8="Emerging Threat",'Compound Alert'!N51))) -> 1.5 | I77: =ROUNDDOWN(G77,0) -> 1 | J77: =IF( $B$8="Overall Alert",IF( 'Compound Alert'!R51 >= 7, "HIGH",IF( 'Compound Alert'!R51 >= 5, "MED","LOW")), IF( $B$8="Underlying Vulnerability", IF( 'Compound Alert'!Y51 >= 10, "HIGH",IF( 'Compound Alert'!Y51 >= 7, "MED","LOW")),IF( $B$8="Emerging Threat", IF( 'Compound Alert'!AF51 >= 10, "HIGH",IF( 'Compound Alert'!AF51 >= 7, "MED","LOW"))))) -> LOW | K77: =IF( $B$8="Overall Alert",IF( 'Compound Alert'!S51 >= 7, "HIGH",IF( 'Compound Alert'!S51 >= 5, "MED","LOW")), IF( $B$8="Underlying Vulnerability", IF( 'Compound Alert'!Z51 >= 10, "HIGH",IF( 'Compound Alert'!Z51 >= 7, "MED","LOW")),IF( $B$8="Emerging Threat", IF( 'Compound Alert'!AG51 >= 10, "HIGH",IF( 'Compound Alert'!AG51 >= 7, "MED","LOW"))))) -> LOW | L77: =IF( $B$8="Overall Alert",IF( 'Compound Alert'!T51 >= 7, "HIGH",IF( 'Compound Alert'!T51 >= 5, "MED","LOW")), IF( $B$8="Underlying Vulnerability", IF( 'Compound Alert'!AA51 >= 10, "HIGH",IF( 'Compound Alert'!AA51 >= 7, "MED","LOW")),IF( $B$8="Emerging Threat", IF( 'Compound Alert'!AH51 >= 10, "HIGH",IF( 'Compound Alert'!AH51 >= 7, "MED","LOW"))))) -> MED | M77: =IF( $B$8="Overall Alert",IF( 'Compound Alert'!U51 >= 7, "HIGH",IF( 'Compound Alert'!U51 >= 5, "MED","LOW")), IF( $B$8="Underlying Vulnerability", IF( 'Compound Alert'!AB51 >= 10, "HIGH",IF( 'Compound Alert'!AB51 >= 7, "MED","LOW")),IF( $B$8="Emerging Threat", IF( 'Compound Alert'!AI51 >= 10, "HIGH",IF( 'Compound Alert'!AI51 >= 7, "MED","LOW"))))) -> LOW | N77: =IF( $B$8="Overall Alert",IF( 'Compound Alert'!V51 >= 7, "HIGH",IF( 'Compound Alert'!V51 >= 5, "MED","LOW")), IF( $B$8="Underlying Vulnerability", IF( 'Compound Alert'!AC51 >= 10, "HIGH",IF( 'Compound Alert'!AC51 >= 7, "MED","LOW")),IF( $B$8="Emerging Threat", IF( 'Compound Alert'!AJ51 >= 10, "HIGH",IF( 'Compound Alert'!AJ51 >= 7, "MED","LOW"))))) -> HIGH | O77: =IF( $B$8="Overall Alert",IF( 'Compound Alert'!W51 >= 7, "HIGH",IF( 'Compound Alert'!W51 >= 5, "MED","LOW")), IF( $B$8="Underlying Vulnerability", IF( 'Compound Alert'!AD51 >= 10, "HIGH",IF( 'Compound Alert'!AD51 >= 7, "MED","LOW")),IF( $B$8="Emerging Threat", IF( 'Compound Alert'!AK51 >= 10, "HIGH",IF( 'Compound Alert'!AK51 >= 7, "MED","LOW"))))) -> LOW
A78: 37 | B78: ='Compound Alert'!B73 -> Gabon | C78: ='Compound Alert'!C73 -> GAB | D78: ='Compound Alert'!D73 -> SSF Sub-Saharan Africa | E78: ='Compound Alert'!E73 -> IBRD | F78: ='Compound Alert'!F73 -> 68 | G78: =IF($B$8="Overall Alert",'Compound Alert'!G73,IF($B$8="Underlying Vulnerability",'Compound Alert'!J73,IF($B$8="Emerging Threat",'Compound Alert'!M73))) -> 0 | H78: =IF($B$8="Overall Alert",'Compound Alert'!H73,IF($B$8="Underlying Vulnerability",'Compound Alert'!K73,IF($B$8="Emerging Threat",'Compound Alert'!N73))) -> 0 | I78: =ROUNDDOWN(G78,0) -> 0 | J78: =IF( $B$8="Overall Alert",IF( 'Compound Alert'!R73 >= 7, "HIGH",IF( 'Compound Alert'!R73 >= 5, "MED","LOW")), IF( $B$8="Underlying Vulnerability", IF( 'Compound Alert'!Y73 >= 10, "HIGH",IF( 'Compound Alert'!Y73 >= 7, "MED","LOW")),IF( $B$8="Emerging Threat", IF( 'Compound Alert'!AF73 >= 10, "HIGH",IF( 'Compound Alert'!AF73 >= 7, "MED","LOW"))))) -> LOW | K78: =IF( $B$8="Overall Alert",IF( 'Compound Alert'!S73 >= 7, "HIGH",IF( 'Compound Alert'!S73 >= 5, "MED","LOW")), IF( $B$8="Underlying Vulnerability", IF( 'Compound Alert'!Z73 >= 10, "HIGH",IF( 'Compound Alert'!Z73 >= 7, "MED","LOW")),IF( $B$8="Emerging Threat", IF( 'Compound Alert'!AG73 >= 10, "HIGH",IF( 'Compound Alert'!AG73 >= 7, "MED","LOW"))))) -> LOW | L78: =IF( $B$8="Overall Alert",IF( 'Compound Alert'!T73 >= 7, "HIGH",IF( 'Compound Alert'!T73 >= 5, "MED","LOW")), IF( $B$8="Underlying Vulnerability", IF( 'Compound Alert'!AA73 >= 10, "HIGH",IF( 'Compound Alert'!AA73 >= 7, "MED","LOW")),IF( $B$8="Emerging Threat", IF( 'Compound Alert'!AH73 >= 10, "HIGH",IF( 'Compound Alert'!AH73 >= 7, "MED","LOW"))))) -> LOW | M78: =IF( $B$8="Overall Alert",IF( 'Compound Alert'!U73 >= 7, "HIGH",IF( 'Compound Alert'!U73 >= 5, "MED","LOW")), IF( $B$8="Underlying Vulnerability", IF( 'Compound Alert'!AB73 >= 10, "HIGH",IF( 'Compound Alert'!AB73 >= 7, "MED","LOW")),IF( $B$8="Emerging Threat", IF( 'Compound Alert'!AI73 >= 10, "HIGH",IF( 'Compound Alert'!AI73 >= 7, "MED","LOW"))))) -> LOW | N78: =IF( $B$8="Overall Alert",IF( 'Compound Alert'!V73 >= 7, "HIGH",IF( 'Compound Alert'!V73 >= 5, "MED","LOW")), IF( $B$8="Underlying Vulnerability", IF( 'Compound Alert'!AC73 >= 10, "HIGH",IF( 'Compound Alert'!AC73 >= 7, "MED","LOW")),IF( $B$8="Emerging Threat", IF( 'Compound Alert'!AJ73 >= 10, "HIGH",IF( 'Compound Alert'!AJ73 >= 7, "MED","LOW"))))) -> LOW | O78: =IF( $B$8="Overall Alert",IF( 'Compound Alert'!W73 >= 7, "HIGH",IF( 'Compound Alert'!W73 >= 5, "MED","LOW")), IF( $B$8="Underlying Vulnerability", IF( 'Compound Alert'!AD73 >= 10, "HIGH",IF( 'Compound Alert'!AD73 >= 7, "MED","LOW")),IF( $B$8="Emerging Threat", IF( 'Compound Alert'!AK73 >= 10, "HIGH",IF( 'Compound Alert'!AK73 >= 7, "MED","LOW"))))) -> LOW
A79: 38 | B79: ='Compound Alert'!B216 -> Vietnam | C79: ='Compound Alert'!C216 -> VNM | D79: ='Compound Alert'!D216 -> EAS East Asia & Pacific | E79: ='Compound Alert'!E216 -> IBRD | F79: ='Compound Alert'!F216 -> 0 | G79: =IF($B$8="Overall Alert",'Compound Alert'!G216,IF($B$8="Underlying Vulnerability",'Compound Alert'!J216,IF($B$8="Emerging Threat",'Compound Alert'!M216))) -> 0 | H79: =IF($B$8="Overall Alert",'Compound Alert'!H216,IF($B$8="Underlying Vulnerability",'Compound Alert'!K216,IF($B$8="Emerging Threat",'Compound Alert'!N216))) -> 0 | I79: =ROUNDDOWN(G79,0) -> 0 | J79: =IF( $B$8="Overall Alert",IF( 'Compound Alert'!R216 >= 7, "HIGH",IF( 'Compound Alert'!R216 >= 5, "MED","LOW")), IF( $B$8="Underlying Vulnerability", IF( 'Compound Alert'!Y216 >= 10, "HIGH",IF( 'Compound Alert'!Y216 >= 7, "MED","LOW")),IF( $B$8="Emerging Threat", IF( 'Compound Alert'!AF216 >= 10, "HIGH",IF( 'Compound Alert'!AF216 >= 7, "MED","LOW"))))) -> LOW | K79: =IF( $B$8="Overall Alert",IF( 'Compound Alert'!S216 >= 7, "HIGH",IF( 'Compound Alert'!S216 >= 5, "MED","LOW")), IF( $B$8="Underlying Vulnerability", IF( 'Compound Alert'!Z216 >= 10, "HIGH",IF( 'Compound Alert'!Z216 >= 7, "MED","LOW")),IF( $B$8="Emerging Threat", IF( 'Compound Alert'!AG216 >= 10, "HIGH",IF( 'Compound Alert'!AG216 >= 7, "MED","LOW"))))) -> LOW | L79: =IF( $B$8="Overall Alert",IF( 'Compound Alert'!T216 >= 7, "HIGH",IF( 'Compound Alert'!T216 >= 5, "MED","LOW")), IF( $B$8="Underlying Vulnerability", IF( 'Compound Alert'!AA216 >= 10, "HIGH",IF( 'Compound Alert'!AA216 >= 7, "MED","LOW")),IF( $B$8="Emerging Threat", IF( 'Compound Alert'!AH216 >= 10, "HIGH",IF( 'Compound Alert'!AH216 >= 7, "MED","LOW"))))) -> LOW | M79: =IF( $B$8="Overall Alert",IF( 'Compound Alert'!U216 >= 7, "HIGH",IF( 'Compound Alert'!U216 >= 5, "MED","LOW")), IF( $B$8="Underlying Vulnerability", IF( 'Compound Alert'!AB216 >= 10, "HIGH",IF( 'Compound Alert'!AB216 >= 7, "MED","LOW")),IF( $B$8="Emerging Threat", IF( 'Compound Alert'!AI216 >= 10, "HIGH",IF( 'Compound Alert'!AI216 >= 7, "MED","LOW"))))) -> LOW | N79: =IF( $B$8="Overall Alert",IF( 'Compound Alert'!V216 >= 7, "HIGH",IF( 'Compound Alert'!V216 >= 5, "MED","LOW")), IF( $B$8="Underlying Vulnerability", IF( 'Compound Alert'!AC216 >= 10, "HIGH",IF( 'Compound Alert'!AC216 >= 7, "MED","LOW")),IF( $B$8="Emerging Threat", IF( 'Compound Alert'!AJ216 >= 10, "HIGH",IF( 'Compound Alert'!AJ216 >= 7, "MED","LOW"))))) -> LOW | O79: =IF( $B$8="Overall Alert",IF( 'Compound Alert'!W216 >= 7, "HIGH",IF( 'Compound Alert'!W216 >= 5, "MED","LOW")), IF( $B$8="Underlying Vulnerability", IF( 'Compound Alert'!AD216 >= 10, "HIGH",IF( 'Compound Alert'!AD216 >= 7, "MED","LOW")),IF( $B$8="Emerging Threat", IF( 'Compound Alert'!AK216 >= 10, "HIGH",IF( 'Compound Alert'!AK216 >= 7, "MED","LOW"))))) -> LOW
A80: 39 | B80: ='Compound Alert'!B78 -> Guinea | C80: ='Compound Alert'!C78 -> GIN | D80: ='Compound Alert'!D78 -> SSF Sub-Saharan Africa | E80: ='Compound Alert'!E78 -> IDA | F80: ='Compound Alert'!F78 -> 73 | G80: =IF($B$8="Overall Alert",'Compound Alert'!G78,IF($B$8="Underlying Vulnerability",'Compound Alert'!J78,IF($B$8="Emerging Threat",'Compound Alert'!M78))) -> 0.5 | H80: =IF($B$8="Overall Alert",'Compound Alert'!H78,IF($B$8="Underlying Vulnerability",'Compound Alert'!K78,IF($B$8="Emerging Threat",'Compound Alert'!N78))) -> 0.5 | I80: =ROUNDDOWN(G80,0) -> 0 | J80: =IF( $B$8="Overall Alert",IF( 'Compound Alert'!R78 >= 7, "HIGH",IF( 'Compound Alert'!R78 >= 5, "MED","LOW")), IF( $B$8="Underlying Vulnerability", IF( 'Compound Alert'!Y78 >= 10, "HIGH",IF( 'Compound Alert'!Y78 >= 7, "MED","LOW")),IF( $B$8="Emerging Threat", IF( 'Compound Alert'!AF78 >= 10, "HIGH",IF( 'Compound Alert'!AF78 >= 7, "MED","LOW"))))) -> LOW | K80: =IF( $B$8="Overall Alert",IF( 'Compound Alert'!S78 >= 7, "HIGH",IF( 'Compound Alert'!S78 >= 5, "MED","LOW")), IF( $B$8="Underlying Vulnerability", IF( 'Compound Alert'!Z78 >= 10, "HIGH",IF( 'Compound Alert'!Z78 >= 7, "MED","LOW")),IF( $B$8="Emerging Threat", IF( 'Compound Alert'!AG78 >= 10, "HIGH",IF( 'Compound Alert'!AG78 >= 7, "MED","LOW"))))) -> MED | L80: =IF( $B$8="Overall Alert",IF( 'Compound Alert'!T78 >= 7, "HIGH",IF( 'Compound Alert'!T78 >= 5, "MED","LOW")), IF( $B$8="Underlying Vulnerability", IF( 'Compound Alert'!AA78 >= 10, "HIGH",IF( 'Compound Alert'!AA78 >= 7, "MED","LOW")),IF( $B$8="Emerging Threat", IF( 'Compound Alert'!AH78 >= 10, "HIGH",IF( 'Compound Alert'!AH78 >= 7, "MED","LOW"))))) -> LOW | M80: =IF( $B$8="Overall Alert",IF( 'Compound Alert'!U78 >= 7, "HIGH",IF( 'Compound Alert'!U78 >= 5, "MED","LOW")), IF( $B$8="Underlying Vulnerability", IF( 'Compound Alert'!AB78 >= 10, "HIGH",IF( 'Compound Alert'!AB78 >= 7, "MED","LOW")),IF( $B$8="Emerging Threat", IF( 'Compound Alert'!AI78 >= 10, "HIGH",IF( 'Compound Alert'!AI78 >= 7, "MED","LOW"))))) -> LOW | N80: =IF( $B$8="Overall Alert",IF( 'Compound Alert'!V78 >= 7, "HIGH",IF( 'Compound Alert'!V78 >= 5, "MED","LOW")), IF( $B$8="Underlying Vulnerability", IF( 'Compound Alert'!AC78 >= 10, "HIGH",IF( 'Compound Alert'!AC78 >= 7, "MED","LOW")),IF( $B$8="Emerging Threat", IF( 'Compound Alert'!AJ78 >= 10, "HIGH",IF( 'Compound Alert'!AJ78 >= 7, "MED","LOW"))))) -> LOW | O80: =IF( $B$8="Overall Alert",IF( 'Compound Alert'!W78 >= 7, "HIGH",IF( 'Compound Alert'!W78 >= 5, "MED","LOW")), IF( $B$8="Underlying Vulnerability", IF( 'Compound Alert'!AD78 >= 10, "HIGH",IF( 'Compound Alert'!AD78 >= 7, "MED","LOW")),IF( $B$8="Emerging Threat", IF( 'Compound Alert'!AK78 >= 10, "HIGH",IF( 'Compound Alert'!AK78 >= 7, "MED","LOW"))))) -> LOW
A81: 40 | B81: ='Compound Alert'!B37 -> Central African Republic | C81: ='Compound Alert'!C37 -> CAF | D81: ='Compound Alert'!D37 -> SSF Sub-Saharan Africa | E81: ='Compound Alert'!E37 -> IDA | F81: ='Compound Alert'!F37 -> 32 | G81: =IF($B$8="Overall Alert",'Compound Alert'!G37,IF($B$8="Underlying Vulnerability",'Compound Alert'!J37,IF($B$8="Emerging Threat",'Compound Alert'!M37))) -> 2 | H81: =IF($B$8="Overall Alert",'Compound Alert'!H37,IF($B$8="Underlying Vulnerability",'Compound Alert'!K37,IF($B$8="Emerging Threat",'Compound Alert'!N37))) -> 2 | I81: =ROUNDDOWN(G81,0) -> 2 | J81: =IF( $B$8="Overall Alert",IF( 'Compound Alert'!R37 >= 7, "HIGH",IF( 'Compound Alert'!R37 >= 5, "MED","LOW")), IF( $B$8="Underlying Vulnerability", IF( 'Compound Alert'!Y37 >= 10, "HIGH",IF( 'Compound Alert'!Y37 >= 7, "MED","LOW")),IF( $B$8="Emerging Threat", IF( 'Compound Alert'!AF37 >= 10, "HIGH",IF( 'Compound Alert'!AF37 >= 7, "MED","LOW"))))) -> LOW | K81: =IF( $B$8="Overall Alert",IF( 'Compound Alert'!S37 >= 7, "HIGH",IF( 'Compound Alert'!S37 >= 5, "MED","LOW")), IF( $B$8="Underlying Vulnerability", IF( 'Compound Alert'!Z37 >= 10, "HIGH",IF( 'Compound Alert'!Z37 >= 7, "MED","LOW")),IF( $B$8="Emerging Threat", IF( 'Compound Alert'!AG37 >= 10, "HIGH",IF( 'Compound Alert'!AG37 >= 7, "MED","LOW"))))) -> HIGH | L81: =IF( $B$8="Overall Alert",IF( 'Compound Alert'!T37 >= 7, "HIGH",IF( 'Compound Alert'!T37 >= 5, "MED","LOW")), IF( $B$8="Underlying Vulnerability", IF( 'Compound Alert'!AA37 >= 10, "HIGH",IF( 'Compound Alert'!AA37 >= 7, "MED","LOW")),IF( $B$8="Emerging Threat", IF( 'Compound Alert'!AH37 >= 10, "HIGH",IF( 'Compound Alert'!AH37 >= 7, "MED","LOW"))))) -> LOW | M81: =IF( $B$8="Overall Alert",IF( 'Compound Alert'!U37 >= 7, "HIGH",IF( 'Compound Alert'!U37 >= 5, "MED","LOW")), IF( $B$8="Underlying Vulnerability", IF( 'Compound Alert'!AB37 >= 10, "HIGH",IF( 'Compound Alert'!AB37 >= 7, "MED","LOW")),IF( $B$8="Emerging Threat", IF( 'Compound Alert'!AI37 >= 10, "HIGH",IF( 'Compound Alert'!AI37 >= 7, "MED","LOW"))))) -> MED | N81: =IF( $B$8="Overall Alert",IF( 'Compound Alert'!V37 >= 7, "HIGH",IF( 'Compound Alert'!V37 >= 5, "MED","LOW")), IF( $B$8="Underlying Vulnerability", IF( 'Compound Alert'!AC37 >= 10, "HIGH",IF( 'Compound Alert'!AC37 >= 7, "MED","LOW")),IF( $B$8="Emerging Threat", IF( 'Compound Alert'!AJ37 >= 10, "HIGH",IF( 'Compound Alert'!AJ37 >= 7, "MED","LOW"))))) -> MED | O81: =IF( $B$8="Overall Alert",IF( 'Compound Alert'!W37 >= 7, "HIGH",IF( 'Compound Alert'!W37 >= 5, "MED","LOW")), IF( $B$8="Underlying Vulnerability", IF( 'Compound Alert'!AD37 >= 10, "HIGH",IF( 'Compound Alert'!AD37 >= 7, "MED","LOW")),IF( $B$8="Emerging Threat", IF( 'Compound Alert'!AK37 >= 10, "HIGH",IF( 'Compound Alert'!AK37 >= 7, "MED","LOW"))))) -> LOW
A82: 41 | B82: ='Compound Alert'!B79 -> Gambia, The | C82: ='Compound Alert'!C79 -> GMB | D82: ='Compound Alert'!D79 -> SSF Sub-Saharan Africa | E82: ='Compound Alert'!E79 -> IDA | F82: ='Compound Alert'!F79 -> 74 | G82: =IF($B$8="Overall Alert",'Compound Alert'!G79,IF($B$8="Underlying Vulnerability",'Compound Alert'!J79,IF($B$8="Emerging Threat",'Compound Alert'!M79))) -> 1 | H82: =IF($B$8="Overall Alert",'Compound Alert'!H79,IF($B$8="Underlying Vulnerability",'Compound Alert'!K79,IF($B$8="Emerging Threat",'Compound Alert'!N79))) -> 1 | I82: =ROUNDDOWN(G82,0) -> 1 | J82: =IF( $B$8="Overall Alert",IF( 'Compound Alert'!R79 >= 7, "HIGH",IF( 'Compound Alert'!R79 >= 5, "MED","LOW")), IF( $B$8="Underlying Vulnerability", IF( 'Compound Alert'!Y79 >= 10, "HIGH",IF( 'Compound Alert'!Y79 >= 7, "MED","LOW")),IF( $B$8="Emerging Threat", IF( 'Compound Alert'!AF79 >= 10, "HIGH",IF( 'Compound Alert'!AF79 >= 7, "MED","LOW"))))) -> LOW | K82: =IF( $B$8="Overall Alert",IF( 'Compound Alert'!S79 >= 7, "HIGH",IF( 'Compound Alert'!S79 >= 5, "MED","LOW")), IF( $B$8="Underlying Vulnerability", IF( 'Compound Alert'!Z79 >= 10, "HIGH",IF( 'Compound Alert'!Z79 >= 7, "MED","LOW")),IF( $B$8="Emerging Threat", IF( 'Compound Alert'!AG79 >= 10, "HIGH",IF( 'Compound Alert'!AG79 >= 7, "MED","LOW"))))) -> MED | L82: =IF( $B$8="Overall Alert",IF( 'Compound Alert'!T79 >= 7, "HIGH",IF( 'Compound Alert'!T79 >= 5, "MED","LOW")), IF( $B$8="Underlying Vulnerability", IF( 'Compound Alert'!AA79 >= 10, "HIGH",IF( 'Compound Alert'!AA79 >= 7, "MED","LOW")),IF( $B$8="Emerging Threat", IF( 'Compound Alert'!AH79 >= 10, "HIGH",IF( 'Compound Alert'!AH79 >= 7, "MED","LOW"))))) -> MED | M82: =IF( $B$8="Overall Alert",IF( 'Compound Alert'!U79 >= 7, "HIGH",IF( 'Compound Alert'!U79 >= 5, "MED","LOW")), IF( $B$8="Underlying Vulnerability", IF( 'Compound Alert'!AB79 >= 10, "HIGH",IF( 'Compound Alert'!AB79 >= 7, "MED","LOW")),IF( $B$8="Emerging Threat", IF( 'Compound Alert'!AI79 >= 10, "HIGH",IF( 'Compound Alert'!AI79 >= 7, "MED","LOW"))))) -> LOW | N82: =IF( $B$8="Overall Alert",IF( 'Compound Alert'!V79 >= 7, "HIGH",IF( 'Compound Alert'!V79 >= 5, "MED","LOW")), IF( $B$8="Underlying Vulnerability", IF( 'Compound Alert'!AC79 >= 10, "HIGH",IF( 'Compound Alert'!AC79 >= 7, "MED","LOW")),IF( $B$8="Emerging Threat", IF( 'Compound Alert'!AJ79 >= 10, "HIGH",IF( 'Compound Alert'!AJ79 >= 7, "MED","LOW"))))) -> LOW | O82: =IF( $B$8="Overall Alert",IF( 'Compound Alert'!W79 >= 7, "HIGH",IF( 'Compound Alert'!W79 >= 5, "MED","LOW")), IF( $B$8="Underlying Vulnerability", IF( 'Compound Alert'!AD79 >= 10, "HIGH",IF( 'Compound Alert'!AD79 >= 7, "MED","LOW")),IF( $B$8="Emerging Threat", IF( 'Compound Alert'!AK79 >= 10, "HIGH",IF( 'Compound Alert'!AK79 >= 7, "MED","LOW"))))) -> LOW
A83: 42 | B83: ='Compound Alert'!B76 -> Ghana | C83: ='Compound Alert'!C76 -> GHA | D83: ='Compound Alert'!D76 -> SSF Sub-Saharan Africa | E83: ='Compound Alert'!E76 -> IDA | F83: ='Compound Alert'!F76 -> 71 | G83: =IF($B$8="Overall Alert",'Compound Alert'!G76,IF($B$8="Underlying Vulnerability",'Compound Alert'!J76,IF($B$8="Emerging Threat",'Compound Alert'!M76))) -> 0 | H83: =IF($B$8="Overall Alert",'Compound Alert'!H76,IF($B$8="Underlying Vulnerability",'Compound Alert'!K76,IF($B$8="Emerging Threat",'Compound Alert'!N76))) -> 0 | I83: =ROUNDDOWN(G83,0) -> 0 | J83: =IF( $B$8="Overall Alert",IF( 'Compound Alert'!R76 >= 7, "HIGH",IF( 'Compound Alert'!R76 >= 5, "MED","LOW")), IF( $B$8="Underlying Vulnerability", IF( 'Compound Alert'!Y76 >= 10, "HIGH",IF( 'Compound Alert'!Y76 >= 7, "MED","LOW")),IF( $B$8="Emerging Threat", IF( 'Compound Alert'!AF76 >= 10, "HIGH",IF( 'Compound Alert'!AF76 >= 7, "MED","LOW"))))) -> LOW | K83: =IF( $B$8="Overall Alert",IF( 'Compound Alert'!S76 >= 7, "HIGH",IF( 'Compound Alert'!S76 >= 5, "MED","LOW")), IF( $B$8="Underlying Vulnerability", IF( 'Compound Alert'!Z76 >= 10, "HIGH",IF( 'Compound Alert'!Z76 >= 7, "MED","LOW")),IF( $B$8="Emerging Threat", IF( 'Compound Alert'!AG76 >= 10, "HIGH",IF( 'Compound Alert'!AG76 >= 7, "MED","LOW"))))) -> LOW | L83: =IF( $B$8="Overall Alert",IF( 'Compound Alert'!T76 >= 7, "HIGH",IF( 'Compound Alert'!T76 >= 5, "MED","LOW")), IF( $B$8="Underlying Vulnerability", IF( 'Compound Alert'!AA76 >= 10, "HIGH",IF( 'Compound Alert'!AA76 >= 7, "MED","LOW")),IF( $B$8="Emerging Threat", IF( 'Compound Alert'!AH76 >= 10, "HIGH",IF( 'Compound Alert'!AH76 >= 7, "MED","LOW"))))) -> LOW | M83: =IF( $B$8="Overall Alert",IF( 'Compound Alert'!U76 >= 7, "HIGH",IF( 'Compound Alert'!U76 >= 5, "MED","LOW")), IF( $B$8="Underlying Vulnerability", IF( 'Compound Alert'!AB76 >= 10, "HIGH",IF( 'Compound Alert'!AB76 >= 7, "MED","LOW")),IF( $B$8="Emerging Threat", IF( 'Compound Alert'!AI76 >= 10, "HIGH",IF( 'Compound Alert'!AI76 >= 7, "MED","LOW"))))) -> LOW | N83: =IF( $B$8="Overall Alert",IF( 'Compound Alert'!V76 >= 7, "HIGH",IF( 'Compound Alert'!V76 >= 5, "MED","LOW")), IF( $B$8="Underlying Vulnerability", IF( 'Compound Alert'!AC76 >= 10, "HIGH",IF( 'Compound Alert'!AC76 >= 7, "MED","LOW")),IF( $B$8="Emerging Threat", IF( 'Compound Alert'!AJ76 >= 10, "HIGH",IF( 'Compound Alert'!AJ76 >= 7, "MED","LOW"))))) -> LOW | O83: =IF( $B$8="Overall Alert",IF( 'Compound Alert'!W76 >= 7, "HIGH",IF( 'Compound Alert'!W76 >= 5, "MED","LOW")), IF( $B$8="Underlying Vulnerability", IF( 'Compound Alert'!AD76 >= 10, "HIGH",IF( 'Compound Alert'!AD76 >= 7, "MED","LOW")),IF( $B$8="Emerging Threat", IF( 'Compound Alert'!AK76 >= 10, "HIGH",IF( 'Compound Alert'!AK76 >= 7, "MED","LOW"))))) -> LOW
A84: 43 | B84: ='Compound Alert'!B126 -> Morocco | C84: ='Compound Alert'!C126 -> MAR | D84: ='Compound Alert'!D126 -> MEA Middle East & North Africa | E84: ='Compound Alert'!E126 -> IBRD | F84: ='Compound Alert'!F126 -> 121 | G84: =IF($B$8="Overall Alert",'Compound Alert'!G126,IF($B$8="Underlying Vulnerability",'Compound Alert'!J126,IF($B$8="Emerging Threat",'Compound Alert'!M126))) -> 1 | H84: =IF($B$8="Overall Alert",'Compound Alert'!H126,IF($B$8="Underlying Vulnerability",'Compound Alert'!K126,IF($B$8="Emerging Threat",'Compound Alert'!N126))) -> 1 | I84: =ROUNDDOWN(G84,0) -> 1 | J84: =IF( $B$8="Overall Alert",IF( 'Compound Alert'!R126 >= 7, "HIGH",IF( 'Compound Alert'!R126 >= 5, "MED","LOW")), IF( $B$8="Underlying Vulnerability", IF( 'Compound Alert'!Y126 >= 10, "HIGH",IF( 'Compound Alert'!Y126 >= 7, "MED","LOW")),IF( $B$8="Emerging Threat", IF( 'Compound Alert'!AF126 >= 10, "HIGH",IF( 'Compound Alert'!AF126 >= 7, "MED","LOW"))))) -> LOW | K84: =IF( $B$8="Overall Alert",IF( 'Compound Alert'!S126 >= 7, "HIGH",IF( 'Compound Alert'!S126 >= 5, "MED","LOW")), IF( $B$8="Underlying Vulnerability", IF( 'Compound Alert'!Z126 >= 10, "HIGH",IF( 'Compound Alert'!Z126 >= 7, "MED","LOW")),IF( $B$8="Emerging Threat", IF( 'Compound Alert'!AG126 >= 10, "HIGH",IF( 'Compound Alert'!AG126 >= 7, "MED","LOW"))))) -> LOW | L84: =IF( $B$8="Overall Alert",IF( 'Compound Alert'!T126 >= 7, "HIGH",IF( 'Compound Alert'!T126 >= 5, "MED","LOW")), IF( $B$8="Underlying Vulnerability", IF( 'Compound Alert'!AA126 >= 10, "HIGH",IF( 'Compound Alert'!AA126 >= 7, "MED","LOW")),IF( $B$8="Emerging Threat", IF( 'Compound Alert'!AH126 >= 10, "HIGH",IF( 'Compound Alert'!AH126 >= 7, "MED","LOW"))))) -> LOW | M84: =IF( $B$8="Overall Alert",IF( 'Compound Alert'!U126 >= 7, "HIGH",IF( 'Compound Alert'!U126 >= 5, "MED","LOW")), IF( $B$8="Underlying Vulnerability", IF( 'Compound Alert'!AB126 >= 10, "HIGH",IF( 'Compound Alert'!AB126 >= 7, "MED","LOW")),IF( $B$8="Emerging Threat", IF( 'Compound Alert'!AI126 >= 10, "HIGH",IF( 'Compound Alert'!AI126 >= 7, "MED","LOW"))))) -> LOW | N84: =IF( $B$8="Overall Alert",IF( 'Compound Alert'!V126 >= 7, "HIGH",IF( 'Compound Alert'!V126 >= 5, "MED","LOW")), IF( $B$8="Underlying Vulnerability", IF( 'Compound Alert'!AC126 >= 10, "HIGH",IF( 'Compound Alert'!AC126 >= 7, "MED","LOW")),IF( $B$8="Emerging Threat", IF( 'Compound Alert'!AJ126 >= 10, "HIGH",IF( 'Compound Alert'!AJ126 >= 7, "MED","LOW"))))) -> HIGH | O84: =IF( $B$8="Overall Alert",IF( 'Compound Alert'!W126 >= 7, "HIGH",IF( 'Compound Alert'!W126 >= 5, "MED","LOW")), IF( $B$8="Underlying Vulnerability", IF( 'Compound Alert'!AD126 >= 10, "HIGH",IF( 'Compound Alert'!AD126 >= 7, "MED","LOW")),IF( $B$8="Emerging Threat", IF( 'Compound Alert'!AK126 >= 10, "HIGH",IF( 'Compound Alert'!AK126 >= 7, "MED","LOW"))))) -> LOW
A85: 44 | B85: ='Compound Alert'!B166 -> Paraguay | C85: ='Compound Alert'!C166 -> PRY | D85: ='Compound Alert'!D166 -> LCN Latin America & Caribbean | E85: ='Compound Alert'!E166 -> IBRD | F85: ='Compound Alert'!F166 -> 161 | G85: =IF($B$8="Overall Alert",'Compound Alert'!G166,IF($B$8="Underlying Vulnerability",'Compound Alert'!J166,IF($B$8="Emerging Threat",'Compound Alert'!M166))) -> 0 | H85: =IF($B$8="Overall Alert",'Compound Alert'!H166,IF($B$8="Underlying Vulnerability",'Compound Alert'!K166,IF($B$8="Emerging Threat",'Compound Alert'!N166))) -> 0 | I85: =ROUNDDOWN(G85,0) -> 0 | J85: =IF( $B$8="Overall Alert",IF( 'Compound Alert'!R166 >= 7, "HIGH",IF( 'Compound Alert'!R166 >= 5, "MED","LOW")), IF( $B$8="Underlying Vulnerability", IF( 'Compound Alert'!Y166 >= 10, "HIGH",IF( 'Compound Alert'!Y166 >= 7, "MED","LOW")),IF( $B$8="Emerging Threat", IF( 'Compound Alert'!AF166 >= 10, "HIGH",IF( 'Compound Alert'!AF166 >= 7, "MED","LOW"))))) -> LOW | K85: =IF( $B$8="Overall Alert",IF( 'Compound Alert'!S166 >= 7, "HIGH",IF( 'Compound Alert'!S166 >= 5, "MED","LOW")), IF( $B$8="Underlying Vulnerability", IF( 'Compound Alert'!Z166 >= 10, "HIGH",IF( 'Compound Alert'!Z166 >= 7, "MED","LOW")),IF( $B$8="Emerging Threat", IF( 'Compound Alert'!AG166 >= 10, "HIGH",IF( 'Compound Alert'!AG166 >= 7, "MED","LOW"))))) -> LOW | L85: =IF( $B$8="Overall Alert",IF( 'Compound Alert'!T166 >= 7, "HIGH",IF( 'Compound Alert'!T166 >= 5, "MED","LOW")), IF( $B$8="Underlying Vulnerability", IF( 'Compound Alert'!AA166 >= 10, "HIGH",IF( 'Compound Alert'!AA166 >= 7, "MED","LOW")),IF( $B$8="Emerging Threat", IF( 'Compound Alert'!AH166 >= 10, "HIGH",IF( 'Compound Alert'!AH166 >= 7, "MED","LOW"))))) -> LOW | M85: =IF( $B$8="Overall Alert",IF( 'Compound Alert'!U166 >= 7, "HIGH",IF( 'Compound Alert'!U166 >= 5, "MED","LOW")), IF( $B$8="Underlying Vulnerability", IF( 'Compound Alert'!AB166 >= 10, "HIGH",IF( 'Compound Alert'!AB166 >= 7, "MED","LOW")),IF( $B$8="Emerging Threat", IF( 'Compound Alert'!AI166 >= 10, "HIGH",IF( 'Compound Alert'!AI166 >= 7, "MED","LOW"))))) -> LOW | N85: =IF( $B$8="Overall Alert",IF( 'Compound Alert'!V166 >= 7, "HIGH",IF( 'Compound Alert'!V166 >= 5, "MED","LOW")), IF( $B$8="Underlying Vulnerability", IF( 'Compound Alert'!AC166 >= 10, "HIGH",IF( 'Compound Alert'!AC166 >= 7, "MED","LOW")),IF( $B$8="Emerging Threat", IF( 'Compound Alert'!AJ166 >= 10, "HIGH",IF( 'Compound Alert'!AJ166 >= 7, "MED","LOW"))))) -> LOW | O85: =IF( $B$8="Overall Alert",IF( 'Compound Alert'!W166 >= 7, "HIGH",IF( 'Compound Alert'!W166 >= 5, "MED","LOW")), IF( $B$8="Underlying Vulnerability", IF( 'Compound Alert'!AD166 >= 10, "HIGH",IF( 'Compound Alert'!AD166 >= 7, "MED","LOW")),IF( $B$8="Emerging Threat", IF( 'Compound Alert'!AK166 >= 10, "HIGH",IF( 'Compound Alert'!AK166 >= 7, "MED","LOW"))))) -> LOW
A86: 45 | B86: ='Compound Alert'!B203 -> Türkiye | C86: ='Compound Alert'!C203 -> TUR | D86: ='Compound Alert'!D203 -> ECS Europe & Central Asia | E86: ='Compound Alert'!E203 -> IBRD | F86: ='Compound Alert'!F203 -> 0 | G86: =IF($B$8="Overall Alert",'Compound Alert'!G203,IF($B$8="Underlying Vulnerability",'Compound Alert'!J203,IF($B$8="Emerging Threat",'Compound Alert'!M203))) -> 0.5 | H86: =IF($B$8="Overall Alert",'Compound Alert'!H203,IF($B$8="Underlying Vulnerability",'Compound Alert'!K203,IF($B$8="Emerging Threat",'Compound Alert'!N203))) -> 0.5 | I86: =ROUNDDOWN(G86,0) -> 0 | J86: =IF( $B$8="Overall Alert",IF( 'Compound Alert'!R203 >= 7, "HIGH",IF( 'Compound Alert'!R203 >= 5, "MED","LOW")), IF( $B$8="Underlying Vulnerability", IF( 'Compound Alert'!Y203 >= 10, "HIGH",IF( 'Compound Alert'!Y203 >= 7, "MED","LOW")),IF( $B$8="Emerging Threat", IF( 'Compound Alert'!AF203 >= 10, "HIGH",IF( 'Compound Alert'!AF203 >= 7, "MED","LOW"))))) -> LOW | K86: =IF( $B$8="Overall Alert",IF( 'Compound Alert'!S203 >= 7, "HIGH",IF( 'Compound Alert'!S203 >= 5, "MED","LOW")), IF( $B$8="Underlying Vulnerability", IF( 'Compound Alert'!Z203 >= 10, "HIGH",IF( 'Compound Alert'!Z203 >= 7, "MED","LOW")),IF( $B$8="Emerging Threat", IF( 'Compound Alert'!AG203 >= 10, "HIGH",IF( 'Compound Alert'!AG203 >= 7, "MED","LOW"))))) -> LOW | L86: =IF( $B$8="Overall Alert",IF( 'Compound Alert'!T203 >= 7, "HIGH",IF( 'Compound Alert'!T203 >= 5, "MED","LOW")), IF( $B$8="Underlying Vulnerability", IF( 'Compound Alert'!AA203 >= 10, "HIGH",IF( 'Compound Alert'!AA203 >= 7, "MED","LOW")),IF( $B$8="Emerging Threat", IF( 'Compound Alert'!AH203 >= 10, "HIGH",IF( 'Compound Alert'!AH203 >= 7, "MED","LOW"))))) -> LOW | M86: =IF( $B$8="Overall Alert",IF( 'Compound Alert'!U203 >= 7, "HIGH",IF( 'Compound Alert'!U203 >= 5, "MED","LOW")), IF( $B$8="Underlying Vulnerability", IF( 'Compound Alert'!AB203 >= 10, "HIGH",IF( 'Compound Alert'!AB203 >= 7, "MED","LOW")),IF( $B$8="Emerging Threat", IF( 'Compound Alert'!AI203 >= 10, "HIGH",IF( 'Compound Alert'!AI203 >= 7, "MED","LOW"))))) -> LOW | N86: =IF( $B$8="Overall Alert",IF( 'Compound Alert'!V203 >= 7, "HIGH",IF( 'Compound Alert'!V203 >= 5, "MED","LOW")), IF( $B$8="Underlying Vulnerability", IF( 'Compound Alert'!AC203 >= 10, "HIGH",IF( 'Compound Alert'!AC203 >= 7, "MED","LOW")),IF( $B$8="Emerging Threat", IF( 'Compound Alert'!AJ203 >= 10, "HIGH",IF( 'Compound Alert'!AJ203 >= 7, "MED","LOW"))))) -> LOW | O86: =IF( $B$8="Overall Alert",IF( 'Compound Alert'!W203 >= 7, "HIGH",IF( 'Compound Alert'!W203 >= 5, "MED","LOW")), IF( $B$8="Underlying Vulnerability", IF( 'Compound Alert'!AD203 >= 10, "HIGH",IF( 'Compound Alert'!AD203 >= 7, "MED","LOW")),IF( $B$8="Emerging Threat", IF( 'Compound Alert'!AK203 >= 10, "HIGH",IF( 'Compound Alert'!AK203 >= 7, "MED","LOW"))))) -> MED
A87: 46 | B87: ='Compound Alert'!B202 -> Tunisia | C87: ='Compound Alert'!C202 -> TUN | D87: ='Compound Alert'!D202 -> MEA Middle East & North Africa | E87: ='Compound Alert'!E202 -> IBRD | F87: ='Compound Alert'!F202 -> 0 | G87: =IF($B$8="Overall Alert",'Compound Alert'!G202,IF($B$8="Underlying Vulnerability",'Compound Alert'!J202,IF($B$8="Emerging Threat",'Compound Alert'!M202))) -> 0.5 | H87: =IF($B$8="Overall Alert",'Compound Alert'!H202,IF($B$8="Underlying Vulnerability",'Compound Alert'!K202,IF($B$8="Emerging Threat",'Compound Alert'!N202))) -> 0.5 | I87: =ROUNDDOWN(G87,0) -> 0 | J87: =IF( $B$8="Overall Alert",IF( 'Compound Alert'!R202 >= 7, "HIGH",IF( 'Compound Alert'!R202 >= 5, "MED","LOW")), IF( $B$8="Underlying Vulnerability", IF( 'Compound Alert'!Y202 >= 10, "HIGH",IF( 'Compound Alert'!Y202 >= 7, "MED","LOW")),IF( $B$8="Emerging Threat", IF( 'Compound Alert'!AF202 >= 10, "HIGH",IF( 'Compound Alert'!AF202 >= 7, "MED","LOW"))))) -> LOW | K87: =IF( $B$8="Overall Alert",IF( 'Compound Alert'!S202 >= 7, "HIGH",IF( 'Compound Alert'!S202 >= 5, "MED","LOW")), IF( $B$8="Underlying Vulnerability", IF( 'Compound Alert'!Z202 >= 10, "HIGH",IF( 'Compound Alert'!Z202 >= 7, "MED","LOW")),IF( $B$8="Emerging Threat", IF( 'Compound Alert'!AG202 >= 10, "HIGH",IF( 'Compound Alert'!AG202 >= 7, "MED","LOW"))))) -> LOW | L87: =IF( $B$8="Overall Alert",IF( 'Compound Alert'!T202 >= 7, "HIGH",IF( 'Compound Alert'!T202 >= 5, "MED","LOW")), IF( $B$8="Underlying Vulnerability", IF( 'Compound Alert'!AA202 >= 10, "HIGH",IF( 'Compound Alert'!AA202 >= 7, "MED","LOW")),IF( $B$8="Emerging Threat", IF( 'Compound Alert'!AH202 >= 10, "HIGH",IF( 'Compound Alert'!AH202 >= 7, "MED","LOW"))))) -> MED | M87: =IF( $B$8="Overall Alert",IF( 'Compound Alert'!U202 >= 7, "HIGH",IF( 'Compound Alert'!U202 >= 5, "MED","LOW")), IF( $B$8="Underlying Vulnerability", IF( 'Compound Alert'!AB202 >= 10, "HIGH",IF( 'Compound Alert'!AB202 >= 7, "MED","LOW")),IF( $B$8="Emerging Threat", IF( 'Compound Alert'!AI202 >= 10, "HIGH",IF( 'Compound Alert'!AI202 >= 7, "MED","LOW"))))) -> LOW | N87: =IF( $B$8="Overall Alert",IF( 'Compound Alert'!V202 >= 7, "HIGH",IF( 'Compound Alert'!V202 >= 5, "MED","LOW")), IF( $B$8="Underlying Vulnerability", IF( 'Compound Alert'!AC202 >= 10, "HIGH",IF( 'Compound Alert'!AC202 >= 7, "MED","LOW")),IF( $B$8="Emerging Threat", IF( 'Compound Alert'!AJ202 >= 10, "HIGH",IF( 'Compound Alert'!AJ202 >= 7, "MED","LOW"))))) -> LOW | O87: =IF( $B$8="Overall Alert",IF( 'Compound Alert'!W202 >= 7, "HIGH",IF( 'Compound Alert'!W202 >= 5, "MED","LOW")), IF( $B$8="Underlying Vulnerability", IF( 'Compound Alert'!AD202 >= 10, "HIGH",IF( 'Compound Alert'!AD202 >= 7, "MED","LOW")),IF( $B$8="Emerging Threat", IF( 'Compound Alert'!AK202 >= 10, "HIGH",IF( 'Compound Alert'!AK202 >= 7, "MED","LOW"))))) -> LOW
A88: 47 | B88: ='Compound Alert'!B119 -> Sri Lanka | C88: ='Compound Alert'!C119 -> LKA | D88: ='Compound Alert'!D119 -> SAS South Asia | E88: ='Compound Alert'!E119 -> IBRD | F88: ='Compound Alert'!F119 -> 114 | G88: =IF($B$8="Overall Alert",'Compound Alert'!G119,IF($B$8="Underlying Vulnerability",'Compound Alert'!J119,IF($B$8="Emerging Threat",'Compound Alert'!M119))) -> 2 | H88: =IF($B$8="Overall Alert",'Compound Alert'!H119,IF($B$8="Underlying Vulnerability",'Compound Alert'!K119,IF($B$8="Emerging Threat",'Compound Alert'!N119))) -> 2 | I88: =ROUNDDOWN(G88,0) -> 2 | J88: =IF( $B$8="Overall Alert",IF( 'Compound Alert'!R119 >= 7, "HIGH",IF( 'Compound Alert'!R119 >= 5, "MED","LOW")), IF( $B$8="Underlying Vulnerability", IF( 'Compound Alert'!Y119 >= 10, "HIGH",IF( 'Compound Alert'!Y119 >= 7, "MED","LOW")),IF( $B$8="Emerging Threat", IF( 'Compound Alert'!AF119 >= 10, "HIGH",IF( 'Compound Alert'!AF119 >= 7, "MED","LOW"))))) -> LOW | K88: =IF( $B$8="Overall Alert",IF( 'Compound Alert'!S119 >= 7, "HIGH",IF( 'Compound Alert'!S119 >= 5, "MED","LOW")), IF( $B$8="Underlying Vulnerability", IF( 'Compound Alert'!Z119 >= 10, "HIGH",IF( 'Compound Alert'!Z119 >= 7, "MED","LOW")),IF( $B$8="Emerging Threat", IF( 'Compound Alert'!AG119 >= 10, "HIGH",IF( 'Compound Alert'!AG119 >= 7, "MED","LOW"))))) -> LOW | L88: =IF( $B$8="Overall Alert",IF( 'Compound Alert'!T119 >= 7, "HIGH",IF( 'Compound Alert'!T119 >= 5, "MED","LOW")), IF( $B$8="Underlying Vulnerability", IF( 'Compound Alert'!AA119 >= 10, "HIGH",IF( 'Compound Alert'!AA119 >= 7, "MED","LOW")),IF( $B$8="Emerging Threat", IF( 'Compound Alert'!AH119 >= 10, "HIGH",IF( 'Compound Alert'!AH119 >= 7, "MED","LOW"))))) -> MED | M88: =IF( $B$8="Overall Alert",IF( 'Compound Alert'!U119 >= 7, "HIGH",IF( 'Compound Alert'!U119 >= 5, "MED","LOW")), IF( $B$8="Underlying Vulnerability", IF( 'Compound Alert'!AB119 >= 10, "HIGH",IF( 'Compound Alert'!AB119 >= 7, "MED","LOW")),IF( $B$8="Emerging Threat", IF( 'Compound Alert'!AI119 >= 10, "HIGH",IF( 'Compound Alert'!AI119 >= 7, "MED","LOW"))))) -> LOW | N88: =IF( $B$8="Overall Alert",IF( 'Compound Alert'!V119 >= 7, "HIGH",IF( 'Compound Alert'!V119 >= 5, "MED","LOW")), IF( $B$8="Underlying Vulnerability", IF( 'Compound Alert'!AC119 >= 10, "HIGH",IF( 'Compound Alert'!AC119 >= 7, "MED","LOW")),IF( $B$8="Emerging Threat", IF( 'Compound Alert'!AJ119 >= 10, "HIGH",IF( 'Compound Alert'!AJ119 >= 7, "MED","LOW"))))) -> MED | O88: =IF( $B$8="Overall Alert",IF( 'Compound Alert'!W119 >= 7, "HIGH",IF( 'Compound Alert'!W119 >= 5, "MED","LOW")), IF( $B$8="Underlying Vulnerability", IF( 'Compound Alert'!AD119 >= 10, "HIGH",IF( 'Compound Alert'!AD119 >= 7, "MED","LOW")),IF( $B$8="Emerging Threat", IF( 'Compound Alert'!AK119 >= 10, "HIGH",IF( 'Compound Alert'!AK119 >= 7, "MED","LOW"))))) -> HIGH
A89: 48 | B89: ='Compound Alert'!B149 -> Nicaragua | C89: ='Compound Alert'!C149 -> NIC | D89: ='Compound Alert'!D149 -> LCN Latin America & Caribbean | E89: ='Compound Alert'!E149 -> IDA | F89: ='Compound Alert'!F149 -> 144 | G89: =IF($B$8="Overall Alert",'Compound Alert'!G149,IF($B$8="Underlying Vulnerability",'Compound Alert'!J149,IF($B$8="Emerging Threat",'Compound Alert'!M149))) -> 0.5 | H89: =IF($B$8="Overall Alert",'Compound Alert'!H149,IF($B$8="Underlying Vulnerability",'Compound Alert'!K149,IF($B$8="Emerging Threat",'Compound Alert'!N149))) -> 0.5 | I89: =ROUNDDOWN(G89,0) -> 0 | J89: =IF( $B$8="Overall Alert",IF( 'Compound Alert'!R149 >= 7, "HIGH",IF( 'Compound Alert'!R149 >= 5, "MED","LOW")), IF( $B$8="Underlying Vulnerability", IF( 'Compound Alert'!Y149 >= 10, "HIGH",IF( 'Compound Alert'!Y149 >= 7, "MED","LOW")),IF( $B$8="Emerging Threat", IF( 'Compound Alert'!AF149 >= 10, "HIGH",IF( 'Compound Alert'!AF149 >= 7, "MED","LOW"))))) -> LOW | K89: =IF( $B$8="Overall Alert",IF( 'Compound Alert'!S149 >= 7, "HIGH",IF( 'Compound Alert'!S149 >= 5, "MED","LOW")), IF( $B$8="Underlying Vulnerability", IF( 'Compound Alert'!Z149 >= 10, "HIGH",IF( 'Compound Alert'!Z149 >= 7, "MED","LOW")),IF( $B$8="Emerging Threat", IF( 'Compound Alert'!AG149 >= 10, "HIGH",IF( 'Compound Alert'!AG149 >= 7, "MED","LOW"))))) -> MED | L89: =IF( $B$8="Overall Alert",IF( 'Compound Alert'!T149 >= 7, "HIGH",IF( 'Compound Alert'!T149 >= 5, "MED","LOW")), IF( $B$8="Underlying Vulnerability", IF( 'Compound Alert'!AA149 >= 10, "HIGH",IF( 'Compound Alert'!AA149 >= 7, "MED","LOW")),IF( $B$8="Emerging Threat", IF( 'Compound Alert'!AH149 >= 10, "HIGH",IF( 'Compound Alert'!AH149 >= 7, "MED","LOW"))))) -> LOW | M89: =IF( $B$8="Overall Alert",IF( 'Compound Alert'!U149 >= 7, "HIGH",IF( 'Compound Alert'!U149 >= 5, "MED","LOW")), IF( $B$8="Underlying Vulnerability", IF( 'Compound Alert'!AB149 >= 10, "HIGH",IF( 'Compound Alert'!AB149 >= 7, "MED","LOW")),IF( $B$8="Emerging Threat", IF( 'Compound Alert'!AI149 >= 10, "HIGH",IF( 'Compound Alert'!AI149 >= 7, "MED","LOW"))))) -> LOW | N89: =IF( $B$8="Overall Alert",IF( 'Compound Alert'!V149 >= 7, "HIGH",IF( 'Compound Alert'!V149 >= 5, "MED","LOW")), IF( $B$8="Underlying Vulnerability", IF( 'Compound Alert'!AC149 >= 10, "HIGH",IF( 'Compound Alert'!AC149 >= 7, "MED","LOW")),IF( $B$8="Emerging Threat", IF( 'Compound Alert'!AJ149 >= 10, "HIGH",IF( 'Compound Alert'!AJ149 >= 7, "MED","LOW"))))) -> LOW | O89: =IF( $B$8="Overall Alert",IF( 'Compound Alert'!W149 >= 7, "HIGH",IF( 'Compound Alert'!W149 >= 5, "MED","LOW")), IF( $B$8="Underlying Vulnerability", IF( 'Compound Alert'!AD149 >= 10, "HIGH",IF( 'Compound Alert'!AD149 >= 7, "MED","LOW")),IF( $B$8="Emerging Threat", IF( 'Compound Alert'!AK149 >= 10, "HIGH",IF( 'Compound Alert'!AK149 >= 7, "MED","LOW"))))) -> LOW
A90: 49 | B90: ='Compound Alert'!B93 -> Indonesia | C90: ='Compound Alert'!C93 -> IDN | D90: ='Compound Alert'!D93 -> EAS East Asia & Pacific | E90: ='Compound Alert'!E93 -> IBRD | F90: ='Compound Alert'!F93 -> 88 | G90: =IF($B$8="Overall Alert",'Compound Alert'!G93,IF($B$8="Underlying Vulnerability",'Compound Alert'!J93,IF($B$8="Emerging Threat",'Compound Alert'!M93))) -> 1.5 | H90: =IF($B$8="Overall Alert",'Compound Alert'!H93,IF($B$8="Underlying Vulnerability",'Compound Alert'!K93,IF($B$8="Emerging Threat",'Compound Alert'!N93))) -> 1.5 | I90: =ROUNDDOWN(G90,0) -> 1 | J90: =IF( $B$8="Overall Alert",IF( 'Compound Alert'!R93 >= 7, "HIGH",IF( 'Compound Alert'!R93 >= 5, "MED","LOW")), IF( $B$8="Underlying Vulnerability", IF( 'Compound Alert'!Y93 >= 10, "HIGH",IF( 'Compound Alert'!Y93 >= 7, "MED","LOW")),IF( $B$8="Emerging Threat", IF( 'Compound Alert'!AF93 >= 10, "HIGH",IF( 'Compound Alert'!AF93 >= 7, "MED","LOW"))))) -> LOW | K90: =IF( $B$8="Overall Alert",IF( 'Compound Alert'!S93 >= 7, "HIGH",IF( 'Compound Alert'!S93 >= 5, "MED","LOW")), IF( $B$8="Underlying Vulnerability", IF( 'Compound Alert'!Z93 >= 10, "HIGH",IF( 'Compound Alert'!Z93 >= 7, "MED","LOW")),IF( $B$8="Emerging Threat", IF( 'Compound Alert'!AG93 >= 10, "HIGH",IF( 'Compound Alert'!AG93 >= 7, "MED","LOW"))))) -> LOW | L90: =IF( $B$8="Overall Alert",IF( 'Compound Alert'!T93 >= 7, "HIGH",IF( 'Compound Alert'!T93 >= 5, "MED","LOW")), IF( $B$8="Underlying Vulnerability", IF( 'Compound Alert'!AA93 >= 10, "HIGH",IF( 'Compound Alert'!AA93 >= 7, "MED","LOW")),IF( $B$8="Emerging Threat", IF( 'Compound Alert'!AH93 >= 10, "HIGH",IF( 'Compound Alert'!AH93 >= 7, "MED","LOW"))))) -> MED | M90: =IF( $B$8="Overall Alert",IF( 'Compound Alert'!U93 >= 7, "HIGH",IF( 'Compound Alert'!U93 >= 5, "MED","LOW")), IF( $B$8="Underlying Vulnerability", IF( 'Compound Alert'!AB93 >= 10, "HIGH",IF( 'Compound Alert'!AB93 >= 7, "MED","LOW")),IF( $B$8="Emerging Threat", IF( 'Compound Alert'!AI93 >= 10, "HIGH",IF( 'Compound Alert'!AI93 >= 7, "MED","LOW"))))) -> LOW | N90: =IF( $B$8="Overall Alert",IF( 'Compound Alert'!V93 >= 7, "HIGH",IF( 'Compound Alert'!V93 >= 5, "MED","LOW")), IF( $B$8="Underlying Vulnerability", IF( 'Compound Alert'!AC93 >= 10, "HIGH",IF( 'Compound Alert'!AC93 >= 7, "MED","LOW")),IF( $B$8="Emerging Threat", IF( 'Compound Alert'!AJ93 >= 10, "HIGH",IF( 'Compound Alert'!AJ93 >= 7, "MED","LOW"))))) -> HIGH | O90: =IF( $B$8="Overall Alert",IF( 'Compound Alert'!W93 >= 7, "HIGH",IF( 'Compound Alert'!W93 >= 5, "MED","LOW")), IF( $B$8="Underlying Vulnerability", IF( 'Compound Alert'!AD93 >= 10, "HIGH",IF( 'Compound Alert'!AD93 >= 7, "MED","LOW")),IF( $B$8="Emerging Threat", IF( 'Compound Alert'!AK93 >= 10, "HIGH",IF( 'Compound Alert'!AK93 >= 7, "MED","LOW"))))) -> LOW
A91: 50 | B91: ='Compound Alert'!B199 -> Timor-Leste | C91: ='Compound Alert'!C199 -> TLS | D91: ='Compound Alert'!D199 -> EAS East Asia & Pacific | E91: ='Compound Alert'!E199 -> Blend | F91: ='Compound Alert'!F199 -> 0 | G91: =IF($B$8="Overall Alert",'Compound Alert'!G199,IF($B$8="Underlying Vulnerability",'Compound Alert'!J199,IF($B$8="Emerging Threat",'Compound Alert'!M199))) -> 0.5 | H91: =IF($B$8="Overall Alert",'Compound Alert'!H199,IF($B$8="Underlying Vulnerability",'Compound Alert'!K199,IF($B$8="Emerging Threat",'Compound Alert'!N199))) -> 0.5 | I91: =ROUNDDOWN(G91,0) -> 0 | J91: =IF( $B$8="Overall Alert",IF( 'Compound Alert'!R199 >= 7, "HIGH",IF( 'Compound Alert'!R199 >= 5, "MED","LOW")), IF( $B$8="Underlying Vulnerability", IF( 'Compound Alert'!Y199 >= 10, "HIGH",IF( 'Compound Alert'!Y199 >= 7, "MED","LOW")),IF( $B$8="Emerging Threat", IF( 'Compound Alert'!AF199 >= 10, "HIGH",IF( 'Compound Alert'!AF199 >= 7, "MED","LOW"))))) -> LOW | K91: =IF( $B$8="Overall Alert",IF( 'Compound Alert'!S199 >= 7, "HIGH",IF( 'Compound Alert'!S199 >= 5, "MED","LOW")), IF( $B$8="Underlying Vulnerability", IF( 'Compound Alert'!Z199 >= 10, "HIGH",IF( 'Compound Alert'!Z199 >= 7, "MED","LOW")),IF( $B$8="Emerging Threat", IF( 'Compound Alert'!AG199 >= 10, "HIGH",IF( 'Compound Alert'!AG199 >= 7, "MED","LOW"))))) -> LOW | L91: =IF( $B$8="Overall Alert",IF( 'Compound Alert'!T199 >= 7, "HIGH",IF( 'Compound Alert'!T199 >= 5, "MED","LOW")), IF( $B$8="Underlying Vulnerability", IF( 'Compound Alert'!AA199 >= 10, "HIGH",IF( 'Compound Alert'!AA199 >= 7, "MED","LOW")),IF( $B$8="Emerging Threat", IF( 'Compound Alert'!AH199 >= 10, "HIGH",IF( 'Compound Alert'!AH199 >= 7, "MED","LOW"))))) -> LOW | M91: =IF( $B$8="Overall Alert",IF( 'Compound Alert'!U199 >= 7, "HIGH",IF( 'Compound Alert'!U199 >= 5, "MED","LOW")), IF( $B$8="Underlying Vulnerability", IF( 'Compound Alert'!AB199 >= 10, "HIGH",IF( 'Compound Alert'!AB199 >= 7, "MED","LOW")),IF( $B$8="Emerging Threat", IF( 'Compound Alert'!AI199 >= 10, "HIGH",IF( 'Compound Alert'!AI199 >= 7, "MED","LOW"))))) -> LOW | N91: =IF( $B$8="Overall Alert",IF( 'Compound Alert'!V199 >= 7, "HIGH",IF( 'Compound Alert'!V199 >= 5, "MED","LOW")), IF( $B$8="Underlying Vulnerability", IF( 'Compound Alert'!AC199 >= 10, "HIGH",IF( 'Compound Alert'!AC199 >= 7, "MED","LOW")),IF( $B$8="Emerging Threat", IF( 'Compound Alert'!AJ199 >= 10, "HIGH",IF( 'Compound Alert'!AJ199 >= 7, "MED","LOW"))))) -> MED | O91: =IF( $B$8="Overall Alert",IF( 'Compound Alert'!W199 >= 7, "HIGH",IF( 'Compound Alert'!W199 >= 5, "MED","LOW")), IF( $B$8="Underlying Vulnerability", IF( 'Compound Alert'!AD199 >= 10, "HIGH",IF( 'Compound Alert'!AD199 >= 7, "MED","LOW")),IF( $B$8="Emerging Threat", IF( 'Compound Alert'!AK199 >= 10, "HIGH",IF( 'Compound Alert'!AK199 >= 7, "MED","LOW"))))) -> LOW
A92: 51 | B92: ='Compound Alert'!B208 -> Ukraine | C92: ='Compound Alert'!C208 -> UKR | D92: ='Compound Alert'!D208 -> ECS Europe & Central Asia | E92: ='Compound Alert'!E208 -> IBRD | F92: ='Compound Alert'!F208 -> 0 | G92: =IF($B$8="Overall Alert",'Compound Alert'!G208,IF($B$8="Underlying Vulnerability",'Compound Alert'!J208,IF($B$8="Emerging Threat",'Compound Alert'!M208))) -> 0.5 | H92: =IF($B$8="Overall Alert",'Compound Alert'!H208,IF($B$8="Underlying Vulnerability",'Compound Alert'!K208,IF($B$8="Emerging Threat",'Compound Alert'!N208))) -> 0.5 | I92: =ROUNDDOWN(G92,0) -> 0 | J92: =IF( $B$8="Overall Alert",IF( 'Compound Alert'!R208 >= 7, "HIGH",IF( 'Compound Alert'!R208 >= 5, "MED","LOW")), IF( $B$8="Underlying Vulnerability", IF( 'Compound Alert'!Y208 >= 10, "HIGH",IF( 'Compound Alert'!Y208 >= 7, "MED","LOW")),IF( $B$8="Emerging Threat", IF( 'Compound Alert'!AF208 >= 10, "HIGH",IF( 'Compound Alert'!AF208 >= 7, "MED","LOW"))))) -> LOW | K92: =IF( $B$8="Overall Alert",IF( 'Compound Alert'!S208 >= 7, "HIGH",IF( 'Compound Alert'!S208 >= 5, "MED","LOW")), IF( $B$8="Underlying Vulnerability", IF( 'Compound Alert'!Z208 >= 10, "HIGH",IF( 'Compound Alert'!Z208 >= 7, "MED","LOW")),IF( $B$8="Emerging Threat", IF( 'Compound Alert'!AG208 >= 10, "HIGH",IF( 'Compound Alert'!AG208 >= 7, "MED","LOW"))))) -> LOW | L92: =IF( $B$8="Overall Alert",IF( 'Compound Alert'!T208 >= 7, "HIGH",IF( 'Compound Alert'!T208 >= 5, "MED","LOW")), IF( $B$8="Underlying Vulnerability", IF( 'Compound Alert'!AA208 >= 10, "HIGH",IF( 'Compound Alert'!AA208 >= 7, "MED","LOW")),IF( $B$8="Emerging Threat", IF( 'Compound Alert'!AH208 >= 10, "HIGH",IF( 'Compound Alert'!AH208 >= 7, "MED","LOW"))))) -> LOW | M92: =IF( $B$8="Overall Alert",IF( 'Compound Alert'!U208 >= 7, "HIGH",IF( 'Compound Alert'!U208 >= 5, "MED","LOW")), IF( $B$8="Underlying Vulnerability", IF( 'Compound Alert'!AB208 >= 10, "HIGH",IF( 'Compound Alert'!AB208 >= 7, "MED","LOW")),IF( $B$8="Emerging Threat", IF( 'Compound Alert'!AI208 >= 10, "HIGH",IF( 'Compound Alert'!AI208 >= 7, "MED","LOW"))))) -> LOW | N92: =IF( $B$8="Overall Alert",IF( 'Compound Alert'!V208 >= 7, "HIGH",IF( 'Compound Alert'!V208 >= 5, "MED","LOW")), IF( $B$8="Underlying Vulnerability", IF( 'Compound Alert'!AC208 >= 10, "HIGH",IF( 'Compound Alert'!AC208 >= 7, "MED","LOW")),IF( $B$8="Emerging Threat", IF( 'Compound Alert'!AJ208 >= 10, "HIGH",IF( 'Compound Alert'!AJ208 >= 7, "MED","LOW"))))) -> LOW | O92: =IF( $B$8="Overall Alert",IF( 'Compound Alert'!W208 >= 7, "HIGH",IF( 'Compound Alert'!W208 >= 5, "MED","LOW")), IF( $B$8="Underlying Vulnerability", IF( 'Compound Alert'!AD208 >= 10, "HIGH",IF( 'Compound Alert'!AD208 >= 7, "MED","LOW")),IF( $B$8="Emerging Threat", IF( 'Compound Alert'!AK208 >= 10, "HIGH",IF( 'Compound Alert'!AK208 >= 7, "MED","LOW"))))) -> MED
A93: 52 | B93: ='Compound Alert'!B185 -> Suriname | C93: ='Compound Alert'!C185 -> SUR | D93: ='Compound Alert'!D185 -> LCN Latin America & Caribbean | E93: ='Compound Alert'!E185 -> IBRD | F93: ='Compound Alert'!F185 -> 180 | G93: =IF($B$8="Overall Alert",'Compound Alert'!G185,IF($B$8="Underlying Vulnerability",'Compound Alert'!J185,IF($B$8="Emerging Threat",'Compound Alert'!M185))) -> 0.5 | H93: =IF($B$8="Overall Alert",'Compound Alert'!H185,IF($B$8="Underlying Vulnerability",'Compound Alert'!K185,IF($B$8="Emerging Threat",'Compound Alert'!N185))) -> 0.5 | I93: =ROUNDDOWN(G93,0) -> 0 | J93: =IF( $B$8="Overall Alert",IF( 'Compound Alert'!R185 >= 7, "HIGH",IF( 'Compound Alert'!R185 >= 5, "MED","LOW")), IF( $B$8="Underlying Vulnerability", IF( 'Compound Alert'!Y185 >= 10, "HIGH",IF( 'Compound Alert'!Y185 >= 7, "MED","LOW")),IF( $B$8="Emerging Threat", IF( 'Compound Alert'!AF185 >= 10, "HIGH",IF( 'Compound Alert'!AF185 >= 7, "MED","LOW"))))) -> LOW | K93: =IF( $B$8="Overall Alert",IF( 'Compound Alert'!S185 >= 7, "HIGH",IF( 'Compound Alert'!S185 >= 5, "MED","LOW")), IF( $B$8="Underlying Vulnerability", IF( 'Compound Alert'!Z185 >= 10, "HIGH",IF( 'Compound Alert'!Z185 >= 7, "MED","LOW")),IF( $B$8="Emerging Threat", IF( 'Compound Alert'!AG185 >= 10, "HIGH",IF( 'Compound Alert'!AG185 >= 7, "MED","LOW"))))) -> LOW | L93: =IF( $B$8="Overall Alert",IF( 'Compound Alert'!T185 >= 7, "HIGH",IF( 'Compound Alert'!T185 >= 5, "MED","LOW")), IF( $B$8="Underlying Vulnerability", IF( 'Compound Alert'!AA185 >= 10, "HIGH",IF( 'Compound Alert'!AA185 >= 7, "MED","LOW")),IF( $B$8="Emerging Threat", IF( 'Compound Alert'!AH185 >= 10, "HIGH",IF( 'Compound Alert'!AH185 >= 7, "MED","LOW"))))) -> MED | M93: =IF( $B$8="Overall Alert",IF( 'Compound Alert'!U185 >= 7, "HIGH",IF( 'Compound Alert'!U185 >= 5, "MED","LOW")), IF( $B$8="Underlying Vulnerability", IF( 'Compound Alert'!AB185 >= 10, "HIGH",IF( 'Compound Alert'!AB185 >= 7, "MED","LOW")),IF( $B$8="Emerging Threat", IF( 'Compound Alert'!AI185 >= 10, "HIGH",IF( 'Compound Alert'!AI185 >= 7, "MED","LOW"))))) -> LOW | N93: =IF( $B$8="Overall Alert",IF( 'Compound Alert'!V185 >= 7, "HIGH",IF( 'Compound Alert'!V185 >= 5, "MED","LOW")), IF( $B$8="Underlying Vulnerability", IF( 'Compound Alert'!AC185 >= 10, "HIGH",IF( 'Compound Alert'!AC185 >= 7, "MED","LOW")),IF( $B$8="Emerging Threat", IF( 'Compound Alert'!AJ185 >= 10, "HIGH",IF( 'Compound Alert'!AJ185 >= 7, "MED","LOW"))))) -> LOW | O93: =IF( $B$8="Overall Alert",IF( 'Compound Alert'!W185 >= 7, "HIGH",IF( 'Compound Alert'!W185 >= 5, "MED","LOW")), IF( $B$8="Underlying Vulnerability", IF( 'Compound Alert'!AD185 >= 10, "HIGH",IF( 'Compound Alert'!AD185 >= 7, "MED","LOW")),IF( $B$8="Emerging Threat", IF( 'Compound Alert'!AK185 >= 10, "HIGH",IF( 'Compound Alert'!AK185 >= 7, "MED","LOW"))))) -> LOW
A94: 53 | B94: ='Compound Alert'!B43 -> Côte d’Ivoire | C94: ='Compound Alert'!C43 -> CIV | D94: ='Compound Alert'!D43 -> SSF Sub-Saharan Africa | E94: ='Compound Alert'!E43 -> IDA | F94: ='Compound Alert'!F43 -> 38 | G94: =IF($B$8="Overall Alert",'Compound Alert'!G43,IF($B$8="Underlying Vulnerability",'Compound Alert'!J43,IF($B$8="Emerging Threat",'Compound Alert'!M43))) -> 0 | H94: =IF($B$8="Overall Alert",'Compound Alert'!H43,IF($B$8="Underlying Vulnerability",'Compound Alert'!K43,IF($B$8="Emerging Threat",'Compound Alert'!N43))) -> 0 | I94: =ROUNDDOWN(G94,0) -> 0 | J94: =IF( $B$8="Overall Alert",IF( 'Compound Alert'!R43 >= 7, "HIGH",IF( 'Compound Alert'!R43 >= 5, "MED","LOW")), IF( $B$8="Underlying Vulnerability", IF( 'Compound Alert'!Y43 >= 10, "HIGH",IF( 'Compound Alert'!Y43 >= 7, "MED","LOW")),IF( $B$8="Emerging Threat", IF( 'Compound Alert'!AF43 >= 10, "HIGH",IF( 'Compound Alert'!AF43 >= 7, "MED","LOW"))))) -> LOW | K94: =IF( $B$8="Overall Alert",IF( 'Compound Alert'!S43 >= 7, "HIGH",IF( 'Compound Alert'!S43 >= 5, "MED","LOW")), IF( $B$8="Underlying Vulnerability", IF( 'Compound Alert'!Z43 >= 10, "HIGH",IF( 'Compound Alert'!Z43 >= 7, "MED","LOW")),IF( $B$8="Emerging Threat", IF( 'Compound Alert'!AG43 >= 10, "HIGH",IF( 'Compound Alert'!AG43 >= 7, "MED","LOW"))))) -> LOW | L94: =IF( $B$8="Overall Alert",IF( 'Compound Alert'!T43 >= 7, "HIGH",IF( 'Compound Alert'!T43 >= 5, "MED","LOW")), IF( $B$8="Underlying Vulnerability", IF( 'Compound Alert'!AA43 >= 10, "HIGH",IF( 'Compound Alert'!AA43 >= 7, "MED","LOW")),IF( $B$8="Emerging Threat", IF( 'Compound Alert'!AH43 >= 10, "HIGH",IF( 'Compound Alert'!AH43 >= 7, "MED","LOW"))))) -> LOW | M94: =IF( $B$8="Overall Alert",IF( 'Compound Alert'!U43 >= 7, "HIGH",IF( 'Compound Alert'!U43 >= 5, "MED","LOW")), IF( $B$8="Underlying Vulnerability", IF( 'Compound Alert'!AB43 >= 10, "HIGH",IF( 'Compound Alert'!AB43 >= 7, "MED","LOW")),IF( $B$8="Emerging Threat", IF( 'Compound Alert'!AI43 >= 10, "HIGH",IF( 'Compound Alert'!AI43 >= 7, "MED","LOW"))))) -> LOW | N94: =IF( $B$8="Overall Alert",IF( 'Compound Alert'!V43 >= 7, "HIGH",IF( 'Compound Alert'!V43 >= 5, "MED","LOW")), IF( $B$8="Underlying Vulnerability", IF( 'Compound Alert'!AC43 >= 10, "HIGH",IF( 'Compound Alert'!AC43 >= 7, "MED","LOW")),IF( $B$8="Emerging Threat", IF( 'Compound Alert'!AJ43 >= 10, "HIGH",IF( 'Compound Alert'!AJ43 >= 7, "MED","LOW"))))) -> LOW | O94: =IF( $B$8="Overall Alert",IF( 'Compound Alert'!W43 >= 7, "HIGH",IF( 'Compound Alert'!W43 >= 5, "MED","LOW")), IF( $B$8="Underlying Vulnerability", IF( 'Compound Alert'!AD43 >= 10, "HIGH",IF( 'Compound Alert'!AD43 >= 7, "MED","LOW")),IF( $B$8="Emerging Threat", IF( 'Compound Alert'!AK43 >= 10, "HIGH",IF( 'Compound Alert'!AK43 >= 7, "MED","LOW"))))) -> LOW
A95: 54 | B95: ='Compound Alert'!B175 -> Senegal | C95: ='Compound Alert'!C175 -> SEN | D95: ='Compound Alert'!D175 -> SSF Sub-Saharan Africa | E95: ='Compound Alert'!E175 -> IDA | F95: ='Compound Alert'!F175 -> 170 | G95: =IF($B$8="Overall Alert",'Compound Alert'!G175,IF($B$8="Underlying Vulnerability",'Compound Alert'!J175,IF($B$8="Emerging Threat",'Compound Alert'!M175))) -> 0 | H95: =IF($B$8="Overall Alert",'Compound Alert'!H175,IF($B$8="Underlying Vulnerability",'Compound Alert'!K175,IF($B$8="Emerging Threat",'Compound Alert'!N175))) -> 0 | I95: =ROUNDDOWN(G95,0) -> 0 | J95: =IF( $B$8="Overall Alert",IF( 'Compound Alert'!R175 >= 7, "HIGH",IF( 'Compound Alert'!R175 >= 5, "MED","LOW")), IF( $B$8="Underlying Vulnerability", IF( 'Compound Alert'!Y175 >= 10, "HIGH",IF( 'Compound Alert'!Y175 >= 7, "MED","LOW")),IF( $B$8="Emerging Threat", IF( 'Compound Alert'!AF175 >= 10, "HIGH",IF( 'Compound Alert'!AF175 >= 7, "MED","LOW"))))) -> LOW | K95: =IF( $B$8="Overall Alert",IF( 'Compound Alert'!S175 >= 7, "HIGH",IF( 'Compound Alert'!S175 >= 5, "MED","LOW")), IF( $B$8="Underlying Vulnerability", IF( 'Compound Alert'!Z175 >= 10, "HIGH",IF( 'Compound Alert'!Z175 >= 7, "MED","LOW")),IF( $B$8="Emerging Threat", IF( 'Compound Alert'!AG175 >= 10, "HIGH",IF( 'Compound Alert'!AG175 >= 7, "MED","LOW"))))) -> LOW | L95: =IF( $B$8="Overall Alert",IF( 'Compound Alert'!T175 >= 7, "HIGH",IF( 'Compound Alert'!T175 >= 5, "MED","LOW")), IF( $B$8="Underlying Vulnerability", IF( 'Compound Alert'!AA175 >= 10, "HIGH",IF( 'Compound Alert'!AA175 >= 7, "MED","LOW")),IF( $B$8="Emerging Threat", IF( 'Compound Alert'!AH175 >= 10, "HIGH",IF( 'Compound Alert'!AH175 >= 7, "MED","LOW"))))) -> LOW | M95: =IF( $B$8="Overall Alert",IF( 'Compound Alert'!U175 >= 7, "HIGH",IF( 'Compound Alert'!U175 >= 5, "MED","LOW")), IF( $B$8="Underlying Vulnerability", IF( 'Compound Alert'!AB175 >= 10, "HIGH",IF( 'Compound Alert'!AB175 >= 7, "MED","LOW")),IF( $B$8="Emerging Threat", IF( 'Compound Alert'!AI175 >= 10, "HIGH",IF( 'Compound Alert'!AI175 >= 7, "MED","LOW"))))) -> LOW | N95: =IF( $B$8="Overall Alert",IF( 'Compound Alert'!V175 >= 7, "HIGH",IF( 'Compound Alert'!V175 >= 5, "MED","LOW")), IF( $B$8="Underlying Vulnerability", IF( 'Compound Alert'!AC175 >= 10, "HIGH",IF( 'Compound Alert'!AC175 >= 7, "MED","LOW")),IF( $B$8="Emerging Threat", IF( 'Compound Alert'!AJ175 >= 10, "HIGH",IF( 'Compound Alert'!AJ175 >= 7, "MED","LOW"))))) -> LOW | O95: =IF( $B$8="Overall Alert",IF( 'Compound Alert'!W175 >= 7, "HIGH",IF( 'Compound Alert'!W175 >= 5, "MED","LOW")), IF( $B$8="Underlying Vulnerability", IF( 'Compound Alert'!AD175 >= 10, "HIGH",IF( 'Compound Alert'!AD175 >= 7, "MED","LOW")),IF( $B$8="Emerging Threat", IF( 'Compound Alert'!AK175 >= 10, "HIGH",IF( 'Compound Alert'!AK175 >= 7, "MED","LOW"))))) -> LOW
A96: 55 | B96: ='Compound Alert'!B61 -> Algeria | C96: ='Compound Alert'!C61 -> DZA | D96: ='Compound Alert'!D61 -> MEA Middle East & North Africa | E96: ='Compound Alert'!E61 -> IBRD | F96: ='Compound Alert'!F61 -> 56 | G96: =IF($B$8="Overall Alert",'Compound Alert'!G61,IF($B$8="Underlying Vulnerability",'Compound Alert'!J61,IF($B$8="Emerging Threat",'Compound Alert'!M61))) -> 0 | H96: =IF($B$8="Overall Alert",'Compound Alert'!H61,IF($B$8="Underlying Vulnerability",'Compound Alert'!K61,IF($B$8="Emerging Threat",'Compound Alert'!N61))) -> 0 | I96: =ROUNDDOWN(G96,0) -> 0 | J96: =IF( $B$8="Overall Alert",IF( 'Compound Alert'!R61 >= 7, "HIGH",IF( 'Compound Alert'!R61 >= 5, "MED","LOW")), IF( $B$8="Underlying Vulnerability", IF( 'Compound Alert'!Y61 >= 10, "HIGH",IF( 'Compound Alert'!Y61 >= 7, "MED","LOW")),IF( $B$8="Emerging Threat", IF( 'Compound Alert'!AF61 >= 10, "HIGH",IF( 'Compound Alert'!AF61 >= 7, "MED","LOW"))))) -> LOW | K96: =IF( $B$8="Overall Alert",IF( 'Compound Alert'!S61 >= 7, "HIGH",IF( 'Compound Alert'!S61 >= 5, "MED","LOW")), IF( $B$8="Underlying Vulnerability", IF( 'Compound Alert'!Z61 >= 10, "HIGH",IF( 'Compound Alert'!Z61 >= 7, "MED","LOW")),IF( $B$8="Emerging Threat", IF( 'Compound Alert'!AG61 >= 10, "HIGH",IF( 'Compound Alert'!AG61 >= 7, "MED","LOW"))))) -> LOW | L96: =IF( $B$8="Overall Alert",IF( 'Compound Alert'!T61 >= 7, "HIGH",IF( 'Compound Alert'!T61 >= 5, "MED","LOW")), IF( $B$8="Underlying Vulnerability", IF( 'Compound Alert'!AA61 >= 10, "HIGH",IF( 'Compound Alert'!AA61 >= 7, "MED","LOW")),IF( $B$8="Emerging Threat", IF( 'Compound Alert'!AH61 >= 10, "HIGH",IF( 'Compound Alert'!AH61 >= 7, "MED","LOW"))))) -> LOW | M96: =IF( $B$8="Overall Alert",IF( 'Compound Alert'!U61 >= 7, "HIGH",IF( 'Compound Alert'!U61 >= 5, "MED","LOW")), IF( $B$8="Underlying Vulnerability", IF( 'Compound Alert'!AB61 >= 10, "HIGH",IF( 'Compound Alert'!AB61 >= 7, "MED","LOW")),IF( $B$8="Emerging Threat", IF( 'Compound Alert'!AI61 >= 10, "HIGH",IF( 'Compound Alert'!AI61 >= 7, "MED","LOW"))))) -> LOW | N96: =IF( $B$8="Overall Alert",IF( 'Compound Alert'!V61 >= 7, "HIGH",IF( 'Compound Alert'!V61 >= 5, "MED","LOW")), IF( $B$8="Underlying Vulnerability", IF( 'Compound Alert'!AC61 >= 10, "HIGH",IF( 'Compound Alert'!AC61 >= 7, "MED","LOW")),IF( $B$8="Emerging Threat", IF( 'Compound Alert'!AJ61 >= 10, "HIGH",IF( 'Compound Alert'!AJ61 >= 7, "MED","LOW"))))) -> LOW | O96: =IF( $B$8="Overall Alert",IF( 'Compound Alert'!W61 >= 7, "HIGH",IF( 'Compound Alert'!W61 >= 5, "MED","LOW")), IF( $B$8="Underlying Vulnerability", IF( 'Compound Alert'!AD61 >= 10, "HIGH",IF( 'Compound Alert'!AD61 >= 7, "MED","LOW")),IF( $B$8="Emerging Threat", IF( 'Compound Alert'!AK61 >= 10, "HIGH",IF( 'Compound Alert'!AK61 >= 7, "MED","LOW"))))) -> LOW
A97: 56 | B97: ='Compound Alert'!B95 -> India | C97: ='Compound Alert'!C95 -> IND | D97: ='Compound Alert'!D95 -> SAS South Asia | E97: ='Compound Alert'!E95 -> IBRD | F97: ='Compound Alert'!F95 -> 90 | G97: =IF($B$8="Overall Alert",'Compound Alert'!G95,IF($B$8="Underlying Vulnerability",'Compound Alert'!J95,IF($B$8="Emerging Threat",'Compound Alert'!M95))) -> 0 | H97: =IF($B$8="Overall Alert",'Compound Alert'!H95,IF($B$8="Underlying Vulnerability",'Compound Alert'!K95,IF($B$8="Emerging Threat",'Compound Alert'!N95))) -> 0 | I97: =ROUNDDOWN(G97,0) -> 0 | J97: =IF( $B$8="Overall Alert",IF( 'Compound Alert'!R95 >= 7, "HIGH",IF( 'Compound Alert'!R95 >= 5, "MED","LOW")), IF( $B$8="Underlying Vulnerability", IF( 'Compound Alert'!Y95 >= 10, "HIGH",IF( 'Compound Alert'!Y95 >= 7, "MED","LOW")),IF( $B$8="Emerging Threat", IF( 'Compound Alert'!AF95 >= 10, "HIGH",IF( 'Compound Alert'!AF95 >= 7, "MED","LOW"))))) -> LOW | K97: =IF( $B$8="Overall Alert",IF( 'Compound Alert'!S95 >= 7, "HIGH",IF( 'Compound Alert'!S95 >= 5, "MED","LOW")), IF( $B$8="Underlying Vulnerability", IF( 'Compound Alert'!Z95 >= 10, "HIGH",IF( 'Compound Alert'!Z95 >= 7, "MED","LOW")),IF( $B$8="Emerging Threat", IF( 'Compound Alert'!AG95 >= 10, "HIGH",IF( 'Compound Alert'!AG95 >= 7, "MED","LOW"))))) -> LOW | L97: =IF( $B$8="Overall Alert",IF( 'Compound Alert'!T95 >= 7, "HIGH",IF( 'Compound Alert'!T95 >= 5, "MED","LOW")), IF( $B$8="Underlying Vulnerability", IF( 'Compound Alert'!AA95 >= 10, "HIGH",IF( 'Compound Alert'!AA95 >= 7, "MED","LOW")),IF( $B$8="Emerging Threat", IF( 'Compound Alert'!AH95 >= 10, "HIGH",IF( 'Compound Alert'!AH95 >= 7, "MED","LOW"))))) -> LOW | M97: =IF( $B$8="Overall Alert",IF( 'Compound Alert'!U95 >= 7, "HIGH",IF( 'Compound Alert'!U95 >= 5, "MED","LOW")), IF( $B$8="Underlying Vulnerability", IF( 'Compound Alert'!AB95 >= 10, "HIGH",IF( 'Compound Alert'!AB95 >= 7, "MED","LOW")),IF( $B$8="Emerging Threat", IF( 'Compound Alert'!AI95 >= 10, "HIGH",IF( 'Compound Alert'!AI95 >= 7, "MED","LOW"))))) -> LOW | N97: =IF( $B$8="Overall Alert",IF( 'Compound Alert'!V95 >= 7, "HIGH",IF( 'Compound Alert'!V95 >= 5, "MED","LOW")), IF( $B$8="Underlying Vulnerability", IF( 'Compound Alert'!AC95 >= 10, "HIGH",IF( 'Compound Alert'!AC95 >= 7, "MED","LOW")),IF( $B$8="Emerging Threat", IF( 'Compound Alert'!AJ95 >= 10, "HIGH",IF( 'Compound Alert'!AJ95 >= 7, "MED","LOW"))))) -> LOW | O97: =IF( $B$8="Overall Alert",IF( 'Compound Alert'!W95 >= 7, "HIGH",IF( 'Compound Alert'!W95 >= 5, "MED","LOW")), IF( $B$8="Underlying Vulnerability", IF( 'Compound Alert'!AD95 >= 10, "HIGH",IF( 'Compound Alert'!AD95 >= 7, "MED","LOW")),IF( $B$8="Emerging Threat", IF( 'Compound Alert'!AK95 >= 10, "HIGH",IF( 'Compound Alert'!AK95 >= 7, "MED","LOW"))))) -> LOW
A98: 57 | B98: ='Compound Alert'!B42 -> China | C98: ='Compound Alert'!C42 -> CHN | D98: ='Compound Alert'!D42 -> EAS East Asia & Pacific | E98: ='Compound Alert'!E42 -> IBRD | F98: ='Compound Alert'!F42 -> 37 | G98: =IF($B$8="Overall Alert",'Compound Alert'!G42,IF($B$8="Underlying Vulnerability",'Compound Alert'!J42,IF($B$8="Emerging Threat",'Compound Alert'!M42))) -> 1 | H98: =IF($B$8="Overall Alert",'Compound Alert'!H42,IF($B$8="Underlying Vulnerability",'Compound Alert'!K42,IF($B$8="Emerging Threat",'Compound Alert'!N42))) -> 1 | I98: =ROUNDDOWN(G98,0) -> 1 | J98: =IF( $B$8="Overall Alert",IF( 'Compound Alert'!R42 >= 7, "HIGH",IF( 'Compound Alert'!R42 >= 5, "MED","LOW")), IF( $B$8="Underlying Vulnerability", IF( 'Compound Alert'!Y42 >= 10, "HIGH",IF( 'Compound Alert'!Y42 >= 7, "MED","LOW")),IF( $B$8="Emerging Threat", IF( 'Compound Alert'!AF42 >= 10, "HIGH",IF( 'Compound Alert'!AF42 >= 7, "MED","LOW"))))) -> LOW | K98: =IF( $B$8="Overall Alert",IF( 'Compound Alert'!S42 >= 7, "HIGH",IF( 'Compound Alert'!S42 >= 5, "MED","LOW")), IF( $B$8="Underlying Vulnerability", IF( 'Compound Alert'!Z42 >= 10, "HIGH",IF( 'Compound Alert'!Z42 >= 7, "MED","LOW")),IF( $B$8="Emerging Threat", IF( 'Compound Alert'!AG42 >= 10, "HIGH",IF( 'Compound Alert'!AG42 >= 7, "MED","LOW"))))) -> LOW | L98: =IF( $B$8="Overall Alert",IF( 'Compound Alert'!T42 >= 7, "HIGH",IF( 'Compound Alert'!T42 >= 5, "MED","LOW")), IF( $B$8="Underlying Vulnerability", IF( 'Compound Alert'!AA42 >= 10, "HIGH",IF( 'Compound Alert'!AA42 >= 7, "MED","LOW")),IF( $B$8="Emerging Threat", IF( 'Compound Alert'!AH42 >= 10, "HIGH",IF( 'Compound Alert'!AH42 >= 7, "MED","LOW"))))) -> LOW | M98: =IF( $B$8="Overall Alert",IF( 'Compound Alert'!U42 >= 7, "HIGH",IF( 'Compound Alert'!U42 >= 5, "MED","LOW")), IF( $B$8="Underlying Vulnerability", IF( 'Compound Alert'!AB42 >= 10, "HIGH",IF( 'Compound Alert'!AB42 >= 7, "MED","LOW")),IF( $B$8="Emerging Threat", IF( 'Compound Alert'!AI42 >= 10, "HIGH",IF( 'Compound Alert'!AI42 >= 7, "MED","LOW"))))) -> LOW | N98: =IF( $B$8="Overall Alert",IF( 'Compound Alert'!V42 >= 7, "HIGH",IF( 'Compound Alert'!V42 >= 5, "MED","LOW")), IF( $B$8="Underlying Vulnerability", IF( 'Compound Alert'!AC42 >= 10, "HIGH",IF( 'Compound Alert'!AC42 >= 7, "MED","LOW")),IF( $B$8="Emerging Threat", IF( 'Compound Alert'!AJ42 >= 10, "HIGH",IF( 'Compound Alert'!AJ42 >= 7, "MED","LOW"))))) -> HIGH | O98: =IF( $B$8="Overall Alert",IF( 'Compound Alert'!W42 >= 7, "HIGH",IF( 'Compound Alert'!W42 >= 5, "MED","LOW")), IF( $B$8="Underlying Vulnerability", IF( 'Compound Alert'!AD42 >= 10, "HIGH",IF( 'Compound Alert'!AD42 >= 7, "MED","LOW")),IF( $B$8="Emerging Threat", IF( 'Compound Alert'!AK42 >= 10, "HIGH",IF( 'Compound Alert'!AK42 >= 7, "MED","LOW"))))) -> LOW
A99: 58 | B99: ='Compound Alert'!B97 -> Iran, Islamic Rep. | C99: ='Compound Alert'!C97 -> IRN | D99: ='Compound Alert'!D97 -> MEA Middle East & North Africa | E99: ='Compound Alert'!E97 -> IBRD | F99: ='Compound Alert'!F97 -> 92 | G99: =IF($B$8="Overall Alert",'Compound Alert'!G97,IF($B$8="Underlying Vulnerability",'Compound Alert'!J97,IF($B$8="Emerging Threat",'Compound Alert'!M97))) -> 1.5 | H99: =IF($B$8="Overall Alert",'Compound Alert'!H97,IF($B$8="Underlying Vulnerability",'Compound Alert'!K97,IF($B$8="Emerging Threat",'Compound Alert'!N97))) -> 1.5 | I99: =ROUNDDOWN(G99,0) -> 1 | J99: =IF( $B$8="Overall Alert",IF( 'Compound Alert'!R97 >= 7, "HIGH",IF( 'Compound Alert'!R97 >= 5, "MED","LOW")), IF( $B$8="Underlying Vulnerability", IF( 'Compound Alert'!Y97 >= 10, "HIGH",IF( 'Compound Alert'!Y97 >= 7, "MED","LOW")),IF( $B$8="Emerging Threat", IF( 'Compound Alert'!AF97 >= 10, "HIGH",IF( 'Compound Alert'!AF97 >= 7, "MED","LOW"))))) -> LOW | K99: =IF( $B$8="Overall Alert",IF( 'Compound Alert'!S97 >= 7, "HIGH",IF( 'Compound Alert'!S97 >= 5, "MED","LOW")), IF( $B$8="Underlying Vulnerability", IF( 'Compound Alert'!Z97 >= 10, "HIGH",IF( 'Compound Alert'!Z97 >= 7, "MED","LOW")),IF( $B$8="Emerging Threat", IF( 'Compound Alert'!AG97 >= 10, "HIGH",IF( 'Compound Alert'!AG97 >= 7, "MED","LOW"))))) -> LOW | L99: =IF( $B$8="Overall Alert",IF( 'Compound Alert'!T97 >= 7, "HIGH",IF( 'Compound Alert'!T97 >= 5, "MED","LOW")), IF( $B$8="Underlying Vulnerability", IF( 'Compound Alert'!AA97 >= 10, "HIGH",IF( 'Compound Alert'!AA97 >= 7, "MED","LOW")),IF( $B$8="Emerging Threat", IF( 'Compound Alert'!AH97 >= 10, "HIGH",IF( 'Compound Alert'!AH97 >= 7, "MED","LOW"))))) -> HIGH | M99: =IF( $B$8="Overall Alert",IF( 'Compound Alert'!U97 >= 7, "HIGH",IF( 'Compound Alert'!U97 >= 5, "MED","LOW")), IF( $B$8="Underlying Vulnerability", IF( 'Compound Alert'!AB97 >= 10, "HIGH",IF( 'Compound Alert'!AB97 >= 7, "MED","LOW")),IF( $B$8="Emerging Threat", IF( 'Compound Alert'!AI97 >= 10, "HIGH",IF( 'Compound Alert'!AI97 >= 7, "MED","LOW"))))) -> LOW | N99: =IF( $B$8="Overall Alert",IF( 'Compound Alert'!V97 >= 7, "HIGH",IF( 'Compound Alert'!V97 >= 5, "MED","LOW")), IF( $B$8="Underlying Vulnerability", IF( 'Compound Alert'!AC97 >= 10, "HIGH",IF( 'Compound Alert'!AC97 >= 7, "MED","LOW")),IF( $B$8="Emerging Threat", IF( 'Compound Alert'!AJ97 >= 10, "HIGH",IF( 'Compound Alert'!AJ97 >= 7, "MED","LOW"))))) -> LOW | O99: =IF( $B$8="Overall Alert",IF( 'Compound Alert'!W97 >= 7, "HIGH",IF( 'Compound Alert'!W97 >= 5, "MED","LOW")), IF( $B$8="Underlying Vulnerability", IF( 'Compound Alert'!AD97 >= 10, "HIGH",IF( 'Compound Alert'!AD97 >= 7, "MED","LOW")),IF( $B$8="Emerging Threat", IF( 'Compound Alert'!AK97 >= 10, "HIGH",IF( 'Compound Alert'!AK97 >= 7, "MED","LOW"))))) -> MED
A100: 59 | B100: ='Compound Alert'!B197 -> Tajikistan | C100: ='Compound Alert'!C197 -> TJK | D100: ='Compound Alert'!D197 -> ECS Europe & Central Asia | E100: ='Compound Alert'!E197 -> IDA | F100: ='Compound Alert'!F197 -> 0 | G100: =IF($B$8="Overall Alert",'Compound Alert'!G197,IF($B$8="Underlying Vulnerability",'Compound Alert'!J197,IF($B$8="Emerging Threat",'Compound Alert'!M197))) -> 1 | H100: =IF($B$8="Overall Alert",'Compound Alert'!H197,IF($B$8="Underlying Vulnerability",'Compound Alert'!K197,IF($B$8="Emerging Threat",'Compound Alert'!N197))) -> 1 | I100: =ROUNDDOWN(G100,0) -> 1 | J100: =IF( $B$8="Overall Alert",IF( 'Compound Alert'!R197 >= 7, "HIGH",IF( 'Compound Alert'!R197 >= 5, "MED","LOW")), IF( $B$8="Underlying Vulnerability", IF( 'Compound Alert'!Y197 >= 10, "HIGH",IF( 'Compound Alert'!Y197 >= 7, "MED","LOW")),IF( $B$8="Emerging Threat", IF( 'Compound Alert'!AF197 >= 10, "HIGH",IF( 'Compound Alert'!AF197 >= 7, "MED","LOW"))))) -> LOW | K100: =IF( $B$8="Overall Alert",IF( 'Compound Alert'!S197 >= 7, "HIGH",IF( 'Compound Alert'!S197 >= 5, "MED","LOW")), IF( $B$8="Underlying Vulnerability", IF( 'Compound Alert'!Z197 >= 10, "HIGH",IF( 'Compound Alert'!Z197 >= 7, "MED","LOW")),IF( $B$8="Emerging Threat", IF( 'Compound Alert'!AG197 >= 10, "HIGH",IF( 'Compound Alert'!AG197 >= 7, "MED","LOW"))))) -> LOW | L100: =IF( $B$8="Overall Alert",IF( 'Compound Alert'!T197 >= 7, "HIGH",IF( 'Compound Alert'!T197 >= 5, "MED","LOW")), IF( $B$8="Underlying Vulnerability", IF( 'Compound Alert'!AA197 >= 10, "HIGH",IF( 'Compound Alert'!AA197 >= 7, "MED","LOW")),IF( $B$8="Emerging Threat", IF( 'Compound Alert'!AH197 >= 10, "HIGH",IF( 'Compound Alert'!AH197 >= 7, "MED","LOW"))))) -> HIGH | M100: =IF( $B$8="Overall Alert",IF( 'Compound Alert'!U197 >= 7, "HIGH",IF( 'Compound Alert'!U197 >= 5, "MED","LOW")), IF( $B$8="Underlying Vulnerability", IF( 'Compound Alert'!AB197 >= 10, "HIGH",IF( 'Compound Alert'!AB197 >= 7, "MED","LOW")),IF( $B$8="Emerging Threat", IF( 'Compound Alert'!AI197 >= 10, "HIGH",IF( 'Compound Alert'!AI197 >= 7, "MED","LOW"))))) -> LOW | N100: =IF( $B$8="Overall Alert",IF( 'Compound Alert'!V197 >= 7, "HIGH",IF( 'Compound Alert'!V197 >= 5, "MED","LOW")), IF( $B$8="Underlying Vulnerability", IF( 'Compound Alert'!AC197 >= 10, "HIGH",IF( 'Compound Alert'!AC197 >= 7, "MED","LOW")),IF( $B$8="Emerging Threat", IF( 'Compound Alert'!AJ197 >= 10, "HIGH",IF( 'Compound Alert'!AJ197 >= 7, "MED","LOW"))))) -> LOW | O100: =IF( $B$8="Overall Alert",IF( 'Compound Alert'!W197 >= 7, "HIGH",IF( 'Compound Alert'!W197 >= 5, "MED","LOW")), IF( $B$8="Underlying Vulnerability", IF( 'Compound Alert'!AD197 >= 10, "HIGH",IF( 'Compound Alert'!AD197 >= 7, "MED","LOW")),IF( $B$8="Emerging Threat", IF( 'Compound Alert'!AK197 >= 10, "HIGH",IF( 'Compound Alert'!AK197 >= 7, "MED","LOW"))))) -> LOW
A101: 60 | B101: ='Compound Alert'!B211 -> Uzbekistan | C101: ='Compound Alert'!C211 -> UZB | D101: ='Compound Alert'!D211 -> ECS Europe & Central Asia | E101: ='Compound Alert'!E211 -> Blend | F101: ='Compound Alert'!F211 -> 0 | G101: =IF($B$8="Overall Alert",'Compound Alert'!G211,IF($B$8="Underlying Vulnerability",'Compound Alert'!J211,IF($B$8="Emerging Threat",'Compound Alert'!M211))) -> 0 | H101: =IF($B$8="Overall Alert",'Compound Alert'!H211,IF($B$8="Underlying Vulnerability",'Compound Alert'!K211,IF($B$8="Emerging Threat",'Compound Alert'!N211))) -> 0 | I101: =ROUNDDOWN(G101,0) -> 0 | J101: =IF( $B$8="Overall Alert",IF( 'Compound Alert'!R211 >= 7, "HIGH",IF( 'Compound Alert'!R211 >= 5, "MED","LOW")), IF( $B$8="Underlying Vulnerability", IF( 'Compound Alert'!Y211 >= 10, "HIGH",IF( 'Compound Alert'!Y211 >= 7, "MED","LOW")),IF( $B$8="Emerging Threat", IF( 'Compound Alert'!AF211 >= 10, "HIGH",IF( 'Compound Alert'!AF211 >= 7, "MED","LOW"))))) -> LOW | K101: =IF( $B$8="Overall Alert",IF( 'Compound Alert'!S211 >= 7, "HIGH",IF( 'Compound Alert'!S211 >= 5, "MED","LOW")), IF( $B$8="Underlying Vulnerability", IF( 'Compound Alert'!Z211 >= 10, "HIGH",IF( 'Compound Alert'!Z211 >= 7, "MED","LOW")),IF( $B$8="Emerging Threat", IF( 'Compound Alert'!AG211 >= 10, "HIGH",IF( 'Compound Alert'!AG211 >= 7, "MED","LOW"))))) -> LOW | L101: =IF( $B$8="Overall Alert",IF( 'Compound Alert'!T211 >= 7, "HIGH",IF( 'Compound Alert'!T211 >= 5, "MED","LOW")), IF( $B$8="Underlying Vulnerability", IF( 'Compound Alert'!AA211 >= 10, "HIGH",IF( 'Compound Alert'!AA211 >= 7, "MED","LOW")),IF( $B$8="Emerging Threat", IF( 'Compound Alert'!AH211 >= 10, "HIGH",IF( 'Compound Alert'!AH211 >= 7, "MED","LOW"))))) -> LOW | M101: =IF( $B$8="Overall Alert",IF( 'Compound Alert'!U211 >= 7, "HIGH",IF( 'Compound Alert'!U211 >= 5, "MED","LOW")), IF( $B$8="Underlying Vulnerability", IF( 'Compound Alert'!AB211 >= 10, "HIGH",IF( 'Compound Alert'!AB211 >= 7, "MED","LOW")),IF( $B$8="Emerging Threat", IF( 'Compound Alert'!AI211 >= 10, "HIGH",IF( 'Compound Alert'!AI211 >= 7, "MED","LOW"))))) -> LOW | N101: =IF( $B$8="Overall Alert",IF( 'Compound Alert'!V211 >= 7, "HIGH",IF( 'Compound Alert'!V211 >= 5, "MED","LOW")), IF( $B$8="Underlying Vulnerability", IF( 'Compound Alert'!AC211 >= 10, "HIGH",IF( 'Compound Alert'!AC211 >= 7, "MED","LOW")),IF( $B$8="Emerging Threat", IF( 'Compound Alert'!AJ211 >= 10, "HIGH",IF( 'Compound Alert'!AJ211 >= 7, "MED","LOW"))))) -> LOW | O101: =IF( $B$8="Overall Alert",IF( 'Compound Alert'!W211 >= 7, "HIGH",IF( 'Compound Alert'!W211 >= 5, "MED","LOW")), IF( $B$8="Underlying Vulnerability", IF( 'Compound Alert'!AD211 >= 10, "HIGH",IF( 'Compound Alert'!AD211 >= 7, "MED","LOW")),IF( $B$8="Emerging Threat", IF( 'Compound Alert'!AK211 >= 10, "HIGH",IF( 'Compound Alert'!AK211 >= 7, "MED","LOW"))))) -> LOW
A102: 61 | B102: ='Compound Alert'!B129 -> Madagascar | C102: ='Compound Alert'!C129 -> MDG | D102: ='Compound Alert'!D129 -> SSF Sub-Saharan Africa | E102: ='Compound Alert'!E129 -> IDA | F102: ='Compound Alert'!F129 -> 124 | G102: =IF($B$8="Overall Alert",'Compound Alert'!G129,IF($B$8="Underlying Vulnerability",'Compound Alert'!J129,IF($B$8="Emerging Threat",'Compound Alert'!M129))) -> 3 | H102: =IF($B$8="Overall Alert",'Compound Alert'!H129,IF($B$8="Underlying Vulnerability",'Compound Alert'!K129,IF($B$8="Emerging Threat",'Compound Alert'!N129))) -> 3 | I102: =ROUNDDOWN(G102,0) -> 3 | J102: =IF( $B$8="Overall Alert",IF( 'Compound Alert'!R129 >= 7, "HIGH",IF( 'Compound Alert'!R129 >= 5, "MED","LOW")), IF( $B$8="Underlying Vulnerability", IF( 'Compound Alert'!Y129 >= 10, "HIGH",IF( 'Compound Alert'!Y129 >= 7, "MED","LOW")),IF( $B$8="Emerging Threat", IF( 'Compound Alert'!AF129 >= 10, "HIGH",IF( 'Compound Alert'!AF129 >= 7, "MED","LOW"))))) -> LOW | K102: =IF( $B$8="Overall Alert",IF( 'Compound Alert'!S129 >= 7, "HIGH",IF( 'Compound Alert'!S129 >= 5, "MED","LOW")), IF( $B$8="Underlying Vulnerability", IF( 'Compound Alert'!Z129 >= 10, "HIGH",IF( 'Compound Alert'!Z129 >= 7, "MED","LOW")),IF( $B$8="Emerging Threat", IF( 'Compound Alert'!AG129 >= 10, "HIGH",IF( 'Compound Alert'!AG129 >= 7, "MED","LOW"))))) -> HIGH | L102: =IF( $B$8="Overall Alert",IF( 'Compound Alert'!T129 >= 7, "HIGH",IF( 'Compound Alert'!T129 >= 5, "MED","LOW")), IF( $B$8="Underlying Vulnerability", IF( 'Compound Alert'!AA129 >= 10, "HIGH",IF( 'Compound Alert'!AA129 >= 7, "MED","LOW")),IF( $B$8="Emerging Threat", IF( 'Compound Alert'!AH129 >= 10, "HIGH",IF( 'Compound Alert'!AH129 >= 7, "MED","LOW"))))) -> LOW | M102: =IF( $B$8="Overall Alert",IF( 'Compound Alert'!U129 >= 7, "HIGH",IF( 'Compound Alert'!U129 >= 5, "MED","LOW")), IF( $B$8="Underlying Vulnerability", IF( 'Compound Alert'!AB129 >= 10, "HIGH",IF( 'Compound Alert'!AB129 >= 7, "MED","LOW")),IF( $B$8="Emerging Threat", IF( 'Compound Alert'!AI129 >= 10, "HIGH",IF( 'Compound Alert'!AI129 >= 7, "MED","LOW"))))) -> LOW | N102: =IF( $B$8="Overall Alert",IF( 'Compound Alert'!V129 >= 7, "HIGH",IF( 'Compound Alert'!V129 >= 5, "MED","LOW")), IF( $B$8="Underlying Vulnerability", IF( 'Compound Alert'!AC129 >= 10, "HIGH",IF( 'Compound Alert'!AC129 >= 7, "MED","LOW")),IF( $B$8="Emerging Threat", IF( 'Compound Alert'!AJ129 >= 10, "HIGH",IF( 'Compound Alert'!AJ129 >= 7, "MED","LOW"))))) -> HIGH | O102: =IF( $B$8="Overall Alert",IF( 'Compound Alert'!W129 >= 7, "HIGH",IF( 'Compound Alert'!W129 >= 5, "MED","LOW")), IF( $B$8="Underlying Vulnerability", IF( 'Compound Alert'!AD129 >= 10, "HIGH",IF( 'Compound Alert'!AD129 >= 7, "MED","LOW")),IF( $B$8="Emerging Threat", IF( 'Compound Alert'!AK129 >= 10, "HIGH",IF( 'Compound Alert'!AK129 >= 7, "MED","LOW"))))) -> HIGH
A103: 62 | B103: ='Compound Alert'!B107 -> Kyrgyz Republic | C103: ='Compound Alert'!C107 -> KGZ | D103: ='Compound Alert'!D107 -> ECS Europe & Central Asia | E103: ='Compound Alert'!E107 -> IDA | F103: ='Compound Alert'!F107 -> 102 | G103: =IF($B$8="Overall Alert",'Compound Alert'!G107,IF($B$8="Underlying Vulnerability",'Compound Alert'!J107,IF($B$8="Emerging Threat",'Compound Alert'!M107))) -> 0.5 | H103: =IF($B$8="Overall Alert",'Compound Alert'!H107,IF($B$8="Underlying Vulnerability",'Compound Alert'!K107,IF($B$8="Emerging Threat",'Compound Alert'!N107))) -> 0.5 | I103: =ROUNDDOWN(G103,0) -> 0 | J103: =IF( $B$8="Overall Alert",IF( 'Compound Alert'!R107 >= 7, "HIGH",IF( 'Compound Alert'!R107 >= 5, "MED","LOW")), IF( $B$8="Underlying Vulnerability", IF( 'Compound Alert'!Y107 >= 10, "HIGH",IF( 'Compound Alert'!Y107 >= 7, "MED","LOW")),IF( $B$8="Emerging Threat", IF( 'Compound Alert'!AF107 >= 10, "HIGH",IF( 'Compound Alert'!AF107 >= 7, "MED","LOW"))))) -> LOW | K103: =IF( $B$8="Overall Alert",IF( 'Compound Alert'!S107 >= 7, "HIGH",IF( 'Compound Alert'!S107 >= 5, "MED","LOW")), IF( $B$8="Underlying Vulnerability", IF( 'Compound Alert'!Z107 >= 10, "HIGH",IF( 'Compound Alert'!Z107 >= 7, "MED","LOW")),IF( $B$8="Emerging Threat", IF( 'Compound Alert'!AG107 >= 10, "HIGH",IF( 'Compound Alert'!AG107 >= 7, "MED","LOW"))))) -> LOW | L103: =IF( $B$8="Overall Alert",IF( 'Compound Alert'!T107 >= 7, "HIGH",IF( 'Compound Alert'!T107 >= 5, "MED","LOW")), IF( $B$8="Underlying Vulnerability", IF( 'Compound Alert'!AA107 >= 10, "HIGH",IF( 'Compound Alert'!AA107 >= 7, "MED","LOW")),IF( $B$8="Emerging Threat", IF( 'Compound Alert'!AH107 >= 10, "HIGH",IF( 'Compound Alert'!AH107 >= 7, "MED","LOW"))))) -> MED | M103: =IF( $B$8="Overall Alert",IF( 'Compound Alert'!U107 >= 7, "HIGH",IF( 'Compound Alert'!U107 >= 5, "MED","LOW")), IF( $B$8="Underlying Vulnerability", IF( 'Compound Alert'!AB107 >= 10, "HIGH",IF( 'Compound Alert'!AB107 >= 7, "MED","LOW")),IF( $B$8="Emerging Threat", IF( 'Compound Alert'!AI107 >= 10, "HIGH",IF( 'Compound Alert'!AI107 >= 7, "MED","LOW"))))) -> LOW | N103: =IF( $B$8="Overall Alert",IF( 'Compound Alert'!V107 >= 7, "HIGH",IF( 'Compound Alert'!V107 >= 5, "MED","LOW")), IF( $B$8="Underlying Vulnerability", IF( 'Compound Alert'!AC107 >= 10, "HIGH",IF( 'Compound Alert'!AC107 >= 7, "MED","LOW")),IF( $B$8="Emerging Threat", IF( 'Compound Alert'!AJ107 >= 10, "HIGH",IF( 'Compound Alert'!AJ107 >= 7, "MED","LOW"))))) -> LOW | O103: =IF( $B$8="Overall Alert",IF( 'Compound Alert'!W107 >= 7, "HIGH",IF( 'Compound Alert'!W107 >= 5, "MED","LOW")), IF( $B$8="Underlying Vulnerability", IF( 'Compound Alert'!AD107 >= 10, "HIGH",IF( 'Compound Alert'!AD107 >= 7, "MED","LOW")),IF( $B$8="Emerging Threat", IF( 'Compound Alert'!AK107 >= 10, "HIGH",IF( 'Compound Alert'!AK107 >= 7, "MED","LOW"))))) -> LOW
A104: 63 | B104: ='Compound Alert'!B159 -> Philippines | C104: ='Compound Alert'!C159 -> PHL | D104: ='Compound Alert'!D159 -> EAS East Asia & Pacific | E104: ='Compound Alert'!E159 -> IBRD | F104: ='Compound Alert'!F159 -> 154 | G104: =IF($B$8="Overall Alert",'Compound Alert'!G159,IF($B$8="Underlying Vulnerability",'Compound Alert'!J159,IF($B$8="Emerging Threat",'Compound Alert'!M159))) -> 1 | H104: =IF($B$8="Overall Alert",'Compound Alert'!H159,IF($B$8="Underlying Vulnerability",'Compound Alert'!K159,IF($B$8="Emerging Threat",'Compound Alert'!N159))) -> 1 | I104: =ROUNDDOWN(G104,0) -> 1 | J104: =IF( $B$8="Overall Alert",IF( 'Compound Alert'!R159 >= 7, "HIGH",IF( 'Compound Alert'!R159 >= 5, "MED","LOW")), IF( $B$8="Underlying Vulnerability", IF( 'Compound Alert'!Y159 >= 10, "HIGH",IF( 'Compound Alert'!Y159 >= 7, "MED","LOW")),IF( $B$8="Emerging Threat", IF( 'Compound Alert'!AF159 >= 10, "HIGH",IF( 'Compound Alert'!AF159 >= 7, "MED","LOW"))))) -> LOW | K104: =IF( $B$8="Overall Alert",IF( 'Compound Alert'!S159 >= 7, "HIGH",IF( 'Compound Alert'!S159 >= 5, "MED","LOW")), IF( $B$8="Underlying Vulnerability", IF( 'Compound Alert'!Z159 >= 10, "HIGH",IF( 'Compound Alert'!Z159 >= 7, "MED","LOW")),IF( $B$8="Emerging Threat", IF( 'Compound Alert'!AG159 >= 10, "HIGH",IF( 'Compound Alert'!AG159 >= 7, "MED","LOW"))))) -> LOW | L104: =IF( $B$8="Overall Alert",IF( 'Compound Alert'!T159 >= 7, "HIGH",IF( 'Compound Alert'!T159 >= 5, "MED","LOW")), IF( $B$8="Underlying Vulnerability", IF( 'Compound Alert'!AA159 >= 10, "HIGH",IF( 'Compound Alert'!AA159 >= 7, "MED","LOW")),IF( $B$8="Emerging Threat", IF( 'Compound Alert'!AH159 >= 10, "HIGH",IF( 'Compound Alert'!AH159 >= 7, "MED","LOW"))))) -> LOW | M104: =IF( $B$8="Overall Alert",IF( 'Compound Alert'!U159 >= 7, "HIGH",IF( 'Compound Alert'!U159 >= 5, "MED","LOW")), IF( $B$8="Underlying Vulnerability", IF( 'Compound Alert'!AB159 >= 10, "HIGH",IF( 'Compound Alert'!AB159 >= 7, "MED","LOW")),IF( $B$8="Emerging Threat", IF( 'Compound Alert'!AI159 >= 10, "HIGH",IF( 'Compound Alert'!AI159 >= 7, "MED","LOW"))))) -> LOW | N104: =IF( $B$8="Overall Alert",IF( 'Compound Alert'!V159 >= 7, "HIGH",IF( 'Compound Alert'!V159 >= 5, "MED","LOW")), IF( $B$8="Underlying Vulnerability", IF( 'Compound Alert'!AC159 >= 10, "HIGH",IF( 'Compound Alert'!AC159 >= 7, "MED","LOW")),IF( $B$8="Emerging Threat", IF( 'Compound Alert'!AJ159 >= 10, "HIGH",IF( 'Compound Alert'!AJ159 >= 7, "MED","LOW"))))) -> HIGH | O104: =IF( $B$8="Overall Alert",IF( 'Compound Alert'!W159 >= 7, "HIGH",IF( 'Compound Alert'!W159 >= 5, "MED","LOW")), IF( $B$8="Underlying Vulnerability", IF( 'Compound Alert'!AD159 >= 10, "HIGH",IF( 'Compound Alert'!AD159 >= 7, "MED","LOW")),IF( $B$8="Emerging Threat", IF( 'Compound Alert'!AK159 >= 10, "HIGH",IF( 'Compound Alert'!AK159 >= 7, "MED","LOW"))))) -> LOW
A105: 64 | B105: ='Compound Alert'!B115 -> Liberia | C105: ='Compound Alert'!C115 -> LBR | D105: ='Compound Alert'!D115 -> SSF Sub-Saharan Africa | E105: ='Compound Alert'!E115 -> IDA | F105: ='Compound Alert'!F115 -> 110 | G105: =IF($B$8="Overall Alert",'Compound Alert'!G115,IF($B$8="Underlying Vulnerability",'Compound Alert'!J115,IF($B$8="Emerging Threat",'Compound Alert'!M115))) -> 0.5 | H105: =IF($B$8="Overall Alert",'Compound Alert'!H115,IF($B$8="Underlying Vulnerability",'Compound Alert'!K115,IF($B$8="Emerging Threat",'Compound Alert'!N115))) -> 0.5 | I105: =ROUNDDOWN(G105,0) -> 0 | J105: =IF( $B$8="Overall Alert",IF( 'Compound Alert'!R115 >= 7, "HIGH",IF( 'Compound Alert'!R115 >= 5, "MED","LOW")), IF( $B$8="Underlying Vulnerability", IF( 'Compound Alert'!Y115 >= 10, "HIGH",IF( 'Compound Alert'!Y115 >= 7, "MED","LOW")),IF( $B$8="Emerging Threat", IF( 'Compound Alert'!AF115 >= 10, "HIGH",IF( 'Compound Alert'!AF115 >= 7, "MED","LOW"))))) -> LOW | K105: =IF( $B$8="Overall Alert",IF( 'Compound Alert'!S115 >= 7, "HIGH",IF( 'Compound Alert'!S115 >= 5, "MED","LOW")), IF( $B$8="Underlying Vulnerability", IF( 'Compound Alert'!Z115 >= 10, "HIGH",IF( 'Compound Alert'!Z115 >= 7, "MED","LOW")),IF( $B$8="Emerging Threat", IF( 'Compound Alert'!AG115 >= 10, "HIGH",IF( 'Compound Alert'!AG115 >= 7, "MED","LOW"))))) -> MED | L105: =IF( $B$8="Overall Alert",IF( 'Compound Alert'!T115 >= 7, "HIGH",IF( 'Compound Alert'!T115 >= 5, "MED","LOW")), IF( $B$8="Underlying Vulnerability", IF( 'Compound Alert'!AA115 >= 10, "HIGH",IF( 'Compound Alert'!AA115 >= 7, "MED","LOW")),IF( $B$8="Emerging Threat", IF( 'Compound Alert'!AH115 >= 10, "HIGH",IF( 'Compound Alert'!AH115 >= 7, "MED","LOW"))))) -> LOW | M105: =IF( $B$8="Overall Alert",IF( 'Compound Alert'!U115 >= 7, "HIGH",IF( 'Compound Alert'!U115 >= 5, "MED","LOW")), IF( $B$8="Underlying Vulnerability", IF( 'Compound Alert'!AB115 >= 10, "HIGH",IF( 'Compound Alert'!AB115 >= 7, "MED","LOW")),IF( $B$8="Emerging Threat", IF( 'Compound Alert'!AI115 >= 10, "HIGH",IF( 'Compound Alert'!AI115 >= 7, "MED","LOW"))))) -> LOW | N105: =IF( $B$8="Overall Alert",IF( 'Compound Alert'!V115 >= 7, "HIGH",IF( 'Compound Alert'!V115 >= 5, "MED","LOW")), IF( $B$8="Underlying Vulnerability", IF( 'Compound Alert'!AC115 >= 10, "HIGH",IF( 'Compound Alert'!AC115 >= 7, "MED","LOW")),IF( $B$8="Emerging Threat", IF( 'Compound Alert'!AJ115 >= 10, "HIGH",IF( 'Compound Alert'!AJ115 >= 7, "MED","LOW"))))) -> LOW | O105: =IF( $B$8="Overall Alert",IF( 'Compound Alert'!W115 >= 7, "HIGH",IF( 'Compound Alert'!W115 >= 5, "MED","LOW")), IF( $B$8="Underlying Vulnerability", IF( 'Compound Alert'!AD115 >= 10, "HIGH",IF( 'Compound Alert'!AD115 >= 7, "MED","LOW")),IF( $B$8="Emerging Threat", IF( 'Compound Alert'!AK115 >= 10, "HIGH",IF( 'Compound Alert'!AK115 >= 7, "MED","LOW"))))) -> LOW
A106: 65 | B106: ='Compound Alert'!B116 -> Libya | C106: ='Compound Alert'!C116 -> LBY | D106: ='Compound Alert'!D116 -> MEA Middle East & North Africa | E106: ='Compound Alert'!E116 -> IBRD | F106: ='Compound Alert'!F116 -> 111 | G106: =IF($B$8="Overall Alert",'Compound Alert'!G116,IF($B$8="Underlying Vulnerability",'Compound Alert'!J116,IF($B$8="Emerging Threat",'Compound Alert'!M116))) -> 1.5 | H106: =IF($B$8="Overall Alert",'Compound Alert'!H116,IF($B$8="Underlying Vulnerability",'Compound Alert'!K116,IF($B$8="Emerging Threat",'Compound Alert'!N116))) -> 1.5 | I106: =ROUNDDOWN(G106,0) -> 1 | J106: =IF( $B$8="Overall Alert",IF( 'Compound Alert'!R116 >= 7, "HIGH",IF( 'Compound Alert'!R116 >= 5, "MED","LOW")), IF( $B$8="Underlying Vulnerability", IF( 'Compound Alert'!Y116 >= 10, "HIGH",IF( 'Compound Alert'!Y116 >= 7, "MED","LOW")),IF( $B$8="Emerging Threat", IF( 'Compound Alert'!AF116 >= 10, "HIGH",IF( 'Compound Alert'!AF116 >= 7, "MED","LOW"))))) -> LOW | K106: =IF( $B$8="Overall Alert",IF( 'Compound Alert'!S116 >= 7, "HIGH",IF( 'Compound Alert'!S116 >= 5, "MED","LOW")), IF( $B$8="Underlying Vulnerability", IF( 'Compound Alert'!Z116 >= 10, "HIGH",IF( 'Compound Alert'!Z116 >= 7, "MED","LOW")),IF( $B$8="Emerging Threat", IF( 'Compound Alert'!AG116 >= 10, "HIGH",IF( 'Compound Alert'!AG116 >= 7, "MED","LOW"))))) -> LOW | L106: =IF( $B$8="Overall Alert",IF( 'Compound Alert'!T116 >= 7, "HIGH",IF( 'Compound Alert'!T116 >= 5, "MED","LOW")), IF( $B$8="Underlying Vulnerability", IF( 'Compound Alert'!AA116 >= 10, "HIGH",IF( 'Compound Alert'!AA116 >= 7, "MED","LOW")),IF( $B$8="Emerging Threat", IF( 'Compound Alert'!AH116 >= 10, "HIGH",IF( 'Compound Alert'!AH116 >= 7, "MED","LOW"))))) -> HIGH | M106: =IF( $B$8="Overall Alert",IF( 'Compound Alert'!U116 >= 7, "HIGH",IF( 'Compound Alert'!U116 >= 5, "MED","LOW")), IF( $B$8="Underlying Vulnerability", IF( 'Compound Alert'!AB116 >= 10, "HIGH",IF( 'Compound Alert'!AB116 >= 7, "MED","LOW")),IF( $B$8="Emerging Threat", IF( 'Compound Alert'!AI116 >= 10, "HIGH",IF( 'Compound Alert'!AI116 >= 7, "MED","LOW"))))) -> LOW | N106: =IF( $B$8="Overall Alert",IF( 'Compound Alert'!V116 >= 7, "HIGH",IF( 'Compound Alert'!V116 >= 5, "MED","LOW")), IF( $B$8="Underlying Vulnerability", IF( 'Compound Alert'!AC116 >= 10, "HIGH",IF( 'Compound Alert'!AC116 >= 7, "MED","LOW")),IF( $B$8="Emerging Threat", IF( 'Compound Alert'!AJ116 >= 10, "HIGH",IF( 'Compound Alert'!AJ116 >= 7, "MED","LOW"))))) -> LOW | O106: =IF( $B$8="Overall Alert",IF( 'Compound Alert'!W116 >= 7, "HIGH",IF( 'Compound Alert'!W116 >= 5, "MED","LOW")), IF( $B$8="Underlying Vulnerability", IF( 'Compound Alert'!AD116 >= 10, "HIGH",IF( 'Compound Alert'!AD116 >= 7, "MED","LOW")),IF( $B$8="Emerging Threat", IF( 'Compound Alert'!AK116 >= 10, "HIGH",IF( 'Compound Alert'!AK116 >= 7, "MED","LOW"))))) -> MED
A107: 66 | B107: ='Compound Alert'!B113 -> Lao PDR | C107: ='Compound Alert'!C113 -> LAO | D107: ='Compound Alert'!D113 -> EAS East Asia & Pacific | E107: ='Compound Alert'!E113 -> IDA | F107: ='Compound Alert'!F113 -> 108 | G107: =IF($B$8="Overall Alert",'Compound Alert'!G113,IF($B$8="Underlying Vulnerability",'Compound Alert'!J113,IF($B$8="Emerging Threat",'Compound Alert'!M113))) -> 1.5 | H107: =IF($B$8="Overall Alert",'Compound Alert'!H113,IF($B$8="Underlying Vulnerability",'Compound Alert'!K113,IF($B$8="Emerging Threat",'Compound Alert'!N113))) -> 1.5 | I107: =ROUNDDOWN(G107,0) -> 1 | J107: =IF( $B$8="Overall Alert",IF( 'Compound Alert'!R113 >= 7, "HIGH",IF( 'Compound Alert'!R113 >= 5, "MED","LOW")), IF( $B$8="Underlying Vulnerability", IF( 'Compound Alert'!Y113 >= 10, "HIGH",IF( 'Compound Alert'!Y113 >= 7, "MED","LOW")),IF( $B$8="Emerging Threat", IF( 'Compound Alert'!AF113 >= 10, "HIGH",IF( 'Compound Alert'!AF113 >= 7, "MED","LOW"))))) -> LOW | K107: =IF( $B$8="Overall Alert",IF( 'Compound Alert'!S113 >= 7, "HIGH",IF( 'Compound Alert'!S113 >= 5, "MED","LOW")), IF( $B$8="Underlying Vulnerability", IF( 'Compound Alert'!Z113 >= 10, "HIGH",IF( 'Compound Alert'!Z113 >= 7, "MED","LOW")),IF( $B$8="Emerging Threat", IF( 'Compound Alert'!AG113 >= 10, "HIGH",IF( 'Compound Alert'!AG113 >= 7, "MED","LOW"))))) -> MED | L107: =IF( $B$8="Overall Alert",IF( 'Compound Alert'!T113 >= 7, "HIGH",IF( 'Compound Alert'!T113 >= 5, "MED","LOW")), IF( $B$8="Underlying Vulnerability", IF( 'Compound Alert'!AA113 >= 10, "HIGH",IF( 'Compound Alert'!AA113 >= 7, "MED","LOW")),IF( $B$8="Emerging Threat", IF( 'Compound Alert'!AH113 >= 10, "HIGH",IF( 'Compound Alert'!AH113 >= 7, "MED","LOW"))))) -> MED | M107: =IF( $B$8="Overall Alert",IF( 'Compound Alert'!U113 >= 7, "HIGH",IF( 'Compound Alert'!U113 >= 5, "MED","LOW")), IF( $B$8="Underlying Vulnerability", IF( 'Compound Alert'!AB113 >= 10, "HIGH",IF( 'Compound Alert'!AB113 >= 7, "MED","LOW")),IF( $B$8="Emerging Threat", IF( 'Compound Alert'!AI113 >= 10, "HIGH",IF( 'Compound Alert'!AI113 >= 7, "MED","LOW"))))) -> LOW | N107: =IF( $B$8="Overall Alert",IF( 'Compound Alert'!V113 >= 7, "HIGH",IF( 'Compound Alert'!V113 >= 5, "MED","LOW")), IF( $B$8="Underlying Vulnerability", IF( 'Compound Alert'!AC113 >= 10, "HIGH",IF( 'Compound Alert'!AC113 >= 7, "MED","LOW")),IF( $B$8="Emerging Threat", IF( 'Compound Alert'!AJ113 >= 10, "HIGH",IF( 'Compound Alert'!AJ113 >= 7, "MED","LOW"))))) -> MED | O107: =IF( $B$8="Overall Alert",IF( 'Compound Alert'!W113 >= 7, "HIGH",IF( 'Compound Alert'!W113 >= 5, "MED","LOW")), IF( $B$8="Underlying Vulnerability", IF( 'Compound Alert'!AD113 >= 10, "HIGH",IF( 'Compound Alert'!AD113 >= 7, "MED","LOW")),IF( $B$8="Emerging Threat", IF( 'Compound Alert'!AK113 >= 10, "HIGH",IF( 'Compound Alert'!AK113 >= 7, "MED","LOW"))))) -> LOW
A108: 67 | B108: ='Compound Alert'!B12 -> Argentina | C108: ='Compound Alert'!C12 -> ARG | D108: ='Compound Alert'!D12 -> LCN Latin America & Caribbean | E108: ='Compound Alert'!E12 -> IBRD | F108: ='Compound Alert'!F12 -> 7 | G108: =IF($B$8="Overall Alert",'Compound Alert'!G12,IF($B$8="Underlying Vulnerability",'Compound Alert'!J12,IF($B$8="Emerging Threat",'Compound Alert'!M12))) -> 0.5 | H108: =IF($B$8="Overall Alert",'Compound Alert'!H12,IF($B$8="Underlying Vulnerability",'Compound Alert'!K12,IF($B$8="Emerging Threat",'Compound Alert'!N12))) -> 0.5 | I108: =ROUNDDOWN(G108,0) -> 0 | J108: =IF( $B$8="Overall Alert",IF( 'Compound Alert'!R12 >= 7, "HIGH",IF( 'Compound Alert'!R12 >= 5, "MED","LOW")), IF( $B$8="Underlying Vulnerability", IF( 'Compound Alert'!Y12 >= 10, "HIGH",IF( 'Compound Alert'!Y12 >= 7, "MED","LOW")),IF( $B$8="Emerging Threat", IF( 'Compound Alert'!AF12 >= 10, "HIGH",IF( 'Compound Alert'!AF12 >= 7, "MED","LOW"))))) -> LOW | K108: =IF( $B$8="Overall Alert",IF( 'Compound Alert'!S12 >= 7, "HIGH",IF( 'Compound Alert'!S12 >= 5, "MED","LOW")), IF( $B$8="Underlying Vulnerability", IF( 'Compound Alert'!Z12 >= 10, "HIGH",IF( 'Compound Alert'!Z12 >= 7, "MED","LOW")),IF( $B$8="Emerging Threat", IF( 'Compound Alert'!AG12 >= 10, "HIGH",IF( 'Compound Alert'!AG12 >= 7, "MED","LOW"))))) -> LOW | L108: =IF( $B$8="Overall Alert",IF( 'Compound Alert'!T12 >= 7, "HIGH",IF( 'Compound Alert'!T12 >= 5, "MED","LOW")), IF( $B$8="Underlying Vulnerability", IF( 'Compound Alert'!AA12 >= 10, "HIGH",IF( 'Compound Alert'!AA12 >= 7, "MED","LOW")),IF( $B$8="Emerging Threat", IF( 'Compound Alert'!AH12 >= 10, "HIGH",IF( 'Compound Alert'!AH12 >= 7, "MED","LOW"))))) -> MED | M108: =IF( $B$8="Overall Alert",IF( 'Compound Alert'!U12 >= 7, "HIGH",IF( 'Compound Alert'!U12 >= 5, "MED","LOW")), IF( $B$8="Underlying Vulnerability", IF( 'Compound Alert'!AB12 >= 10, "HIGH",IF( 'Compound Alert'!AB12 >= 7, "MED","LOW")),IF( $B$8="Emerging Threat", IF( 'Compound Alert'!AI12 >= 10, "HIGH",IF( 'Compound Alert'!AI12 >= 7, "MED","LOW"))))) -> LOW | N108: =IF( $B$8="Overall Alert",IF( 'Compound Alert'!V12 >= 7, "HIGH",IF( 'Compound Alert'!V12 >= 5, "MED","LOW")), IF( $B$8="Underlying Vulnerability", IF( 'Compound Alert'!AC12 >= 10, "HIGH",IF( 'Compound Alert'!AC12 >= 7, "MED","LOW")),IF( $B$8="Emerging Threat", IF( 'Compound Alert'!AJ12 >= 10, "HIGH",IF( 'Compound Alert'!AJ12 >= 7, "MED","LOW"))))) -> LOW | O108: =IF( $B$8="Overall Alert",IF( 'Compound Alert'!W12 >= 7, "HIGH",IF( 'Compound Alert'!W12 >= 5, "MED","LOW")), IF( $B$8="Underlying Vulnerability", IF( 'Compound Alert'!AD12 >= 10, "HIGH",IF( 'Compound Alert'!AD12 >= 7, "MED","LOW")),IF( $B$8="Emerging Threat", IF( 'Compound Alert'!AK12 >= 10, "HIGH",IF( 'Compound Alert'!AK12 >= 7, "MED","LOW"))))) -> LOW
A109: 68 | B109: ='Compound Alert'!B32 -> Brazil | C109: ='Compound Alert'!C32 -> BRA | D109: ='Compound Alert'!D32 -> LCN Latin America & Caribbean | E109: ='Compound Alert'!E32 -> IBRD | F109: ='Compound Alert'!F32 -> 27 | G109: =IF($B$8="Overall Alert",'Compound Alert'!G32,IF($B$8="Underlying Vulnerability",'Compound Alert'!J32,IF($B$8="Emerging Threat",'Compound Alert'!M32))) -> 0 | H109: =IF($B$8="Overall Alert",'Compound Alert'!H32,IF($B$8="Underlying Vulnerability",'Compound Alert'!K32,IF($B$8="Emerging Threat",'Compound Alert'!N32))) -> 0 | I109: =ROUNDDOWN(G109,0) -> 0 | J109: =IF( $B$8="Overall Alert",IF( 'Compound Alert'!R32 >= 7, "HIGH",IF( 'Compound Alert'!R32 >= 5, "MED","LOW")), IF( $B$8="Underlying Vulnerability", IF( 'Compound Alert'!Y32 >= 10, "HIGH",IF( 'Compound Alert'!Y32 >= 7, "MED","LOW")),IF( $B$8="Emerging Threat", IF( 'Compound Alert'!AF32 >= 10, "HIGH",IF( 'Compound Alert'!AF32 >= 7, "MED","LOW"))))) -> LOW | K109: =IF( $B$8="Overall Alert",IF( 'Compound Alert'!S32 >= 7, "HIGH",IF( 'Compound Alert'!S32 >= 5, "MED","LOW")), IF( $B$8="Underlying Vulnerability", IF( 'Compound Alert'!Z32 >= 10, "HIGH",IF( 'Compound Alert'!Z32 >= 7, "MED","LOW")),IF( $B$8="Emerging Threat", IF( 'Compound Alert'!AG32 >= 10, "HIGH",IF( 'Compound Alert'!AG32 >= 7, "MED","LOW"))))) -> LOW | L109: =IF( $B$8="Overall Alert",IF( 'Compound Alert'!T32 >= 7, "HIGH",IF( 'Compound Alert'!T32 >= 5, "MED","LOW")), IF( $B$8="Underlying Vulnerability", IF( 'Compound Alert'!AA32 >= 10, "HIGH",IF( 'Compound Alert'!AA32 >= 7, "MED","LOW")),IF( $B$8="Emerging Threat", IF( 'Compound Alert'!AH32 >= 10, "HIGH",IF( 'Compound Alert'!AH32 >= 7, "MED","LOW"))))) -> LOW | M109: =IF( $B$8="Overall Alert",IF( 'Compound Alert'!U32 >= 7, "HIGH",IF( 'Compound Alert'!U32 >= 5, "MED","LOW")), IF( $B$8="Underlying Vulnerability", IF( 'Compound Alert'!AB32 >= 10, "HIGH",IF( 'Compound Alert'!AB32 >= 7, "MED","LOW")),IF( $B$8="Emerging Threat", IF( 'Compound Alert'!AI32 >= 10, "HIGH",IF( 'Compound Alert'!AI32 >= 7, "MED","LOW"))))) -> LOW | N109: =IF( $B$8="Overall Alert",IF( 'Compound Alert'!V32 >= 7, "HIGH",IF( 'Compound Alert'!V32 >= 5, "MED","LOW")), IF( $B$8="Underlying Vulnerability", IF( 'Compound Alert'!AC32 >= 10, "HIGH",IF( 'Compound Alert'!AC32 >= 7, "MED","LOW")),IF( $B$8="Emerging Threat", IF( 'Compound Alert'!AJ32 >= 10, "HIGH",IF( 'Compound Alert'!AJ32 >= 7, "MED","LOW"))))) -> LOW | O109: =IF( $B$8="Overall Alert",IF( 'Compound Alert'!W32 >= 7, "HIGH",IF( 'Compound Alert'!W32 >= 5, "MED","LOW")), IF( $B$8="Underlying Vulnerability", IF( 'Compound Alert'!AD32 >= 10, "HIGH",IF( 'Compound Alert'!AD32 >= 7, "MED","LOW")),IF( $B$8="Emerging Threat", IF( 'Compound Alert'!AK32 >= 10, "HIGH",IF( 'Compound Alert'!AK32 >= 7, "MED","LOW"))))) -> LOW
A110: 69 | B110: ='Compound Alert'!B108 -> Cambodia | C110: ='Compound Alert'!C108 -> KHM | D110: ='Compound Alert'!D108 -> EAS East Asia & Pacific | E110: ='Compound Alert'!E108 -> IDA | F110: ='Compound Alert'!F108 -> 103 | G110: =IF($B$8="Overall Alert",'Compound Alert'!G108,IF($B$8="Underlying Vulnerability",'Compound Alert'!J108,IF($B$8="Emerging Threat",'Compound Alert'!M108))) -> 1 | H110: =IF($B$8="Overall Alert",'Compound Alert'!H108,IF($B$8="Underlying Vulnerability",'Compound Alert'!K108,IF($B$8="Emerging Threat",'Compound Alert'!N108))) -> 1 | I110: =ROUNDDOWN(G110,0) -> 1 | J110: =IF( $B$8="Overall Alert",IF( 'Compound Alert'!R108 >= 7, "HIGH",IF( 'Compound Alert'!R108 >= 5, "MED","LOW")), IF( $B$8="Underlying Vulnerability", IF( 'Compound Alert'!Y108 >= 10, "HIGH",IF( 'Compound Alert'!Y108 >= 7, "MED","LOW")),IF( $B$8="Emerging Threat", IF( 'Compound Alert'!AF108 >= 10, "HIGH",IF( 'Compound Alert'!AF108 >= 7, "MED","LOW"))))) -> LOW | K110: =IF( $B$8="Overall Alert",IF( 'Compound Alert'!S108 >= 7, "HIGH",IF( 'Compound Alert'!S108 >= 5, "MED","LOW")), IF( $B$8="Underlying Vulnerability", IF( 'Compound Alert'!Z108 >= 10, "HIGH",IF( 'Compound Alert'!Z108 >= 7, "MED","LOW")),IF( $B$8="Emerging Threat", IF( 'Compound Alert'!AG108 >= 10, "HIGH",IF( 'Compound Alert'!AG108 >= 7, "MED","LOW"))))) -> LOW | L110: =IF( $B$8="Overall Alert",IF( 'Compound Alert'!T108 >= 7, "HIGH",IF( 'Compound Alert'!T108 >= 5, "MED","LOW")), IF( $B$8="Underlying Vulnerability", IF( 'Compound Alert'!AA108 >= 10, "HIGH",IF( 'Compound Alert'!AA108 >= 7, "MED","LOW")),IF( $B$8="Emerging Threat", IF( 'Compound Alert'!AH108 >= 10, "HIGH",IF( 'Compound Alert'!AH108 >= 7, "MED","LOW"))))) -> MED | M110: =IF( $B$8="Overall Alert",IF( 'Compound Alert'!U108 >= 7, "HIGH",IF( 'Compound Alert'!U108 >= 5, "MED","LOW")), IF( $B$8="Underlying Vulnerability", IF( 'Compound Alert'!AB108 >= 10, "HIGH",IF( 'Compound Alert'!AB108 >= 7, "MED","LOW")),IF( $B$8="Emerging Threat", IF( 'Compound Alert'!AI108 >= 10, "HIGH",IF( 'Compound Alert'!AI108 >= 7, "MED","LOW"))))) -> LOW | N110: =IF( $B$8="Overall Alert",IF( 'Compound Alert'!V108 >= 7, "HIGH",IF( 'Compound Alert'!V108 >= 5, "MED","LOW")), IF( $B$8="Underlying Vulnerability", IF( 'Compound Alert'!AC108 >= 10, "HIGH",IF( 'Compound Alert'!AC108 >= 7, "MED","LOW")),IF( $B$8="Emerging Threat", IF( 'Compound Alert'!AJ108 >= 10, "HIGH",IF( 'Compound Alert'!AJ108 >= 7, "MED","LOW"))))) -> LOW | O110: =IF( $B$8="Overall Alert",IF( 'Compound Alert'!W108 >= 7, "HIGH",IF( 'Compound Alert'!W108 >= 5, "MED","LOW")), IF( $B$8="Underlying Vulnerability", IF( 'Compound Alert'!AD108 >= 10, "HIGH",IF( 'Compound Alert'!AD108 >= 7, "MED","LOW")),IF( $B$8="Emerging Threat", IF( 'Compound Alert'!AK108 >= 10, "HIGH",IF( 'Compound Alert'!AK108 >= 7, "MED","LOW"))))) -> MED
A111: 70 | B111: ='Compound Alert'!B41 -> Chile | C111: ='Compound Alert'!C41 -> CHL | D111: ='Compound Alert'!D41 -> LCN Latin America & Caribbean | E111: ='Compound Alert'!E41 -> IBRD | F111: ='Compound Alert'!F41 -> 36 | G111: =IF($B$8="Overall Alert",'Compound Alert'!G41,IF($B$8="Underlying Vulnerability",'Compound Alert'!J41,IF($B$8="Emerging Threat",'Compound Alert'!M41))) -> 1.5 | H111: =IF($B$8="Overall Alert",'Compound Alert'!H41,IF($B$8="Underlying Vulnerability",'Compound Alert'!K41,IF($B$8="Emerging Threat",'Compound Alert'!N41))) -> 1.5 | I111: =ROUNDDOWN(G111,0) -> 1 | J111: =IF( $B$8="Overall Alert",IF( 'Compound Alert'!R41 >= 7, "HIGH",IF( 'Compound Alert'!R41 >= 5, "MED","LOW")), IF( $B$8="Underlying Vulnerability", IF( 'Compound Alert'!Y41 >= 10, "HIGH",IF( 'Compound Alert'!Y41 >= 7, "MED","LOW")),IF( $B$8="Emerging Threat", IF( 'Compound Alert'!AF41 >= 10, "HIGH",IF( 'Compound Alert'!AF41 >= 7, "MED","LOW"))))) -> LOW | K111: =IF( $B$8="Overall Alert",IF( 'Compound Alert'!S41 >= 7, "HIGH",IF( 'Compound Alert'!S41 >= 5, "MED","LOW")), IF( $B$8="Underlying Vulnerability", IF( 'Compound Alert'!Z41 >= 10, "HIGH",IF( 'Compound Alert'!Z41 >= 7, "MED","LOW")),IF( $B$8="Emerging Threat", IF( 'Compound Alert'!AG41 >= 10, "HIGH",IF( 'Compound Alert'!AG41 >= 7, "MED","LOW"))))) -> LOW | L111: =IF( $B$8="Overall Alert",IF( 'Compound Alert'!T41 >= 7, "HIGH",IF( 'Compound Alert'!T41 >= 5, "MED","LOW")), IF( $B$8="Underlying Vulnerability", IF( 'Compound Alert'!AA41 >= 10, "HIGH",IF( 'Compound Alert'!AA41 >= 7, "MED","LOW")),IF( $B$8="Emerging Threat", IF( 'Compound Alert'!AH41 >= 10, "HIGH",IF( 'Compound Alert'!AH41 >= 7, "MED","LOW"))))) -> MED | M111: =IF( $B$8="Overall Alert",IF( 'Compound Alert'!U41 >= 7, "HIGH",IF( 'Compound Alert'!U41 >= 5, "MED","LOW")), IF( $B$8="Underlying Vulnerability", IF( 'Compound Alert'!AB41 >= 10, "HIGH",IF( 'Compound Alert'!AB41 >= 7, "MED","LOW")),IF( $B$8="Emerging Threat", IF( 'Compound Alert'!AI41 >= 10, "HIGH",IF( 'Compound Alert'!AI41 >= 7, "MED","LOW"))))) -> LOW | N111: =IF( $B$8="Overall Alert",IF( 'Compound Alert'!V41 >= 7, "HIGH",IF( 'Compound Alert'!V41 >= 5, "MED","LOW")), IF( $B$8="Underlying Vulnerability", IF( 'Compound Alert'!AC41 >= 10, "HIGH",IF( 'Compound Alert'!AC41 >= 7, "MED","LOW")),IF( $B$8="Emerging Threat", IF( 'Compound Alert'!AJ41 >= 10, "HIGH",IF( 'Compound Alert'!AJ41 >= 7, "MED","LOW"))))) -> HIGH | O111: =IF( $B$8="Overall Alert",IF( 'Compound Alert'!W41 >= 7, "HIGH",IF( 'Compound Alert'!W41 >= 5, "MED","LOW")), IF( $B$8="Underlying Vulnerability", IF( 'Compound Alert'!AD41 >= 10, "HIGH",IF( 'Compound Alert'!AD41 >= 7, "MED","LOW")),IF( $B$8="Emerging Threat", IF( 'Compound Alert'!AK41 >= 10, "HIGH",IF( 'Compound Alert'!AK41 >= 7, "MED","LOW"))))) -> LOW
